Workbook

Sheet PMMOQP

Sheet 封面
B1: 索引页
C4: 资 产 评 估 申 报 表
D5: 企业填写以下内容
D7: 被评估单位： | Q7: 评估对象是企业整体资产时，为被评估企业，评估对象是单项资产时，为产权持有单位
D9: 评估基准日： | G9: 年 | I9: 月 | K9: 日
D11: 被评估单位填表人： | Q11: 同第一行
D13: 填表日期： | G13: 年 | I13: 月 | K13: 日
D15: 评估机构填写以下内容
D16: 项目负责人：
D18: 签字注册资产评估师：
D20: 流动资产评估人员：
D22: 长期投资评估人员：
D24: 房 屋 类评估人员：
D26: 设 备 类评估人员：
D28: 土 地评估人员：
D30: 生物资产评估人员：
D32: 油气资产评估人员：
D34: 其他无形评估人员：
D36: 其他资产评估人员：
D38: 负 债类评估人员：

Sheet 索引目录
A1: 资产评估申报表索引目录
B2: 评估申报表封面
B3: 评估申报表说明（填表前请先阅读）
B4: 基本情况表 | C4: 资产负债表 | D4: 汇总表 | E4: 分类汇总表
C6: 流动资产 | D6: 货币资金 | E6: 现金 | G6: 流动负债 | I6: 短期借款
E7: 银行存款 | I7: 交易性金融负债
E8: 其他货币资金 | I8: 应付票据
D9: 交易性金融资产 | E9: 股票投资 | I9: 应付账款
E10: 债券投资 | I10: 预收款项
E11: 基金投资 | I11: 应付职工薪酬
D12: 应收票据 | I12: 应交税费
D13: 应收账款 | I13: 应付利息
D14: 预付账款 | I14: 应付股利（应付利润）
D15: 应收利息 | I15: 其他应付款
D16: 应收股利 | I16: 一年内到期的非流动负债
D17: 其他应收款 | I17: 其他流动负债
D18: 存货 | E18: 材料采购（在途物资）
E19: 原材料
E20: 在库周转材料 | G20: 非流动负债 | I20: 长期借款
E21: 委托加工物资 | I21: 应付债券
E22: 产成品（库存商品） | I22: 长期应付款
E23: 在产品（自制半成品） | I23: 专项应付款
E24: 发出商品 | I24: 预计负债
E25: 在用周转材料 | I25: 递延所得税负债
D26: 一年到期非流动资产 | I26: 其他非流动负债
D27: 其他流动资产
C28: 长期投资 | D28: 可供出售金融资产 | E28: 股票投资
E29: 债券投资
E30: 其他投资
D31: 持有至到期投资
D32: 长期应收款
D33: 长期股权投资
D34: 投资性房地产
C35: 固定资产 | D35: 固定资产 | E35: 房屋建筑物
E36: 构筑物及其他辅助设施
E37: 管道及沟槽
E38: 机器设备
E39: 车辆
E40: 电子设备
E41: 土地
D42: 在建工程 | E42: 在建工程-土建工程
E43: 在建工程-设备安装工程
D44: 工程物资
D45: 固定资产清理
D46: 生产性生物资产
D47: 油气资产
C48: 无形资产 | D48: 无形资产 | E48: 土地使用权
E49: 其他无形资产
D50: 开发支出
D51: 商誉
C52: 其他资产 | D52: 长期待摊费用
D53: 递延所得税资产
D54: 其他非流动资产

Sheet 填表说明
A1: 评估申报表填表说明
A2: 返回索引页
A3: 1、 | B3: 本工作簿用于资产评估委托方或资产占有方对评估基准日下的委估资产及负债的账面价值的申报；
B4: 请贵单位填表人员按要求对工作表中账面价值及其以左各栏次或项目据实填写
B5: （此外，应收账款、其他应收款还需要填写账龄分析内容）；
A6: 2、 | B6: 此表各科目明细的合计数，应与本次资产评估范围内的资产评估基准日的资产负债表的数据相符；
A7: 3、 | B7: 如有债权、债务性资产的未达、坏账及实物性资产的毁损、报废等的项目应在其备注中说明；
A8: 4、 | B8: 明细表中如有日期档，除各明细表中有具体要求外，其格式应为“XXXX-XX”；
B9: 例：“2000年09月10日”应填为“2000-09”
B10: 如无法确定具体月份，请将月份填为01月；
B11: 例：“2000年”应填为“2000-01”
B12: 如为累计发生的业务，请将发生日期填为最后一笔业务的发生日期；
A13: 5、 | B13: 如明细表的行数不够时，请填表人员在“合计”的上两行进行插入行。
A14: 6、 | B14: 填表人可通过“资产评估申报表索引目录”来选择要查看或修改的科目,通过“返回索引页”按纽可返回“选择目录”
A15: 7、 | B15: 填表人可通过点击各汇总表中的“科目名称”进入各明细表，再通过点击各工作表左上角的“返回”来返回上一级汇总表。
A16: 注： | B16: 除以上要求企业填写的或按具体情况评估人员另作要求填写的栏目或项外，企业不应对此套表的其它部分
B17: 作任何修改变动，谢谢合作！
A19: 核心提示：不适用的工作表可以隐藏，但不可删除！
C20: 工作表标签不能更改！
B22: 如有疑问请与我公司项目组或我公司现场人员联系
B23: 公司电话：010-68365066 传真：010-68365038

Sheet 资产负债表
A1: 返回索引页
A2: 资产负债表
A3: =CONCATENATE(封面!F9,封面!G9,封面!H9,封面!I9,封面!J9,封面!K9)
A4: ="编制单位:"&封面!F7 | J4: 金额单位：人民币元
A5: 资产 | B5: 序号 | C5: 期初数 | D5: 期末数 | E5: 备注 | F5: 负债及所有者权益 | G5: 序号 | H5: 期初数 | I5: 期末数 | J5: 备注
A6: 流动资产： | B6: 1 | F6: 流动负债： | G6: 34
A7: 货币资金 | B7: 2 | F7: 短期借款 | G7: 35
A8: 交易性金融资产 | B8: 3 | F8: 交易性金融负债 | G8: 36
A9: 应收票据 | B9: 4 | F9: 应付票据 | G9: 37
A10: 应收账款 | B10: 5 | F10: 应付账款 | G10: 38
A11: 预付款项 | B11: 6 | F11: 预收款项 | G11: 39
A12: 应收利息 | B12: 7 | F12: 应付职工薪酬 | G12: 40
A13: 应收股利 | B13: 8 | F13: 应交税费 | G13: 41
A14: 其他应收款 | B14: 9 | F14: 应付利息 | G14: 42
A15: 存货 | B15: 10 | F15: 应付股利 | G15: 43
A16: 一年内到期的非流动资产 | B16: 11 | F16: 其他应付款 | G16: 44
A17: 其他流动资产 | B17: 12 | F17: 一年内到期的非流动负债 | G17: 45
A18: 流动资产合计 | B18: 13 | C18: =SUM(C7:C17) | D18: =SUM(D7:D17) | F18: 其他流动负债 | G18: 46
A19: 非流动资产： | B19: 14 | F19: 流动负债合计 | G19: 47 | H19: =SUM(H7:H18) | I19: =SUM(I7:I18)
A20: 可供出售金融资产 | B20: 15 | F20: 非流动负债： | G20: 48
A21: 持有至到期投资 | B21: 16 | F21: 长期借款 | G21: 49
A22: 长期应收款 | B22: 17 | F22: 应付债券 | G22: 50
A23: 长期股权投资 | B23: 18 | C23: =D23 | F23: 长期应付款 | G23: 51
A24: 投资性房地产 | B24: 19 | F24: 专项应付款 | G24: 52
A25: 固定资产 | B25: 20 | F25: 预计负债 | G25: 53
A26: 在建工程 | B26: 21 | F26: 递延所得税负债 | G26: 54
A27: 工程物资 | B27: 22 | F27: 其他非流动负债 | G27: 55
A28: 固定资产清理 | B28: 23 | F28: 非流动负债合计 | G28: 56 | H28: =SUM(H21:H27) | I28: =SUM(I21:I27)
A29: 生产性生物资产 | B29: 24 | F29: 负债合计 | G29: 57 | H29: =H19+H28 | I29: =I19+I28
A30: 油气资产 | B30: 25 | F30: 所有者权益： | G30: 58
A31: 无形资产 | B31: 26 | F31: 实收资本 | G31: 59 | I31: =H31
A32: 开发支出 | B32: 27 | F32: 资本公积 | G32: 60 | I32: =H32
A33: 商誉 | B33: 28 | F33: 减：库存股 | G33: 61
A34: 长期待摊费用 | B34: 29 | F34: 盈余公积 | G34: 62
A35: 递延所得税资产 | B35: 30 | F35: 未分配利润 | G35: 63
A36: 其他非流动资产 | B36: 31 | F36: 所有者权益合计 | G36: 64 | H36: =SUM(H31,H32,H34,H35) | I36: =SUM(I31,I32,I34,I35)
A37: 非流动资产合计 | B37: 32 | C37: =SUM(C20:C36) | D37: =SUM(D20:D36)
A38: 资产总计 | B38: 33 | C38: =SUM(C37,C18) | D38: =SUM(D37,D18) | F38: 负债及所有者权益合计 | G38: 65 | H38: =H29+H36 | I38: =I29+I36
F39: 与总资产相差 | G39: 66 | H39: =H38-C38 | I39: =I38-D38
C40: 填表人： | E40: 财务主管： | H40: 负责人：

Sheet 汇总表
A1: 返回索引页
A2: 资 产 评 估 结 果 汇 总 表
A3: =CONCATENATE(封面!D9,封面!F9,封面!G9,封面!H9,封面!I9,封面!J9,封面!K9)
A4: =封面!D7&封面!F7 | G4: 金额单位：人民币元
A5: 项 目 | C5: 审计前账面值 | D5: 账面价值 | E5: 评估价值 | F5: 增减值 | G5: 增值率％
C6: A | D6: B | E6: C | F6: D=C-B | G6: E=D/B×100%
A7: 1 | B7: 流动资产 | C7: =分类汇总!C6/10000 | D7: =分类汇总!E6/10000 | E7: =分类汇总!F6/10000 | F7: =E7-D7 | G7: =IF(D7=0,"",F7/ABS(D7)*100)
A8: 2 | B8: 非流动资产 | C8: =分类汇总!C19/10000 | D8: =分类汇总!E19/10000 | E8: =分类汇总!F19/10000 | F8: =E8-D8 | G8: =IF(D8=0,"",F8/ABS(D8)*100)
B9: 可供出售金融资产 | C9: =分类汇总!C20/10000 | D9: =分类汇总!E20/10000 | E9: =分类汇总!F20/10000 | F9: =E9-D9 | G9: =IF(D9=0,"",F9/ABS(D9)*100)
B10: 持有至到期投资 | C10: =分类汇总!C21/10000 | D10: =分类汇总!E21/10000 | E10: =分类汇总!F21/10000 | F10: =E10-D10 | G10: =IF(D10=0,"",F10/ABS(D10)*100)
A11: 3 | B11: 其中：长期应收款 | C11: =分类汇总!C22/10000 | D11: =分类汇总!E22/10000 | E11: =分类汇总!F22/10000 | F11: =E11-D11 | G11: =IF(D11=0,"",F11/ABS(D11)*100)
A12: 4 | B12: 长期股权投资 | C12: =分类汇总!C23/10000 | D12: =分类汇总!E23 | E12: =分类汇总!F23 | F12: =E12-D12 | G12: =IF(D12=0,"",F12/ABS(D12)*100)
A13: 5 | B13: 投资性房地产 | C13: =分类汇总!C24/10000 | D13: =分类汇总!E24/10000 | E13: =分类汇总!F24/10000 | F13: =E13-D13 | G13: =IF(D13=0,"",F13/ABS(D13)*100)
A14: 6 | B14: 固定资产 | C14: =分类汇总!C25/10000 | D14: =分类汇总!E25/10000 | E14: =分类汇总!F25/10000 | F14: =E14-D14 | G14: =IF(D14=0,"",F14/ABS(D14)*100)
A15: 7 | B15: 其中：建 筑 物 | C15: =固定资产汇总!D7/10000 | D15: =固定资产汇总!F7/10000 | E15: =固定资产汇总!H7/10000 | F15: =E15-D15 | G15: =IF(D15=0,"",F15/ABS(D15)*100)
A16: 8 | B16: 设 备 | C16: =固定资产汇总!D13/10000 | D16: =固定资产汇总!F13/10000 | E16: =固定资产汇总!H13/10000 | F16: =E16-D16 | G16: =IF(D16=0,"",F16/ABS(D16)*100)
A17: 9 | B17: 土 地 | C17: =固定资产汇总!D19/10000 | D17: =固定资产汇总!F19/10000 | E17: =固定资产汇总!H19/10000 | F17: =E17-D17 | G17: =IF(D17=0,"",F17/ABS(D17)*100)
A18: 7 | B18: 在建工程 | C18: =分类汇总!C26/10000 | D18: =分类汇总!E26/10000 | E18: =分类汇总!F26/10000 | F18: =E18-D18 | G18: =IF(D18=0,"",F18/ABS(D18)*100)
A19: 8 | B19: 工程物资 | C19: =分类汇总!C27/10000 | D19: =分类汇总!E27/10000 | E19: =分类汇总!F27/10000 | F19: =E19-D19 | G19: =IF(D19=0,"",F19/ABS(D19)*100)
A20: 9 | B20: 固定资产清理 | C20: =分类汇总!C28/10000 | D20: =分类汇总!E28/10000 | E20: =分类汇总!F28/10000 | F20: =E20-D20 | G20: =IF(D20=0,"",F20/ABS(D20)*100)
A21: 10 | B21: 生产性生物资产 | C21: =分类汇总!C29/10000 | D21: =分类汇总!E29/10000 | E21: =分类汇总!F29/10000 | F21: =E21-D21 | G21: =IF(D21=0,"",F21/ABS(D21)*100)
A22: 11 | B22: 油气资产 | C22: =分类汇总!C30/10000 | D22: =分类汇总!E30/10000 | E22: =分类汇总!F30/10000 | F22: =E22-D22 | G22: =IF(D22=0,"",F22/ABS(D22)*100)
A23: 12 | B23: 无形资产 | C23: =分类汇总!C31/10000 | D23: =分类汇总!E31/10000 | E23: =分类汇总!F31/10000 | F23: =E23-D23 | G23: =IF(D23=0,"",F23/ABS(D23)*100)
A24: 13 | B24: 其中：土地使用权 | C24: =无形资产汇总!C6/10000 | D24: =无形资产汇总!D6/10000 | E24: =无形资产汇总!E6/10000 | F24: =E24-D24 | G24: =IF(D24=0,"",F24/ABS(D24)*100)
A25: 17 | B25: 开发支出 | C25: =分类汇总!C32/10000 | D25: =分类汇总!E32/10000 | E25: =分类汇总!F32/10000 | F25: =E25-D25 | G25: =IF(D25=0,"",F25/ABS(D25)*100)
A26: 18 | B26: 商誉 | C26: =分类汇总!C33/10000 | D26: =分类汇总!E33/10000 | E26: =分类汇总!F33/10000 | F26: =E26-D26 | G26: =IF(D26=0,"",F26/ABS(D26)*100)
A27: 19 | B27: 长期待摊费用 | C27: =分类汇总!C34/10000 | D27: =分类汇总!E34/10000 | E27: =分类汇总!F34/10000 | F27: =E27-D27 | G27: =IF(D27=0,"",F27/ABS(D27)*100)
A28: 20 | B28: 递延所得税资产 | C28: =分类汇总!C35/10000 | D28: =分类汇总!E35/10000 | E28: =分类汇总!F35/10000 | F28: =E28-D28 | G28: =IF(D28=0,"",F28/ABS(D28)*100)
A29: 13 | B29: 其他非流动资产 | C29: =分类汇总!C36/10000 | D29: =分类汇总!E36/10000 | E29: =分类汇总!F36/10000 | F29: =E29-D29 | G29: =IF(D29=0,"",F29/ABS(D29)*100)
A30: 14 | B30: 资产总计 | C30: =SUM(C7,C8) | D30: =SUM(D7,D8) | E30: =SUM(E7,E8) | F30: =SUM(F7,F8) | G30: =IF(D30=0,"",F30/ABS(D30)*100)
A31: 15 | B31: 流动负债 | C31: =分类汇总!C39/10000 | D31: =分类汇总!E39/10000 | E31: =分类汇总!F39/10000 | F31: =E31-D31 | G31: =IF(D31=0,"",F31/ABS(D31)*100)
A32: 16 | B32: 非流动负债 | C32: =分类汇总!C53/10000 | D32: =分类汇总!E53/10000 | E32: =分类汇总!F53/10000 | F32: =E32-D32 | G32: =IF(D32=0,"",F32/ABS(D32)*100)
A33: 17 | B33: 负债总计 | C33: =SUM(C31:C32) | D33: =SUM(D31:D32) | E33: =SUM(E31:E32) | F33: =SUM(F31:F32) | G33: =IF(D33=0,"",F33/ABS(D33)*100)
A34: 18 | B34: 净 资 产（所有者权益） | C34: =C30-C33 | D34: =D30-D33 | E34: =E30-E33 | F34: =F30-F33 | G34: =IF(D34=0,"",F34/ABS(D34)*100)
E35: 评估机构：中立国际房地产土地资产评估有限公司

Sheet 分类汇总
A1: 返回索引页 | B1: 返回
A2: 资产评估结果分类汇总表
A3: =CONCATENATE(封面!D9,封面!F9,封面!G9,封面!H9,封面!I9,封面!J9,封面!K9)
A4: =封面!D7&封面!F7 | H4: 金额单位：人民币元 | J4: =IF(COUNTIF(J6:J91,">0")+COUNTIF(J6:J91,"<0")>0,"出错","OK")
A5: 序号 | B5: 科目名称 | C5: 审计前账面值 | D5: 账面调整值 | E5: 账面价值 | F5: 评估价值 | G5: 增值额 | H5: 增值率% | I5: 企业报表数 | J5: 差异
A6: 1 | B6: 一、流动资产合计 | C6: =SUM(C7:C17) | D6: =SUM(D7:D17) | E6: =SUM(E7:E17) | F6: =SUM(F7:F17) | G6: =SUM(G7:G17) | H6: =IF(E6=0,"",G6/ABS(E6)*100) | I6: =资产负债表!D18 | J6: =ROUND(E6-I6,2)
A7: 2 | B7: 货币资金 | C7: =流动汇总!E6 | D7: =E7-C7 | E7: =流动汇总!F6 | F7: =流动汇总!G6 | G7: =F7-E7 | H7: =IF(E7=0,"",G7/ABS(E7)*100) | I7: =资产负债表!D7 | J7: =ROUND(E7-I7,2)
A8: 3 | B8: 交易性金融资产 | C8: =流动汇总!E7 | D8: =E8-C8 | E8: =流动汇总!F7 | F8: =流动汇总!G7 | G8: =F8-E8 | H8: =IF(E8=0,"",G8/ABS(E8)*100) | I8: =资产负债表!D8 | J8: =ROUND(E8-I8,2)
A9: 4 | B9: 应收票据 | C9: =流动汇总!E8 | D9: =E9-C9 | E9: =流动汇总!F8 | F9: =流动汇总!G8 | G9: =F9-E9 | H9: =IF(E9=0,"",G9/ABS(E9)*100) | I9: =资产负债表!D9 | J9: =ROUND(E9-I9,2)
A10: 5 | B10: 应收账款 | C10: =流动汇总!E9 | D10: =E10-C10 | E10: =流动汇总!F9 | F10: =流动汇总!G9 | G10: =F10-E10 | H10: =IF(E10=0,"",G10/ABS(E10)*100) | I10: =资产负债表!D10 | J10: =ROUND(E10-I10,2)
A11: 6 | B11: 预付款项 | C11: =流动汇总!E10 | D11: =E11-C11 | E11: =流动汇总!F10 | F11: =流动汇总!G10 | G11: =F11-E11 | H11: =IF(E11=0,"",G11/ABS(E11)*100) | I11: =资产负债表!D11 | J11: =ROUND(E11-I11,2)
A12: 7 | B12: 应收利息 | C12: =流动汇总!E11 | D12: =E12-C12 | E12: =流动汇总!F11 | F12: =流动汇总!G11 | G12: =F12-E12 | H12: =IF(E12=0,"",G12/ABS(E12)*100) | I12: =资产负债表!D12 | J12: =ROUND(E12-I12,2)
A13: 8 | B13: 应收股利 | C13: =流动汇总!E12 | D13: =E13-C13 | E13: =流动汇总!F12 | F13: =流动汇总!G12 | G13: =F13-E13 | H13: =IF(E13=0,"",G13/ABS(E13)*100) | I13: =资产负债表!D13 | J13: =ROUND(E13-I13,2)
A14: 9 | B14: 其他应收款 | C14: =流动汇总!E13 | D14: =E14-C14 | E14: =流动汇总!F13 | F14: =流动汇总!G13 | G14: =F14-E14 | H14: =IF(E14=0,"",G14/ABS(E14)*100) | I14: =资产负债表!D14 | J14: =ROUND(E14-I14,2)
A15: 10 | B15: 存货 | C15: =流动汇总!E14 | D15: =E15-C15 | E15: =流动汇总!F14 | F15: =流动汇总!G14 | G15: =F15-E15 | H15: =IF(E15=0,"",G15/ABS(E15)*100) | I15: =资产负债表!D15 | J15: =ROUND(E15-I15,2)
A16: 11 | B16: 一年内到期的非流动资产 | C16: =流动汇总!E15 | D16: =E16-C16 | E16: =流动汇总!F15 | F16: =流动汇总!G15 | G16: =F16-E16 | H16: =IF(E16=0,"",G16/ABS(E16)*100) | I16: =资产负债表!D16 | J16: =ROUND(E16-I16,2)
A17: 12 | B17: 其他流动资产 | C17: =流动汇总!E16 | D17: =E17-C17 | E17: =流动汇总!F16 | F17: =流动汇总!G16 | G17: =F17-E17 | H17: =IF(E17=0,"",G17/ABS(E17)*100) | I17: =资产负债表!D17 | J17: =ROUND(E17-I17,2)
A18: 13 | H18: =IF(E18=0,"",G18/ABS(E18)*100) | J18: =ROUND(E18-I18,2)
A19: 14 | B19: 二、非流动资产合计 | C19: =SUM(C20:C36) | D19: =SUM(D20:D36) | E19: =SUM(E20:E36) | F19: =SUM(F20:F36) | G19: =SUM(G20:G36) | H19: =IF(E19=0,"",G19/ABS(E19)*100) | I19: =资产负债表!D37 | J19: =ROUND(E19-I19,2)
A20: 15 | B20: 可供出售金融资产 | C20: =非流动资产汇总!C6 | D20: =E20-C20 | E20: =非流动资产汇总!D6 | F20: =非流动资产汇总!E6 | G20: =F20-E20 | H20: =IF(E20=0,"",G20/ABS(E20)*100) | I20: =资产负债表!D20 | J20: =ROUND(E20-I20,2)
A21: 16 | B21: 持有至到期投资 | C21: =非流动资产汇总!C7 | D21: =E21-C21 | E21: =非流动资产汇总!D7 | F21: =非流动资产汇总!E7 | G21: =F21-E21 | H21: =IF(E21=0,"",G21/ABS(E21)*100) | I21: =资产负债表!D21 | J21: =ROUND(E21-I21,2)
A22: 17 | B22: 长期应收款 | C22: =非流动资产汇总!C8 | D22: =E22-C22 | E22: =非流动资产汇总!D8 | F22: =非流动资产汇总!E8 | G22: =F22-E22 | H22: =IF(E22=0,"",G22/ABS(E22)*100) | I22: =资产负债表!D22 | J22: =ROUND(E22-I22,2)
A23: 18 | B23: 长期股权投资 | C23: =非流动资产汇总!C9 | D23: =E23-C23 | E23: =非流动资产汇总!D9 | F23: =非流动资产汇总!E9 | G23: =F23-E23 | H23: =IF(E23=0,"",G23/ABS(E23)*100) | I23: =资产负债表!D23 | J23: =ROUND(E23-I23,2)
A24: 19 | B24: 投资性房地产 | C24: =非流动资产汇总!C10 | D24: =E24-C24 | E24: =非流动资产汇总!D10 | F24: =非流动资产汇总!E10 | G24: =F24-E24 | H24: =IF(E24=0,"",G24/ABS(E24)*100) | I24: =资产负债表!D24 | J24: =ROUND(E24-I24,2)
A25: 20 | B25: 固定资产 | C25: =非流动资产汇总!C11 | D25: =E25-C25 | E25: =非流动资产汇总!D11 | F25: =非流动资产汇总!E11 | G25: =F25-E25 | H25: =IF(E25=0,"",G25/ABS(E25)*100) | I25: =资产负债表!D25 | J25: =ROUND(E25-I25,2)
A26: 21 | B26: 在建工程 | C26: =非流动资产汇总!C12 | D26: =E26-C26 | E26: =非流动资产汇总!D12 | F26: =非流动资产汇总!E12 | G26: =F26-E26 | H26: =IF(E26=0,"",G26/ABS(E26)*100) | I26: =资产负债表!D26 | J26: =ROUND(E26-I26,2)
A27: 22 | B27: 工程物资 | C27: =非流动资产汇总!C13 | D27: =E27-C27 | E27: =非流动资产汇总!D13 | F27: =非流动资产汇总!E13 | G27: =F27-E27 | H27: =IF(E27=0,"",G27/ABS(E27)*100) | I27: =资产负债表!D27 | J27: =ROUND(E27-I27,2)
A28: 23 | B28: 固定资产清理 | C28: =非流动资产汇总!C14 | D28: =E28-C28 | E28: =非流动资产汇总!D14 | F28: =非流动资产汇总!E14 | G28: =F28-E28 | H28: =IF(E28=0,"",G28/ABS(E28)*100) | I28: =资产负债表!D28 | J28: =ROUND(E28-I28,2)
A29: 24 | B29: 生产性生物资产 | C29: =非流动资产汇总!C15 | D29: =E29-C29 | E29: =非流动资产汇总!D15 | F29: =非流动资产汇总!E15 | G29: =F29-E29 | H29: =IF(E29=0,"",G29/ABS(E29)*100) | I29: =资产负债表!D29 | J29: =ROUND(E29-I29,2)
A30: 25 | B30: 油气资产 | C30: =非流动资产汇总!C16 | D30: =E30-C30 | E30: =非流动资产汇总!D16 | F30: =非流动资产汇总!E16 | G30: =F30-E30 | H30: =IF(E30=0,"",G30/ABS(E30)*100) | I30: =资产负债表!D30 | J30: =ROUND(E30-I30,2)
A31: 26 | B31: 无形资产 | C31: =非流动资产汇总!C18 | D31: =E31-C31 | E31: =非流动资产汇总!D18 | F31: =非流动资产汇总!E18 | G31: =F31-E31 | H31: =IF(E31=0,"",G31/ABS(E31)*100) | I31: =资产负债表!D31 | J31: =ROUND(E31-I31,2)
A32: 27 | B32: 开发支出 | C32: =非流动资产汇总!C19 | D32: =E32-C32 | E32: =非流动资产汇总!D19 | F32: =非流动资产汇总!E19 | G32: =F32-E32 | H32: =IF(E32=0,"",G32/ABS(E32)*100) | I32: =资产负债表!D32 | J32: =ROUND(E32-I32,2)
A33: 28 | B33: 商誉 | C33: =非流动资产汇总!C20 | D33: =E33-C33 | E33: =非流动资产汇总!D20 | F33: =非流动资产汇总!E20 | G33: =F33-E33 | H33: =IF(E33=0,"",G33/ABS(E33)*100) | I33: =资产负债表!D33 | J33: =ROUND(E33-I33,2)
A34: 29 | B34: 长期待摊费用 | C34: =非流动资产汇总!C21 | D34: =E34-C34 | E34: =非流动资产汇总!D21 | F34: =非流动资产汇总!E21 | G34: =F34-E34 | H34: =IF(E34=0,"",G34/ABS(E34)*100) | I34: =资产负债表!D34 | J34: =ROUND(E34-I34,2)
A35: 30 | B35: 递延所得税资产 | C35: =非流动资产汇总!C22 | D35: =E35-C35 | E35: =非流动资产汇总!D22 | F35: =非流动资产汇总!E22 | G35: =F35-E35 | H35: =IF(E35=0,"",G35/ABS(E35)*100) | I35: =资产负债表!D35 | J35: =ROUND(E35-I35,2)
A36: 31 | B36: 其他非流动资产 | C36: =非流动资产汇总!C23 | D36: =E36-C36 | E36: =非流动资产汇总!D23 | F36: =非流动资产汇总!E23 | G36: =F36-E36 | H36: =IF(E36=0,"",G36/ABS(E36)*100) | I36: =资产负债表!D36 | J36: =ROUND(E36-I36,2)
A37: 32 | H37: =IF(E37=0,"",G37/ABS(E37)*100) | J37: =ROUND(E37-I37,2)
A38: 33 | B38: 三、资产总计 | C38: =SUM(C6,C19) | D38: =SUM(D6,D19) | E38: =SUM(E6,E19) | F38: =SUM(F6,F19) | G38: =SUM(G6,G19) | H38: =IF(E38=0,"",G38/ABS(E38)*100) | I38: =资产负债表!D38 | J38: =ROUND(E38-I38,2)
A39: 35 | B39: 四、流动负债合计 | C39: =SUM(C40:C51) | D39: =SUM(D40:D51) | E39: =SUM(E40:E51) | F39: =SUM(F40:F51) | G39: =SUM(G40:G51) | H39: =IF(E39=0,"",G39/ABS(E39)*100) | I39: =资产负债表!I19 | J39: =ROUND(E39-I39,2)
A40: 36 | B40: 短期借款 | C40: =流动负债汇总!C6 | D40: =E40-C40 | E40: =流动负债汇总!D6 | F40: =流动负债汇总!E6 | G40: =F40-E40 | H40: =IF(E40=0,"",G40/ABS(E40)*100) | I40: =资产负债表!I7 | J40: =ROUND(E40-I40,2)
A41: 37 | B41: 交易性金融负债 | C41: =流动负债汇总!C7 | D41: =E41-C41 | E41: =流动负债汇总!D7 | F41: =流动负债汇总!E7 | G41: =F41-E41 | H41: =IF(E41=0,"",G41/ABS(E41)*100) | I41: =资产负债表!I8 | J41: =ROUND(E41-I41,2)
A42: 38 | B42: 应付票据 | C42: =流动负债汇总!C8 | D42: =E42-C42 | E42: =流动负债汇总!D8 | F42: =流动负债汇总!E8 | G42: =F42-E42 | H42: =IF(E42=0,"",G42/ABS(E42)*100) | I42: =资产负债表!I9 | J42: =ROUND(E42-I42,2)
A43: 39 | B43: 应付账款 | C43: =流动负债汇总!C9 | D43: =E43-C43 | E43: =流动负债汇总!D9 | F43: =流动负债汇总!E9 | G43: =F43-E43 | H43: =IF(E43=0,"",G43/ABS(E43)*100) | I43: =资产负债表!I10 | J43: =ROUND(E43-I43,2)
A44: 40 | B44: 预收款项 | C44: =流动负债汇总!C10 | D44: =E44-C44 | E44: =流动负债汇总!D10 | F44: =流动负债汇总!E10 | G44: =F44-E44 | H44: =IF(E44=0,"",G44/ABS(E44)*100) | I44: =资产负债表!I11 | J44: =ROUND(E44-I44,2)
A45: 41 | B45: 应付职工薪酬 | C45: =流动负债汇总!C11 | D45: =E45-C45 | E45: =流动负债汇总!D11 | F45: =流动负债汇总!E11 | G45: =F45-E45 | H45: =IF(E45=0,"",G45/ABS(E45)*100) | I45: =资产负债表!I12 | J45: =ROUND(E45-I45,2)
A46: 42 | B46: 应交税费 | C46: =流动负债汇总!C12 | D46: =E46-C46 | E46: =流动负债汇总!D12 | F46: =流动负债汇总!E12 | G46: =F46-E46 | H46: =IF(E46=0,"",G46/ABS(E46)*100) | I46: =资产负债表!I13 | J46: =ROUND(E46-I46,2)
A47: 43 | B47: 应付利息 | C47: =流动负债汇总!C13 | D47: =E47-C47 | E47: =流动负债汇总!D13 | F47: =流动负债汇总!E13 | G47: =F47-E47 | H47: =IF(E47=0,"",G47/ABS(E47)*100) | I47: =资产负债表!I14 | J47: =ROUND(E47-I47,2)
A48: 44 | B48: 应付股利 | C48: =流动负债汇总!C14 | D48: =E48-C48 | E48: =流动负债汇总!D14 | F48: =流动负债汇总!E14 | G48: =F48-E48 | H48: =IF(E48=0,"",G48/ABS(E48)*100) | I48: =资产负债表!I15 | J48: =ROUND(E48-I48,2)
A49: 45 | B49: 其他应付款 | C49: =流动负债汇总!C15 | D49: =E49-C49 | E49: =流动负债汇总!D15 | F49: =流动负债汇总!E15 | G49: =F49-E49 | H49: =IF(E49=0,"",G49/ABS(E49)*100) | I49: =资产负债表!I16 | J49: =ROUND(E49-I49,2)
A50: 46 | B50: 一年内到期的非流动负债 | C50: =流动负债汇总!C16 | D50: =E50-C50 | E50: =流动负债汇总!D16 | F50: =流动负债汇总!E16 | G50: =F50-E50 | H50: =IF(E50=0,"",G50/ABS(E50)*100) | I50: =资产负债表!I17 | J50: =ROUND(E50-I50,2)
A51: 47 | B51: 其他流动负债 | C51: =流动负债汇总!C17 | D51: =E51-C51 | E51: =流动负债汇总!D17 | F51: =流动负债汇总!E17 | G51: =F51-E51 | H51: =IF(E51=0,"",G51/ABS(E51)*100) | I51: =资产负债表!I18 | J51: =ROUND(E51-I51,2)
A52: 48 | H52: =IF(E52=0,"",G52/ABS(E52)*100) | J52: =ROUND(E52-I52,2)
A53: 49 | B53: 五、非流动负债合计 | C53: =SUM(C54:C60) | D53: =SUM(D54:D60) | E53: =SUM(E54:E60) | F53: =SUM(F54:F60) | G53: =SUM(G54:G60) | H53: =IF(E53=0,"",G53/ABS(E53)*100) | I53: =资产负债表!I28 | J53: =ROUND(E53-I53,2)
A54: 50 | B54: 长期借款 | C54: ='非流动负债汇总 '!C6 | D54: =E54-C54 | E54: ='非流动负债汇总 '!D6 | F54: ='非流动负债汇总 '!E6 | G54: =F54-E54 | H54: =IF(E54=0,"",G54/ABS(E54)*100) | I54: =资产负债表!I21 | J54: =ROUND(E54-I54,2)
A55: 51 | B55: 应付债券 | C55: ='非流动负债汇总 '!C7 | D55: =E55-C55 | E55: ='非流动负债汇总 '!D7 | F55: ='非流动负债汇总 '!E7 | G55: =F55-E55 | H55: =IF(E55=0,"",G55/ABS(E55)*100) | I55: =资产负债表!I22 | J55: =ROUND(E55-I55,2)
A56: 52 | B56: 长期应付款 | C56: ='非流动负债汇总 '!C8 | D56: =E56-C56 | E56: ='非流动负债汇总 '!D8 | F56: ='非流动负债汇总 '!E8 | G56: =F56-E56 | H56: =IF(E56=0,"",G56/ABS(E56)*100) | I56: =资产负债表!I23 | J56: =ROUND(E56-I56,2)
A57: 53 | B57: 专项应付款 | C57: ='非流动负债汇总 '!C10 | D57: =E57-C57 | E57: ='非流动负债汇总 '!D10 | F57: ='非流动负债汇总 '!E10 | G57: =F57-E57 | H57: =IF(E57=0,"",G57/ABS(E57)*100) | I57: =资产负债表!I24 | J57: =ROUND(E57-I57,2)
A58: 54 | B58: 预计负债 | C58: ='非流动负债汇总 '!C11 | D58: =E58-C58 | E58: ='非流动负债汇总 '!D11 | F58: ='非流动负债汇总 '!E11 | G58: =F58-E58 | H58: =IF(E58=0,"",G58/ABS(E58)*100) | I58: =资产负债表!I25 | J58: =ROUND(E58-I58,2)
A59: 55 | B59: 递延所得税负债 | C59: ='非流动负债汇总 '!C12 | D59: =E59-C59 | E59: ='非流动负债汇总 '!D12 | F59: ='非流动负债汇总 '!E12 | G59: =F59-E59 | H59: =IF(E59=0,"",G59/ABS(E59)*100) | I59: =资产负债表!I26 | J59: =ROUND(E59-I59,2)
A60: 56 | B60: 其他非流动负债 | C60: ='非流动负债汇总 '!C13 | D60: =E60-C60 | E60: ='非流动负债汇总 '!D13 | F60: ='非流动负债汇总 '!E13 | G60: =F60-E60 | H60: =IF(E60=0,"",G60/ABS(E60)*100) | I60: =资产负债表!I27 | J60: =ROUND(E60-I60,2)
A61: 57 | H61: =IF(E61=0,"",G61/ABS(E61)*100) | J61: =ROUND(E61-I61,2)
A62: 58 | B62: 六、负债总计 | C62: =SUM(C39,C53) | D62: =SUM(D39,D53) | E62: =SUM(E39,E53) | F62: =SUM(F39,F53) | G62: =SUM(G39,G53) | H62: =IF(E62=0,"",G62/ABS(E62)*100) | I62: =资产负债表!I29 | J62: =ROUND(E62-I62,2)
A63: 59 | H63: =IF(E63=0,"",G63/ABS(E63)*100) | J63: =ROUND(E63-I63,2)
A64: 60 | B64: 七、净资产（所有者权益） | C64: =C38-C62 | D64: =D38-D62 | E64: =E38-E62 | F64: =F38-F62 | G64: =G38-G62 | H64: =IF(E64=0,"",G64/ABS(E64)*100) | I64: =资产负债表!I36 | J64: =ROUND(E64-I64,2)
F65: 评估机构：中立国际房地产土地资产评估有限公司
B67: 实物资产（万元） | E67: =SUM(E15,E24,E25,E26,E27,E29,E30,-固定资产汇总!F19)/10000
B68: 比例（％） | E68: =E67*10000/E38*100
A71: 资产减值准备
A72: 序号 | B72: 科目名称 | C72: 审计前账面值 | D72: 账面调整值 | E72: 账面价值 | F72: 评估价值 | G72: 增值额 | H72: 增值率% | I72: 企业报表数 | J72: 差异
A73: 一 | B73: 坏账准备 | C73: =SUM(C74:C76) | D73: =SUM(D74:D76) | E73: =SUM(E74:E76) | F73: =SUM(F74:F76) | G73: =SUM(G74:G76) | H73: =IF(E73=0,"",G73/E73*100) | I73: =SUM(I74:I76) | J73: =SUM(J74:J76)
A74: 1 | B74: 其中：应收账款 | C74: =应收账款!F25 | D74: =E74-C74 | E74: =应收账款!P25 | F74: =应收账款!Q25 | G74: =F74-E74 | H74: =IF(E74=0,"",G74/E74*100) | J74: =ROUND(C74-I74,2)
A75: 2 | B75: 其他应收款 | C75: =其他应收款!F43 | D75: =E75-C75 | E75: =其他应收款!P43 | F75: =其他应收款!Q43 | G75: =F75-E75 | H75: =IF(E75=0,"",G75/E75*100) | J75: =ROUND(C75-I75,2)
A76: 3 | B76: 长期应收款 | C76: =长期应收!E25 | D76: =E76-C76 | E76: =长期应收!G25 | F76: =长期应收!H25 | G76: =F76-E76 | H76: =IF(E76=0,"",G76/E76*100) | J76: =ROUND(C76-I76,2)
A77: 二 | B77: 存货跌价准备 | C77: =存货汇总!C26 | D77: =E77-C77 | E77: =存货汇总!D26 | F77: =存货汇总!E26 | G77: =F77-E77 | H77: =IF(E77=0,"",G77/E77*100) | J77: =ROUND(C77-I77,2)
A78: 三 | B78: 可供出售金融资产减值准备 | C78: =可供出售金融资产汇总!C26 | D78: =E78-C78 | E78: =可供出售金融资产汇总!E26 | F78: =可供出售金融资产汇总!F26 | G78: =F78-E78 | H78: =IF(E78=0,"",G78/E78*100) | J78: =ROUND(C78-I78,2)
A79: 四 | B79: 持有至到期投资减值准备 | C79: =持有到期投资!H26 | D79: =E79-C79 | E79: =持有到期投资!J26 | F79: =持有到期投资!K26 | G79: =F79-E79 | H79: =IF(E79=0,"",G79/E79*100) | J79: =ROUND(C79-I79,2)
A80: 五 | B80: 长期股权投资减值准备 | C80: =股权投资!G26 | D80: =E80-C80 | E80: =股权投资!I26 | F80: =股权投资!J26 | G80: =F80-E80 | H80: =IF(E80=0,"",G80/E80*100) | J80: =ROUND(C80-I80,2)
A81: 六 | B81: 投资性房地产减值准备 | C81: ='4-5-1投资性房地产'!K26+'4-5-3投资性地产'!M26 | D81: =E81-C81 | E81: ='4-5-1投资性房地产'!O26+'4-5-3投资性地产'!O26 | F81: ='4-5-1投资性房地产'!R26+'4-5-3投资性地产'!P26 | G81: =F81-E81 | H81: =IF(E81=0,"",G81/E81*100) | J81: =ROUND(C81-I81,2)
A82: 七 | B82: 固定资产减值准备 | C82: =固定资产汇总!D21 | D82: =E82-C82 | E82: =固定资产汇总!F21 | F82: =固定资产汇总!H21 | G82: =F82-E82 | H82: =IF(E82=0,"",G82/E82*100) | J82: =ROUND(C82-I82,2)
A83: 八 | B83: 工程物资减值准备 | C83: =工程物资!G26 | D83: =E83-C83 | E83: =工程物资!K26 | F83: =工程物资!N26 | G83: =F83-E83 | H83: =IF(E83=0,"",G83/E83*100) | J83: =ROUND(C83-I83,2)
A84: 九 | B84: 在建工程减值准备 | C84: =在建工程汇总!C26 | D84: =E84-C84 | E84: =在建工程汇总!D26 | F84: =在建工程汇总!E26 | G84: =F84-E84 | H84: =IF(E84=0,"",G84/E84*100) | J84: =ROUND(C84-I84,2)
A85: 十 | B85: 生产性生物资产减值准备 | C85: =生产性生物资产!I26 | D85: =E85-C85 | E85: =生产性生物资产!M26 | F85: =生产性生物资产!P26 | G85: =F85-E85 | H85: =IF(E85=0,"",G85/E85*100) | J85: =ROUND(C85-I85,2)
A86: 1 | B86: 其中：成熟生产性生物资产 | D86: =E86-C86 | G86: =F86-E86 | H86: =IF(E86=0,"",G86/E86*100) | J86: =ROUND(C86-I86,2)
A87: 十一 | B87: 油气资产减值准备 | C87: =油气资产!J26 | D87: =E87-C87 | E87: =油气资产!N26 | F87: =油气资产!Q26 | G87: =F87-E87 | H87: =IF(E87=0,"",G87/E87*100) | J87: =ROUND(C87-I87,2)
A88: 十二 | B88: 无形资产减值准备 | C88: =无形资产汇总!C26 | D88: =E88-C88 | E88: =无形资产汇总!D26 | F88: =无形资产汇总!E26 | G88: =F88-E88 | H88: =IF(E88=0,"",G88/E88*100) | J88: =ROUND(C88-I88,2)
A89: 十三 | B89: 商誉减值准备 | C89: =商誉!D26 | D89: =E89-C89 | E89: =商誉!F26 | F89: =商誉!G26 | G89: =F89-E89 | H89: =IF(E89=0,"",G89/E89*100) | J89: =ROUND(C89-I89,2)
A90: 十四 | B90: 其他 | D90: =E90-C90 | G90: =F90-E90 | H90: =IF(E90=0,"",G90/E90*100) | J90: =ROUND(C90-I90,2)
B91: 合计 | C91: =SUM(C73,C77:C85,C87:C90) | D91: =SUM(D73,D77:D85,D87:D90) | E91: =SUM(E73,E77:E85,E87:E90) | F91: =SUM(F73,F77:F85,F87:F90) | G91: =SUM(G73,G77:G85,G87:G90) | H91: =IF(E91=0,"",G91/E91*100) | I91: =SUM(I73,I77:I85,I87:I90) | J91: =SUM(J73,J77:J85,J87:J90)

Sheet 流动汇总
A1: 返回索引页 | B1: 返回
A2: 流动资产评估汇总表
A3: =CONCATENATE(封面!D9,封面!F9,封面!G9,封面!H9,封面!I9,封面!J9,封面!K9)
A4: =封面!D7&封面!F7 | I4: 金额单位：人民币元
A5: 编号 | B5: 科目名称 | E5: 审计前账面值 | F5: 账面价值 | G5: 评估价值 | H5: 增值额 | I5: 增值率%
A6: 3-1 | B6: 货币资金（现金 | C6: 存款 | D6: 他币） | E6: =SUM(现金!F27,银行存款!G23,其他货币资金!G20) | F6: =SUM(现金!H27,银行存款!I23,其他货币资金!I20) | G6: =SUM(现金!I27,银行存款!J23,其他货币资金!J20) | H6: =G6-F6 | I6: =IF(F6=0,"",H6/F6*100)
A7: 3-2 | B7: 交易性金融资产 | E7: =交易性金融资产汇总!C27 | F7: =交易性金融资产汇总!D27 | G7: =交易性金融资产汇总!E27 | H7: =G7-F7 | I7: =IF(F7=0,"",H7/F7*100)
A8: 3-3 | B8: 应收票据 | E8: =应收票据!F27 | F8: =应收票据!H27 | G8: =应收票据!I27 | H8: =G8-F8 | I8: =IF(F8=0,"",H8/F8*100)
A9: 3-4 | B9: 应收账款 | E9: =应收账款!F27 | F9: =应收账款!P27 | G9: =应收账款!Q27 | H9: =G9-F9 | I9: =IF(F9=0,"",H9/F9*100)
A10: 3-5 | B10: 预付账款 | E10: =预付账款!F27 | F10: =预付账款!H27 | G10: =预付账款!I27 | H10: =G10-F10 | I10: =IF(F10=0,"",H10/F10*100)
A11: 3-6 | B11: 应收利息 | E11: =应收利息!G27 | F11: =应收利息!I27 | G11: =应收利息!J27 | H11: =G11-F11 | I11: =IF(F11=0,"",H11/F11*100)
A12: 3-7 | B12: 应收股利（应收利润） | E12: ='应收股利（利润）'!E27 | F12: ='应收股利（利润）'!G27 | G12: ='应收股利（利润）'!H27 | H12: =G12-F12 | I12: =IF(F12=0,"",H12/F12*100)
A13: 3-8 | B13: 其他应收款 | E13: =其他应收款!F45 | F13: =其他应收款!P45 | G13: =其他应收款!Q45 | H13: =G13-F13 | I13: =IF(F13=0,"",H13/F13*100)
A14: 3-9 | B14: 存货 | E14: =存货汇总!C27 | F14: =存货汇总!D27 | G14: =存货汇总!E27 | H14: =G14-F14 | I14: =IF(F14=0,"",H14/F14*100)
A15: 3-10 | B15: 一年内到期的非流动资产 | E15: =一年到期非流动资产!E27 | F15: =一年到期非流动资产!G27 | G15: =一年到期非流动资产!H27 | H15: =G15-F15 | I15: =IF(F15=0,"",H15/F15*100)
A16: 3-11 | B16: 其他流动资产 | E16: =其他流动资产!E27 | F16: =其他流动资产!G27 | G16: =其他流动资产!H27 | H16: =G16-F16 | I16: =IF(F16=0,"",H16/F16*100)
I17: =IF(F17=0,"",H17/F17*100)
I18: =IF(F18=0,"",H18/F18*100)
I19: =IF(F19=0,"",H19/F19*100)
I20: =IF(F20=0,"",H20/F20*100)
I21: =IF(F21=0,"",H21/F21*100)
I22: =IF(F22=0,"",H22/F22*100)
I23: =IF(F23=0,"",H23/F23*100)
I24: =IF(F24=0,"",H24/F24*100)
I25: =IF(F25=0,"",H25/F25*100)
A27: 3 | B27: 流动资产合计 | E27: =SUM(E6:E26) | F27: =SUM(F6:F26) | G27: =SUM(G6:G26) | H27: =SUM(H6:H26) | I27: =IF(F27=0,"",H27/F27*100)
A28: =封面!D11&封面!G11 | G28: ="评估人员："&封面!G20
A29: =CONCATENATE(封面!D13,封面!F13,封面!G13,封面!H13,封面!I13,封面!J13,封面!K13)

Sheet 现金
A1: 返回索引页 | B1: 返回
A2: 货币资金—现金评估明细表
A3: =CONCATENATE(封面!D9,封面!F9,封面!G9,封面!H9,封面!I9,封面!J9,封面!K9)
A4: =封面!D7&封面!F7 | J4: 金额单位：人民币元
A5: 序号 | B5: 存放部门（单位） | C5: 币种 | D5: 外币账面金额 | E5: 评估基准日汇率 | F5: 审计前账面值 | G5: 审计调整 | H5: 账面价值 | I5: 评估价值 | J5: 增值率%
A6: 1 | I6: =H6 | J6: =IF(H6=0,"",(I6-H6)/H6*100)
J7: =IF(H7=0,"",(I7-H7)/H7*100)
J8: =IF(H8=0,"",(I8-H8)/H8*100)
J9: =IF(H9=0,"",(I9-H9)/H9*100)
J10: =IF(H10=0,"",(I10-H10)/H10*100)
J11: =IF(H11=0,"",(I11-H11)/H11*100)
J12: =IF(H12=0,"",(I12-H12)/H12*100)
J13: =IF(H13=0,"",(I13-H13)/H13*100)
J14: =IF(H14=0,"",(I14-H14)/H14*100)
J15: =IF(H15=0,"",(I15-H15)/H15*100)
J16: =IF(H16=0,"",(I16-H16)/H16*100)
J17: =IF(H17=0,"",(I17-H17)/H17*100)
J18: =IF(H18=0,"",(I18-H18)/H18*100)
... J25: =IF(H25=0,"",(I25-H25)/H25*100)
A27: 合 计 | F27: =SUM(F6:F26) | H27: =SUM(H6:H26) | I27: =SUM(I6:I26) | J27: =IF(H27=0,"",(I27-H27)/H27*100)
A28: =封面!D11&封面!G11 | H28: ="评估人员："&封面!G20
A29: =CONCATENATE(封面!D13,封面!F13,封面!G13,封面!H13,封面!I13,封面!J13,封面!K13)

Sheet 银行存款
A1: 返回索引页 | B1: 返回
A2: 货币资金—银行存款评估明细表
A3: =CONCATENATE(封面!D9,封面!F9,封面!G9,封面!H9,封面!I9,封面!J9,封面!K9)
A4: =封面!D7&封面!F7 | K4: 金额单位：人民币元
A5: 序号 | B5: 开户银行 | C5: 账号 | D5: 币种 | E5: 外币账面金额 | F5: 评估基准日汇率 | G5: 审计前账面值 | H5: 审计调整 | I5: 账面价值 | J5: 评估价值 | K5: 增值率%
A6: 1 | J6: =I6 | K6: =IF(I6=0,"",(J6-I6)/I6*100)
J7: =I7 | K7: =IF(I7=0,"",(J7-I7)/I7*100)
J8: =I8 | K8: =IF(I8=0,"",(J8-I8)/I8*100)
J9: =I9 | K9: =IF(I9=0,"",(J9-I9)/I9*100)
J10: =I10 | K10: =IF(I10=0,"",(J10-I10)/I10*100)
J11: =I11 | K11: =IF(I11=0,"",(J11-I11)/I11*100)
J13: =I13 | K13: =IF(I13=0,"",(J13-I13)/I13*100)
J14: =I14 | K14: =IF(I14=0,"",(J14-I14)/I14*100)
J15: =I15 | K15: =IF(I15=0,"",(J15-I15)/I15*100)
J16: =I16 | K16: =IF(I16=0,"",(J16-I16)/I16*100)
J17: =I17 | K17: =IF(I17=0,"",(J17-I17)/I17*100)
J18: =I18 | K18: =IF(I18=0,"",(J18-I18)/I18*100)
J19: =I19 | K19: =IF(I19=0,"",(J19-I19)/I19*100)
J20: =I20 | K20: =IF(I20=0,"",(J20-I20)/I20*100)
K21: =IF(I21=0,"",(J21-I21)/I21*100)
A23: 合 计 | G23: =SUM(G6:G22) | I23: =SUM(I6:I22) | J23: =SUM(J6:J22) | K23: =IF(I23=0,"",(J23-I23)/I23*100)
A24: =封面!D11&封面!G11 | I24: ="评估人员："&封面!G20
A25: =CONCATENATE(封面!D13,封面!F13,封面!G13,封面!H13,封面!I13,封面!J13,封面!K13)

Sheet 其他货币资金
A1: 返回索引页 | B1: 返回
A2: 货币资金—其他货币资金评估明细表
A3: =CONCATENATE(封面!D9,封面!F9,封面!G9,封面!H9,封面!I9,封面!J9,封面!K9)
A4: =封面!D7&封面!F7 | L4: 金额单位：人民币元
A5: 序号 | B5: 名称及内容 | C5: 用途 | D5: 币种 | E5: 外币账面金额 | F5: 评估基准日汇率 | G5: 审计前账面值 | H5: 审计调整 | I5: 账面价值 | J5: 评估价值 | K5: 增值率% | L5: 备注
A6: 1 | K6: =IF(I6=0,"",(J6-I6)/I6*100)
A7: 2 | K7: =IF(I7=0,"",(J7-I7)/I7*100)
A8: 3 | K8: =IF(I8=0,"",(J8-I8)/I8*100)
A9: 4 | K9: =IF(I9=0,"",(J9-I9)/I9*100)
A10: 5 | K10: =IF(I10=0,"",(J10-I10)/I10*100)
A11: 6 | K11: =IF(I11=0,"",(J11-I11)/I11*100)
K17: =IF(I17=0,"",(J17-I17)/I17*100)
K18: =IF(I18=0,"",(J18-I18)/I18*100)
A20: 合 计 | G20: =SUM(G6:G19) | I20: =SUM(I6:I19) | J20: =SUM(J6:J19) | K20: =IF(I20=0,"",(J20-I20)/I20*100)
A21: =封面!D11&封面!G11 | I21: ="评估人员："&封面!G20
A22: =CONCATENATE(封面!D13,封面!F13,封面!G13,封面!H13,封面!I13,封面!J13,封面!K13)

Sheet 交易性金融资产汇总
A1: 返回索引页 | B1: 返回
A2: 交易性金融资产评估汇总表
A3: =CONCATENATE(封面!D9,封面!F9,封面!G9,封面!H9,封面!I9,封面!J9,封面!K9)
A4: =封面!D7&封面!F7 | G4: 金额单位：人民币元
A5: 编号 | B5: 科目名称 | C5: 审计前账面值 | D5: 账面价值 | E5: 评估价值 | F5: 增值额 | G5: 增值率%
A6: 3-2-1 | B6: 交易性金融资产-股票投资 | C6: ='交易性-股票'!G27 | D6: ='交易性-股票'!I27 | E6: ='交易性-股票'!K27 | F6: =E6-D6 | G6: =IF(D6=0,"",F6/D6*100)
A7: 3-2-2 | B7: 交易性金融资产-债券投资 | C7: ='交易性-债券'!H27 | D7: ='交易性-债券'!J27 | E7: ='交易性-债券'!K27 | F7: =E7-D7 | G7: =IF(D7=0,"",F7/D7*100)
A8: 3-2-3 | B8: 交易性金融资产-基金投资 | C8: ='交易性-基金'!H27 | D8: ='交易性-基金'!J27 | E8: ='交易性-基金'!L27 | F8: =E8-D8 | G8: =IF(D8=0,"",F8/D8*100)
A27: 3-2 | B27: 交易性金融资产合计 | C27: =SUM(C6:C26) | D27: =SUM(D6:D26) | E27: =SUM(E6:E26) | F27: =SUM(F6:F26) | G27: =IF(D27=0,"",F27/D27*100)
A28: =封面!D11&封面!G11 | E28: ="评估人员："&封面!G20
A29: =CONCATENATE(封面!D13,封面!F13,封面!G13,封面!H13,封面!I13,封面!J13,封面!K13)

Sheet 交易性-股票
A1: 返回索引页 | B1: 返回
A2: 交易性金融资产—股票投资评估明细表
A3: =CONCATENATE(封面!D9,封面!F9,封面!G9,封面!H9,封面!I9,封面!J9,封面!K9)
A4: =封面!D7&封面!F7 | L4: 金额单位：人民币元
A5: 序号 | B5: 被投资单位名称 | C5: 股票名称 | D5: 投资日期 | E5: 持股数量 | F5: 成本 | G5: 审计前账面值 | H5: 审计调整 | I5: 账面价值 | J5: 基准日收盘价/股 | K5: 评估价值 | L5: 增值率%
L6: =IF(I6=0,"",(K6-I6)/I6*100)
L7: =IF(I7=0,"",(K7-I7)/I7*100)
L8: =IF(I8=0,"",(K8-I8)/I8*100)
L9: =IF(I9=0,"",(K9-I9)/I9*100)
L10: =IF(I10=0,"",(K10-I10)/I10*100)
L11: =IF(I11=0,"",(K11-I11)/I11*100)
L12: =IF(I12=0,"",(K12-I12)/I12*100)
L13: =IF(I13=0,"",(K13-I13)/I13*100)
L14: =IF(I14=0,"",(K14-I14)/I14*100)
L15: =IF(I15=0,"",(K15-I15)/I15*100)
L16: =IF(I16=0,"",(K16-I16)/I16*100)
L17: =IF(I17=0,"",(K17-I17)/I17*100)
... L25: =IF(I25=0,"",(K25-I25)/I25*100)
A27: 合 计 | G27: =SUM(G6:G26) | I27: =SUM(I6:I26) | K27: =SUM(K6:K26) | L27: =IF(I27=0,"",(K27-I27)/I27*100)
A28: =封面!D11&封面!G11 | I28: ="评估人员："&封面!G20
A29: =CONCATENATE(封面!D13,封面!F13,封面!G13,封面!H13,封面!I13,封面!J13,封面!K13)

Sheet 交易性-债券
A1: 返回索引页 | B1: 返回
A2: 交易性金融资产—债券投资评估明细表
A3: =CONCATENATE(封面!D9,封面!F9,封面!G9,封面!H9,封面!I9,封面!J9,封面!K9)
A4: =封面!D7&封面!F7 | L4: 金额单位：人民币元
A5: 序号 | B5: 被投资单位名称 | C5: 债券名称 | D5: 发行日期 | E5: 投资日期 | F5: 票面利率% | G5: 成本 | H5: 审计前账面值 | I5: 审计调整 | J5: 账面价值 | K5: 评估价值 | L5: 增值率%
L6: =IF(J6=0,"",(K6-J6)/J6*100)
L7: =IF(J7=0,"",(K7-J7)/J7*100)
L8: =IF(J8=0,"",(K8-J8)/J8*100)
L9: =IF(J9=0,"",(K9-J9)/J9*100)
L10: =IF(J10=0,"",(K10-J10)/J10*100)
L11: =IF(J11=0,"",(K11-J11)/J11*100)
L12: =IF(J12=0,"",(K12-J12)/J12*100)
L13: =IF(J13=0,"",(K13-J13)/J13*100)
L14: =IF(J14=0,"",(K14-J14)/J14*100)
L15: =IF(J15=0,"",(K15-J15)/J15*100)
L16: =IF(J16=0,"",(K16-J16)/J16*100)
L17: =IF(J17=0,"",(K17-J17)/J17*100)
... L25: =IF(J25=0,"",(K25-J25)/J25*100)
A27: 合 计 | H27: =SUM(H6:H26) | J27: =SUM(J6:J26) | K27: =SUM(K6:K26) | L27: =IF(J27=0,"",(K27-J27)/J27*100)
A28: =封面!D11&封面!G11 | J28: ="评估人员："&封面!G20
A29: =CONCATENATE(封面!D13,封面!F13,封面!G13,封面!H13,封面!I13,封面!J13,封面!K13)

Sheet 交易性-基金
A1: 返回索引页 | B1: 返回
A2: 交易性金融资产—基金投资评估明细表
A3: =CONCATENATE(封面!D9,封面!F9,封面!G9,封面!H9,封面!I9,封面!J9,封面!K9)
A4: =封面!D7&封面!F7 | M4: 金额单位：人民币元
A5: 序号 | B5: 基金发行单位 | C5: 基金名称 | D5: 基金类型 | E5: 投资日期 | F5: 基金份额 | G5: 成本 | H5: 审计前账面值 | I5: 审计调整 | J5: 账面价值 | K5: 基准日净值/份 | L5: 评估价值 | M5: 增值率%
M6: =IF(J6=0,"",(L6-J6)/J6*100)
M7: =IF(J7=0,"",(L7-J7)/J7*100)
M8: =IF(J8=0,"",(L8-J8)/J8*100)
M9: =IF(J9=0,"",(L9-J9)/J9*100)
M10: =IF(J10=0,"",(L10-J10)/J10*100)
M11: =IF(J11=0,"",(L11-J11)/J11*100)
M12: =IF(J12=0,"",(L12-J12)/J12*100)
M13: =IF(J13=0,"",(L13-J13)/J13*100)
M14: =IF(J14=0,"",(L14-J14)/J14*100)
M15: =IF(J15=0,"",(L15-J15)/J15*100)
M16: =IF(J16=0,"",(L16-J16)/J16*100)
M17: =IF(J17=0,"",(L17-J17)/J17*100)
... M25: =IF(J25=0,"",(L25-J25)/J25*100)
A27: 合 计 | H27: =SUM(H6:H26) | J27: =SUM(J6:J26) | L27: =SUM(L6:L26) | M27: =IF(J27=0,"",(L27-J27)/J27*100)
A28: =封面!D11&封面!G11 | J28: ="评估人员："&封面!G20
A29: =CONCATENATE(封面!D13,封面!F13,封面!G13,封面!H13,封面!I13,封面!J13,封面!K13)

Sheet 应收票据
A1: 返回索引页 | B1: 返回
A2: 应收票据评估明细表
A3: =CONCATENATE(封面!D9,封面!F9,封面!G9,封面!H9,封面!I9,封面!J9,封面!K9)
A4: =封面!D7&封面!F7 | K4: 金额单位：人民币元
A5: 序号 | B5: 户名（结算对象） | C5: 出票日期 | D5: 到期日期 | E5: 票面利率% | F5: 审计前账面值 | G5: 审计调整 | H5: 账面价值 | I5: 评估价值 | J5: 增值率% | K5: 备注
J6: =IF(H6=0,"",(I6-H6)/H6*100)
J7: =IF(H7=0,"",(I7-H7)/H7*100)
J8: =IF(H8=0,"",(I8-H8)/H8*100)
J9: =IF(H9=0,"",(I9-H9)/H9*100)
J10: =IF(H10=0,"",(I10-H10)/H10*100)
J11: =IF(H11=0,"",(I11-H11)/H11*100)
J12: =IF(H12=0,"",(I12-H12)/H12*100)
J13: =IF(H13=0,"",(I13-H13)/H13*100)
J14: =IF(H14=0,"",(I14-H14)/H14*100)
J15: =IF(H15=0,"",(I15-H15)/H15*100)
J16: =IF(H16=0,"",(I16-H16)/H16*100)
J17: =IF(H17=0,"",(I17-H17)/H17*100)
... J26: =IF(H26=0,"",(I26-H26)/H26*100)
A27: 合 计 | F27: =SUM(F6:F26) | H27: =SUM(H6:H26) | I27: =SUM(I6:I26) | J27: =IF(H27=0,"",(I27-H27)/H27*100)
A28: =封面!D11&封面!G11 | H28: ="评估人员："&封面!G20
A29: =CONCATENATE(封面!D13,封面!F13,封面!G13,封面!H13,封面!I13,封面!J13,封面!K13)

Sheet 应收账款
A1: 返回索引页 | B1: 返回
A2: 应收账款评估明细表
A3: =CONCATENATE(封面!D9,封面!F9,封面!G9,封面!H9,封面!I9,封面!J9,封面!K9)
A4: =封面!D7&封面!F7 | M4: 账龄总数与审计前账面值差异(应等于0) | N4: 预计不可收回金额(注1) | S4: 金额单位：人民币元
A5: 序号 | B5: 欠款单位名称（结算对象） | C5: 业务内容 | D5: 发生日期 | E5: 账龄 | F5: 审计前账面值 | G5: 1年以内金额 | H5: 1~2年金额 | I5: 2~3年金额 | J5: 3~4年金额 | K5: 4~5年金额 | L5: 5年以上金额 | O5: 审计调整 | P5: 账面价值 | Q5: 评估价值 | R5: 增值率% | S5: 备注
A6: 1 | Q6: =P6 | R6: =IF(P6=0,"",(Q6-P6)/P6*100)
A24: 合 计 | F24: =SUM(F6:F23) | G24: =SUM(G6:G23) | H24: =SUM(H6:H23) | I24: =SUM(I6:I23) | J24: =SUM(J6:J23) | K24: =SUM(K6:K23) | L24: =SUM(L6:L23) | M24: =SUM(M6:M23) | N24: =SUM(N6:N23) | P24: =SUM(P6:P23) | Q24: =SUM(Q6:Q23) | R24: =IF(P24=0,"",(Q24-P24)/P24*100)
A25: 减：坏账准备 | M25: =SUM(G25:L25)-F25 | P25: =F24 | R25: =IF(P25=0,"",(Q25-P25)/P25*100)
A26: 减：评估风险损失 | R26: =IF(P26=0,"",(Q26-P26)/P26*100)
A27: 净 额 | F27: =F24-F25-F26 | G27: =G24-G25-G26 | H27: =H24-H25-H26 | I27: =I24-I25-I26 | J27: =J24-J25-J26 | K27: =K24-K25-K26 | L27: =L24-L25-L26 | M27: =M24-M25-M26 | N27: =N24-N25-N26 | P27: =P24-P25-P26 | Q27: =Q24-Q25-Q26 | R27: =IF(P27=0,"",(Q27-P27)/P27*100)
A28: =封面!D11&封面!G11 | P28: ="评估人员："&封面!G20
A29: =CONCATENATE(封面!D13,封面!F13,封面!G13,封面!H13,封面!I13,封面!J13,封面!K13)
B30: 注1： | C30: 注明账齡在一年以上的账款的可收回性，若有部分可能不能收回，请估计不能收回的金額，以供评估时作參考。
B31: 注2：“备注”栏填写方法： | C31: 1）欠款单位为关联方、总公司内部或本公司内部单位的，应在备注栏注明“关联方”、“总公司内部”、“内部单位”；
C32: 2） 涉诉款项应在备注中标明“涉诉”；
C33: 3）评估基准日后已部分或全部收回款项的，应注明日期及金额，如“2003年2月4日收回8,530.00元”；
C34: 4）填表单位认为其他应说明的事项

Sheet 预付账款
A1: 返回索引页 | B1: 返回
A2: 预付账款评估明细表
A3: =CONCATENATE(封面!D9,封面!F9,封面!G9,封面!H9,封面!I9,封面!J9,封面!K9)
A4: =封面!D7&封面!F7 | K4: 金额单位：人民币元
A5: 序号 | B5: 收款单位名称（结算对象） | C5: 业务内容 | D5: 发生日期 | E5: 账龄 | F5: 审计前账面值 | G5: 审计调整 | H5: 账面价值 | I5: 评估价值 | J5: 增值率% | K5: 备注
A6: 1 | I6: =H6 | J6: =IF(H6=0,"",(I6-H6)/H6*100)
A7: 2 | I7: =H7 | J7: =IF(H7=0,"",(I7-H7)/H7*100)
A27: 合 计 | F27: =SUM(F6:F26) | H27: =SUM(H6:H26) | I27: =SUM(I6:I26) | J27: =IF(H27=0,"",(I27-H27)/H27*100)
A28: =封面!D11&封面!G11 | H28: ="评估人员："&封面!G20
A29: =CONCATENATE(封面!D13,封面!F13,封面!G13,封面!H13,封面!I13,封面!J13,封面!K13)

Sheet 应收利息
A1: 返回索引页 | B1: 返回
A2: 应收利息评估明细表
A3: =CONCATENATE(封面!D9,封面!F9,封面!G9,封面!H9,封面!I9,封面!J9,封面!K9)
A4: =封面!D7&封面!F7 | L4: 金额单位：人民币元
A5: 序号 | B5: 欠款单位名称（结算对象） | C5: 发生日期 | D5: 本金 | E5: 利息所属期间 | F5: 利息率% | G5: 审计前账面值 | H5: 审计调整 | I5: 账面价值 | J5: 评估价值 | K5: 增值率% | L5: 备注
K6: =IF(I6=0,"",(J6-I6)/I6*100)
K7: =IF(I7=0,"",(J7-I7)/I7*100)
K8: =IF(I8=0,"",(J8-I8)/I8*100)
K9: =IF(I9=0,"",(J9-I9)/I9*100)
K10: =IF(I10=0,"",(J10-I10)/I10*100)
K11: =IF(I11=0,"",(J11-I11)/I11*100)
K12: =IF(I12=0,"",(J12-I12)/I12*100)
K13: =IF(I13=0,"",(J13-I13)/I13*100)
K14: =IF(I14=0,"",(J14-I14)/I14*100)
K15: =IF(I15=0,"",(J15-I15)/I15*100)
K16: =IF(I16=0,"",(J16-I16)/I16*100)
K17: =IF(I17=0,"",(J17-I17)/I17*100)
... K25: =IF(I25=0,"",(J25-I25)/I25*100)
A27: 合 计 | D27: =SUM(D6:D26) | G27: =SUM(G6:G26) | I27: =SUM(I6:I26) | J27: =SUM(J6:J26) | K27: =IF(I27=0,"",(J27-I27)/I27*100)
A28: =封面!D11&封面!G11 | I28: ="评估人员："&封面!G20
A29: =CONCATENATE(封面!D13,封面!F13,封面!G13,封面!H13,封面!I13,封面!J13,封面!K13)

Sheet 应收股利（利润）
A1: 返回索引页 | B1: 返回
A2: 应收股利（应收利润）评估明细表
A3: =CONCATENATE(封面!D9,封面!F9,封面!G9,封面!H9,封面!I9,封面!J9,封面!K9)
A4: =封面!D7&封面!F7 | J4: 金额单位：人民币元
A5: 序号 | B5: 户名（结算对象） | C5: 发生日期 | D5: 股利所属期间 | E5: 审计前账面值 | F5: 审计调整 | G5: 账面价值 | H5: 评估价值 | I5: 增值率% | J5: 备注
I6: =IF(G6=0,"",(H6-G6)/G6*100)
I7: =IF(G7=0,"",(H7-G7)/G7*100)
I8: =IF(G8=0,"",(H8-G8)/G8*100)
I9: =IF(G9=0,"",(H9-G9)/G9*100)
I10: =IF(G10=0,"",(H10-G10)/G10*100)
I11: =IF(G11=0,"",(H11-G11)/G11*100)
I12: =IF(G12=0,"",(H12-G12)/G12*100)
I13: =IF(G13=0,"",(H13-G13)/G13*100)
I14: =IF(G14=0,"",(H14-G14)/G14*100)
I15: =IF(G15=0,"",(H15-G15)/G15*100)
I16: =IF(G16=0,"",(H16-G16)/G16*100)
I17: =IF(G17=0,"",(H17-G17)/G17*100)
... I25: =IF(G25=0,"",(H25-G25)/G25*100)
A27: 合 计 | E27: =SUM(E6:E26) | G27: =SUM(G6:G26) | H27: =SUM(H6:H26) | I27: =IF(G27=0,"",(H27-G27)/G27*100)
A28: =封面!D11&封面!G11 | G28: ="评估人员："&封面!G20
A29: =CONCATENATE(封面!D13,封面!F13,封面!G13,封面!H13,封面!I13,封面!J13,封面!K13)

Sheet 其他应收款
A1: 返回索引页 | B1: 返回
A2: 其他应收款评估明细表
A3: =CONCATENATE(封面!D9,封面!F9,封面!G9,封面!H9,封面!I9,封面!J9,封面!K9)
A4: =封面!D7&封面!F7 | M4: 账龄总数与审计前账面值差异(应等于0) | N4: 预计不可收回金额(注1) | S4: 金额单位：人民币元
A5: 序号 | B5: 欠款单位名称（结算对象） | C5: 业务内容 | D5: 发生日期 | E5: 账龄 | F5: 审计前账面值 | G5: 1年以内金额 | H5: 1~2年金额 | I5: 2~3年金额 | J5: 3~4年金额 | K5: 4~5年金额 | L5: 5年以上金额 | O5: 审计调整 | P5: 账面价值 | Q5: 评估价值 | R5: 增值率% | S5: 备注
A6: 1 | Q6: =P6 | R6: =IF(P6=0,"",(Q6-P6)/P6*100)
A7: 2 | Q7: =P7 | R7: =IF(P7=0,"",(Q7-P7)/P7*100)
A8: 3 | Q8: =P8 | R8: =IF(P8=0,"",(Q8-P8)/P8*100)
A9: 4 | Q9: =P9 | R9: =IF(P9=0,"",(Q9-P9)/P9*100)
A10: 5 | Q10: =P10 | R10: =IF(P10=0,"",(Q10-P10)/P10*100)
A11: 6 | Q11: =P11 | R11: =IF(P11=0,"",(Q11-P11)/P11*100)
A12: 7 | Q12: =P12 | R12: =IF(P12=0,"",(Q12-P12)/P12*100)
A13: 8 | Q13: =P13 | R13: =IF(P13=0,"",(Q13-P13)/P13*100)
A14: 9 | Q14: =P14 | R14: =IF(P14=0,"",(Q14-P14)/P14*100)
A15: 10 | Q15: =P15 | R15: =IF(P15=0,"",(Q15-P15)/P15*100)
A16: 11 | Q16: =P16 | R16: =IF(P16=0,"",(Q16-P16)/P16*100)
A17: 12 | Q17: =P17 | R17: =IF(P17=0,"",(Q17-P17)/P17*100)
... A41: 36 | Q41: =P41 | R41: =IF(P41=0,"",(Q41-P41)/P41*100)
A42: 合 计 | F42: =SUM(F6:F41) | G42: =SUM(G6:G41) | H42: =SUM(H6:H41) | I42: =SUM(I6:I41) | J42: =SUM(J6:J41) | K42: =SUM(K6:K41) | L42: =SUM(L6:L41) | M42: =SUM(M6:M41) | N42: =SUM(N6:N41) | P42: =SUM(P6:P41) | Q42: =SUM(Q6:Q41) | R42: =IF(P30=0,"",(Q30-P30)/P30*100)
A43: 减：坏账准备 | M43: =SUM(G31:L31)-F31 | P43: =F31 | R43: =IF(P31=0,"",(Q31-P31)/P31*100)
A44: 减：评估风险损失 | R44: =IF(P32=0,"",(Q32-P32)/P32*100)
A45: 净 额 | F45: =F30-F31-F32 | G45: =G30-G31-G32 | H45: =H30-H31-H32 | I45: =I30-I31-I32 | J45: =J30-J31-J32 | K45: =K30-K31-K32 | L45: =L30-L31-L32 | M45: =M30-M31-M32 | N45: =N30-N31-N32 | P45: =P42-P43 | Q45: =Q42-Q44 | R45: =IF(P33=0,"",(Q33-P33)/P33*100)
A46: =封面!D11&封面!G11 | P46: ="评估人员："&封面!G20
A47: =CONCATENATE(封面!D13,封面!F13,封面!G13,封面!H13,封面!I13,封面!J13,封面!K13)
B48: 注1： | C48: 注明账齡在一年以上的账款的可收回性，若有部分可能不能收回，请估计不能收回的金額，以供评估时作參考。
B49: 注2：“备注”栏填写方法： | C49: 1）欠款单位为关联方、总公司内部或本公司内部单位的，应在备注栏注明“关联方”、“总公司内部”、“内部单位”；
C50: 2） 涉诉款项应在备注中标明“涉诉”；
C51: 3）评估基准日后已部分或全部收回款项的，应注明日期及金额，如“2003年2月4日收回8,530.00元”；
C52: 4）填表单位认为其他应说明的事项

Sheet 存货汇总
A1: 返回索引页 | B1: 返回
A2: 存货评估汇总表
A3: =CONCATENATE(封面!D9,封面!F9,封面!G9,封面!H9,封面!I9,封面!J9,封面!K9)
A4: =封面!D7&封面!F7 | G4: 金额单位：人民币元
A5: 编号 | B5: 科目名称 | C5: 审计前账面值 | D5: 账面价值 | E5: 评估价值 | F5: 增值额 | G5: 增值率%
A6: 3-9-1 | B6: 材料采购（在途物资） | C6: ='材料采购（在途物资）'!F27 | D6: ='材料采购（在途物资）'!J27 | E6: ='材料采购（在途物资）'!M27 | F6: =E6-D6 | G6: =IF(D6=0,"",F6/D6*100)
A7: 3-9-2 | B7: 原材料 | C7: =原材料!F277 | D7: =原材料!J277 | E7: =原材料!M277 | F7: =E7-D7 | G7: =IF(D7=0,"",F7/D7*100)
A8: 3-9-3 | B8: 在库周转材料 | C8: =在库周转材料!F27 | D8: =在库周转材料!J27 | E8: =在库周转材料!M27 | F8: =E8-D8 | G8: =IF(D8=0,"",F8/D8*100)
A9: 3-9-4 | B9: 委托加工物资 | C9: =委托加工物资!G27 | D9: =委托加工物资!K27 | E9: =委托加工物资!N27 | F9: =E9-D9 | G9: =IF(D9=0,"",F9/D9*100)
A10: 3-9-5 | B10: 产成品（库存商品） | C10: ='产成品（库存商品）'!F27 | D10: ='产成品（库存商品）'!J27 | E10: ='产成品（库存商品）'!M27 | F10: =E10-D10 | G10: =IF(D10=0,"",F10/D10*100)
A11: 3-9-6 | B11: 在产品（自制半成品） | C11: ='在产品（自制半成品）'!F27 | D11: ='在产品（自制半成品）'!J27 | E11: ='在产品（自制半成品）'!M27 | F11: =E11-D11 | G11: =IF(D11=0,"",F11/D11*100)
A12: 3-9-7 | B12: 发出商品 | C12: =发出商品!G37 | D12: =发出商品!K37 | E12: =发出商品!N37 | F12: =E12-D12 | G12: =IF(D12=0,"",F12/D12*100)
A13: 3-9-8 | B13: 在用周转材料 | C13: =在用周转材料!G27 | D13: =在用周转材料!J27 | E13: =在用周转材料!N27 | F13: =E13-D13 | G13: =IF(D13=0,"",F13/D13*100)
A25: 3-10 | B25: 存货合计 | C25: =SUM(C6:C24) | D25: =SUM(D6:D24) | E25: =SUM(E6:E24) | F25: =SUM(F6:F24) | G25: =IF(D25=0,"",F25/D25*100)
A26: 3-10 | B26: 减：存货跌价准备 | D26: =C26 | E26: 0 | F26: =E26-D26 | G26: =IF(D26=0,"",F26/D26*100)
A27: 3-10 | B27: 存货净额 | C27: =C25-C26 | D27: =D25-D26 | E27: =E25-E26 | F27: =F25-F26 | G27: =IF(D27=0,"",F27/D27*100)
A28: =封面!D11&封面!G11 | E28: ="评估人员："&封面!G20
A29: =CONCATENATE(封面!D13,封面!F13,封面!G13,封面!H13,封面!I13,封面!J13,封面!K13)

Sheet 材料采购（在途物资）
A1: 返回索引页 | B1: 返回
A2: 存货—材料采购（在途物资）评估明细表
A3: =CONCATENATE(封面!D9,封面!F9,封面!G9,封面!H9,封面!I9,封面!J9,封面!K9)
A4: =封面!D7&封面!F7 | O4: 金额单位：人民币元
A5: 序号 | B5: 名称及规格型号 | C5: 计量单位 | D5: 审计前账面值 | G5: 审计调整 | H5: 账面价值 | K5: 评估价值 | N5: 增值率% | O5: 备注
D6: 数量 | E6: 单价 | F6: 金额 | H6: 数量 | I6: 单价 | J6: 金额 | K6: 实际数量 | L6: 单价 | M6: 金额
E7: =IF(D7=0,"",F7/D7) | N7: =IF(J7=0,"",(M7-J7)/J7*100)
E8: =IF(D8=0,"",F8/D8) | N8: =IF(J8=0,"",(M8-J8)/J8*100)
E9: =IF(D9=0,"",F9/D9) | N9: =IF(J9=0,"",(M9-J9)/J9*100)
E10: =IF(D10=0,"",F10/D10) | N10: =IF(J10=0,"",(M10-J10)/J10*100)
E11: =IF(D11=0,"",F11/D11) | N11: =IF(J11=0,"",(M11-J11)/J11*100)
E12: =IF(D12=0,"",F12/D12) | N12: =IF(J12=0,"",(M12-J12)/J12*100)
E13: =IF(D13=0,"",F13/D13) | N13: =IF(J13=0,"",(M13-J13)/J13*100)
E14: =IF(D14=0,"",F14/D14) | N14: =IF(J14=0,"",(M14-J14)/J14*100)
E15: =IF(D15=0,"",F15/D15) | N15: =IF(J15=0,"",(M15-J15)/J15*100)
E16: =IF(D16=0,"",F16/D16) | N16: =IF(J16=0,"",(M16-J16)/J16*100)
E17: =IF(D17=0,"",F17/D17) | N17: =IF(J17=0,"",(M17-J17)/J17*100)
E18: =IF(D18=0,"",F18/D18) | N18: =IF(J18=0,"",(M18-J18)/J18*100)
... E25: =IF(D25=0,"",F25/D25) | N25: =IF(J25=0,"",(M25-J25)/J25*100)
A27: 合 计 | F27: =SUM(F7:F26) | J27: =SUM(J7:J26) | M27: =SUM(M7:M26) | N27: =IF(J27=0,"",(M27-J27)/J27*100)
A28: =封面!D11&封面!G11 | J28: ="评估人员："&封面!G20
A29: =CONCATENATE(封面!D13,封面!F13,封面!G13,封面!H13,封面!I13,封面!J13,封面!K13)

Sheet 原材料
A1: 返回索引页 | B1: 返回
A2: 存货—原材料评估明细表
A3: =CONCATENATE(封面!D9,封面!F9,封面!G9,封面!H9,封面!I9,封面!J9,封面!K9)
A4: =封面!D7&封面!F7 | O4: 金额单位：人民币元
A5: 序号 | B5: 名称及规格型号 | C5: 计量单位 | D5: 审计前账面值 | G5: 审计调整 | H5: 账面价值 | K5: 评估价值 | N5: 增值率% | O5: 备注
D6: 数量 | E6: 单价 | F6: 金额 | H6: 数量 | I6: 单价 | J6: 金额 | K6: 实际数量 | L6: 单价 | M6: 金额
N7: =IF(J7=0,"",(M7-J7)/J7*100)
N8: =IF(J8=0,"",(M8-J8)/J8*100)
N9: =IF(J9=0,"",(M9-J9)/J9*100)
N10: =IF(J10=0,"",(M10-J10)/J10*100)
N11: =IF(J11=0,"",(M11-J11)/J11*100)
N12: =IF(J12=0,"",(M12-J12)/J12*100)
N13: =IF(J13=0,"",(M13-J13)/J13*100)
N14: =IF(J14=0,"",(M14-J14)/J14*100)
N15: =IF(J15=0,"",(M15-J15)/J15*100)
N16: =IF(J16=0,"",(M16-J16)/J16*100)
N17: =IF(J17=0,"",(M17-J17)/J17*100)
N18: =IF(J18=0,"",(M18-J18)/J18*100)
... N263: =IF(J263=0,"",(M263-J263)/J263*100)
E264: =IF(D264=0,"",F264/D264) | N264: =IF(J264=0,"",(M264-J264)/J264*100)
E265: =IF(D265=0,"",F265/D265) | N265: =IF(J265=0,"",(M265-J265)/J265*100)
E266: =IF(D266=0,"",F266/D266) | N266: =IF(J266=0,"",(M266-J266)/J266*100)
E267: =IF(D267=0,"",F267/D267) | N267: =IF(J267=0,"",(M267-J267)/J267*100)
E268: =IF(D268=0,"",F268/D268) | N268: =IF(J268=0,"",(M268-J268)/J268*100)
E269: =IF(D269=0,"",F269/D269) | N269: =IF(J269=0,"",(M269-J269)/J269*100)
E270: =IF(D270=0,"",F270/D270) | N270: =IF(J270=0,"",(M270-J270)/J270*100)
E271: =IF(D271=0,"",F271/D271) | N271: =IF(J271=0,"",(M271-J271)/J271*100)
E272: =IF(D272=0,"",F272/D272) | N272: =IF(J272=0,"",(M272-J272)/J272*100)
E273: =IF(D273=0,"",F273/D273) | N273: =IF(J273=0,"",(M273-J273)/J273*100)
E274: =IF(D274=0,"",F274/D274) | N274: =IF(J274=0,"",(M274-J274)/J274*100)
E275: =IF(D275=0,"",F275/D275) | N275: =IF(J275=0,"",(M275-J275)/J275*100)
A277: 合 计 | F277: =SUM(F7:F276) | J277: =SUM(J7:J276) | M277: =SUM(M7:M276) | N277: =IF(J277=0,"",(M277-J277)/J277*100)
A278: =封面!D11&封面!G11 | J278: ="评估人员："&封面!G20
A279: =CONCATENATE(封面!D13,封面!F13,封面!G13,封面!H13,封面!I13,封面!J13,封面!K13)
B280: 注1： | C280: 1）正常，无需填写；2）残次，填“A”；3）变质，填“B”；4）毁损，填“C”；5）滞销，填“E”；
C281: 6）积压，填“D”并在备注中填写已积压时间“1年以内”、“1~2年”、“2~3年”、“3年以上”；7）其他情形用文字表述。

Sheet 在库周转材料
A1: 返回索引页 | B1: 返回
A2: 存货—在库周转材料评估明细表
A3: =CONCATENATE(封面!D9,封面!F9,封面!G9,封面!H9,封面!I9,封面!J9,封面!K9)
A4: =封面!D7&封面!F7 | O4: 金额单位：人民币元
A5: 序号 | B5: 名称及规格型号 | C5: 计量单位 | D5: 审计前账面值 | G5: 审计调整 | H5: 账面价值 | K5: 评估价值 | N5: 增值率% | O5: 备注 | P5: 存放地点
D6: 数量 | E6: 单价 | F6: 金额 | H6: 数量 | I6: 单价 | J6: 金额 | K6: 实际数量 | L6: 单价 | M6: 金额
E7: =IF(D7=0,"",F7/D7) | N7: =IF(J7=0,"",(M7-J7)/J7*100)
E8: =IF(D8=0,"",F8/D8) | N8: =IF(J8=0,"",(M8-J8)/J8*100)
E9: =IF(D9=0,"",F9/D9) | N9: =IF(J9=0,"",(M9-J9)/J9*100)
E10: =IF(D10=0,"",F10/D10) | N10: =IF(J10=0,"",(M10-J10)/J10*100)
E11: =IF(D11=0,"",F11/D11) | N11: =IF(J11=0,"",(M11-J11)/J11*100)
E12: =IF(D12=0,"",F12/D12) | N12: =IF(J12=0,"",(M12-J12)/J12*100)
E13: =IF(D13=0,"",F13/D13) | N13: =IF(J13=0,"",(M13-J13)/J13*100)
E14: =IF(D14=0,"",F14/D14) | N14: =IF(J14=0,"",(M14-J14)/J14*100)
E15: =IF(D15=0,"",F15/D15) | N15: =IF(J15=0,"",(M15-J15)/J15*100)
E16: =IF(D16=0,"",F16/D16) | N16: =IF(J16=0,"",(M16-J16)/J16*100)
E17: =IF(D17=0,"",F17/D17) | N17: =IF(J17=0,"",(M17-J17)/J17*100)
E18: =IF(D18=0,"",F18/D18) | N18: =IF(J18=0,"",(M18-J18)/J18*100)
... E25: =IF(D25=0,"",F25/D25) | N25: =IF(J25=0,"",(M25-J25)/J25*100)
A27: 合 计 | F27: =SUM(F7:F26) | J27: =SUM(J7:J26) | M27: =SUM(M7:M26) | N27: =IF(J27=0,"",(M27-J27)/J27*100)
A28: =封面!D11&封面!G11 | J28: ="评估人员："&封面!G20
A29: =CONCATENATE(封面!D13,封面!F13,封面!G13,封面!H13,封面!I13,封面!J13,封面!K13)
B30: 注1： | C30: 1）正常，无需填写；2）残次，填“A”；3）变质，填“B”；4）毁损，填“C”；5）滞销，填“E”；
C31: 6）积压，填“D”并在备注中填写已积压时间“1年以内”、“1~2年”、“2~3年”、“3年以上”；7）其他情形用文字表述。

Sheet 委托加工物资
A1: 返回索引页 | B1: 返回
A2: 存货—委托加工物资评估明细表
A3: =CONCATENATE(封面!D9,封面!F9,封面!G9,封面!H9,封面!I9,封面!J9,封面!K9)
A4: =封面!D7&封面!F7 | P4: 金额单位：人民币元
A5: 序号 | B5: 名称及规格型号 | C5: 加工单位名称 | D5: 计量单位 | E5: 审计前账面值 | H5: 审计调整 | I5: 账面价值 | L5: 评估价值 | O5: 增值率% | P5: 备注
E6: 数量 | F6: 单价 | G6: 金额 | I6: 数量 | J6: 单价 | K6: 金额 | L6: 实际数量 | M6: 单价 | N6: 金额
O7: =IF(K7=0,"",(N7-K7)/K7*100)
O8: =IF(K8=0,"",(N8-K8)/K8*100)
O9: =IF(K9=0,"",(N9-K9)/K9*100)
O10: =IF(K10=0,"",(N10-K10)/K10*100)
O11: =IF(K11=0,"",(N11-K11)/K11*100)
F12: =IF(E12=0,"",G12/E12) | O12: =IF(K12=0,"",(N12-K12)/K12*100)
F13: =IF(E13=0,"",G13/E13) | O13: =IF(K13=0,"",(N13-K13)/K13*100)
F14: =IF(E14=0,"",G14/E14) | O14: =IF(K14=0,"",(N14-K14)/K14*100)
F15: =IF(E15=0,"",G15/E15) | O15: =IF(K15=0,"",(N15-K15)/K15*100)
F16: =IF(E16=0,"",G16/E16) | O16: =IF(K16=0,"",(N16-K16)/K16*100)
F17: =IF(E17=0,"",G17/E17) | O17: =IF(K17=0,"",(N17-K17)/K17*100)
F18: =IF(E18=0,"",G18/E18) | O18: =IF(K18=0,"",(N18-K18)/K18*100)
F19: =IF(E19=0,"",G19/E19) | O19: =IF(K19=0,"",(N19-K19)/K19*100)
F20: =IF(E20=0,"",G20/E20) | O20: =IF(K20=0,"",(N20-K20)/K20*100)
F21: =IF(E21=0,"",G21/E21) | O21: =IF(K21=0,"",(N21-K21)/K21*100)
F22: =IF(E22=0,"",G22/E22) | O22: =IF(K22=0,"",(N22-K22)/K22*100)
F23: =IF(E23=0,"",G23/E23) | O23: =IF(K23=0,"",(N23-K23)/K23*100)
... F25: =IF(E25=0,"",G25/E25) | O25: =IF(K25=0,"",(N25-K25)/K25*100)
A27: 合 计 | G27: =SUM(G7:G26) | K27: =SUM(K7:K26) | N27: =SUM(N7:N26) | O27: =IF(K27=0,"",(N27-K27)/K27*100)
A28: =封面!D11&封面!G11 | K28: ="评估人员："&封面!G20
A29: =CONCATENATE(封面!D13,封面!F13,封面!G13,封面!H13,封面!I13,封面!J13,封面!K13)

Sheet 产成品（库存商品）
A1: 返回索引页 | B1: 返回
A2: 存货—产成品（库存商品）评估明细表
A3: =CONCATENATE(封面!D9,封面!F9,封面!G9,封面!H9,封面!I9,封面!J9,封面!K9)
A4: =封面!D7&封面!F7 | O4: 金额单位：人民币元
A5: 序号 | B5: 名称及规格型号 | C5: 计量单位 | D5: 审计前账面值 | G5: 审计调整 | H5: 账面价值 | K5: 评估价值 | N5: 增值率% | O5: 备注 | P5: 存放地点
D6: 数量 | E6: 单价 | F6: 金额 | H6: 数量 | I6: 单价 | J6: 金额 | K6: 实际数量 | L6: 单价 | M6: 金额
E7: =IF(D7=0,"",F7/D7) | N7: =IF(J7=0,"",(M7-J7)/J7*100)
E8: =IF(D8=0,"",F8/D8) | N8: =IF(J8=0,"",(M8-J8)/J8*100)
E9: =IF(D9=0,"",F9/D9) | N9: =IF(J9=0,"",(M9-J9)/J9*100)
E10: =IF(D10=0,"",F10/D10) | N10: =IF(J10=0,"",(M10-J10)/J10*100)
E11: =IF(D11=0,"",F11/D11) | N11: =IF(J11=0,"",(M11-J11)/J11*100)
E12: =IF(D12=0,"",F12/D12) | N12: =IF(J12=0,"",(M12-J12)/J12*100)
E13: =IF(D13=0,"",F13/D13) | N13: =IF(J13=0,"",(M13-J13)/J13*100)
E14: =IF(D14=0,"",F14/D14) | N14: =IF(J14=0,"",(M14-J14)/J14*100)
E15: =IF(D15=0,"",F15/D15) | N15: =IF(J15=0,"",(M15-J15)/J15*100)
E16: =IF(D16=0,"",F16/D16) | N16: =IF(J16=0,"",(M16-J16)/J16*100)
E17: =IF(D17=0,"",F17/D17) | N17: =IF(J17=0,"",(M17-J17)/J17*100)
E18: =IF(D18=0,"",F18/D18) | N18: =IF(J18=0,"",(M18-J18)/J18*100)
... E25: =IF(D25=0,"",F25/D25) | N25: =IF(J25=0,"",(M25-J25)/J25*100)
A27: 合 计 | F27: =SUM(F7:F26) | J27: =SUM(J7:J26) | M27: =SUM(M7:M26) | N27: =IF(J27=0,"",(M27-J27)/J27*100)
A28: =封面!D11&封面!G11 | J28: ="评估人员："&封面!G20
A29: =CONCATENATE(封面!D13,封面!F13,封面!G13,封面!H13,封面!I13,封面!J13,封面!K13)
B30: 注1： | C30: 1）正常，无需填写；2）残次，填“A”；3）变质，填“B”；4）毁损，填“C”；5）滞销，填“E”；
C31: 6）积压，填“D”并在备注中填写已积压时间“1年以内”、“1~2年”、“2~3年”、“3年以上”；7）其他情形用文字表述。

Sheet 在产品（自制半成品）
A1: 返回索引页 | B1: 返回
A2: 存货—在产品（自制半成品）评估明细表
A3: =CONCATENATE(封面!D9,封面!F9,封面!G9,封面!H9,封面!I9,封面!J9,封面!K9)
A4: =封面!D7&封面!F7 | O4: 金额单位：人民币元
A5: 序号 | B5: 名称及规格型号 | C5: 计量单位 | D5: 审计前账面值 | G5: 审计调整 | H5: 账面价值 | K5: 评估价值 | N5: 增值率% | O5: 备注
D6: 数量 | E6: 单价 | F6: 金额 | H6: 数量 | I6: 单价 | J6: 金额 | K6: 实际数量 | L6: 单价 | M6: 金额
E7: =IF(D7=0,"",F7/D7) | N7: =IF(J7=0,"",(M7-J7)/J7*100)
E8: =IF(D8=0,"",F8/D8) | N8: =IF(J8=0,"",(M8-J8)/J8*100)
E9: =IF(D9=0,"",F9/D9) | N9: =IF(J9=0,"",(M9-J9)/J9*100)
E10: =IF(D10=0,"",F10/D10) | N10: =IF(J10=0,"",(M10-J10)/J10*100)
E11: =IF(D11=0,"",F11/D11) | N11: =IF(J11=0,"",(M11-J11)/J11*100)
E12: =IF(D12=0,"",F12/D12) | N12: =IF(J12=0,"",(M12-J12)/J12*100)
E13: =IF(D13=0,"",F13/D13) | N13: =IF(J13=0,"",(M13-J13)/J13*100)
E14: =IF(D14=0,"",F14/D14) | N14: =IF(J14=0,"",(M14-J14)/J14*100)
E15: =IF(D15=0,"",F15/D15) | N15: =IF(J15=0,"",(M15-J15)/J15*100)
E16: =IF(D16=0,"",F16/D16) | N16: =IF(J16=0,"",(M16-J16)/J16*100)
E17: =IF(D17=0,"",F17/D17) | N17: =IF(J17=0,"",(M17-J17)/J17*100)
E18: =IF(D18=0,"",F18/D18) | N18: =IF(J18=0,"",(M18-J18)/J18*100)
... E25: =IF(D25=0,"",F25/D25) | N25: =IF(J25=0,"",(M25-J25)/J25*100)
A27: 合 计 | F27: =SUM(F7:F26) | J27: =SUM(J7:J26) | M27: =SUM(M7:M26) | N27: =IF(J27=0,"",(M27-J27)/J27*100)
A28: =封面!D11&封面!G11 | J28: ="评估人员："&封面!G20
A29: =CONCATENATE(封面!D13,封面!F13,封面!G13,封面!H13,封面!I13,封面!J13,封面!K13)

Sheet 发出商品
A1: 返回索引页 | B1: 返回
A2: 存货—发出商品评估明细表
A3: =CONCATENATE(封面!D9,封面!F9,封面!G9,封面!H9,封面!I9,封面!J9,封面!K9)
A4: =封面!D7&封面!F7 | P4: 金额单位：人民币元
A5: 序号 | B5: 商品名称 | C5: 对方单位名称 | D5: 计量单位 | E5: 审计前账面值 | H5: 审计调整 | I5: 账面价值 | L5: 评估价值 | O5: 增值率% | P5: 备注
E6: 数量 | F6: 单价 | G6: 金额 | I6: 数量 | J6: 单价 | K6: 金额 | L6: 实际数量 | M6: 单价 | N6: 金额 | W6: 税金及附加率 | X6: 销售费用率 | Y6: 营业利润率 | Z6: 所得税率 | AA6: 净利润率 | AB6: R | AC6: 评估单价
O7: =IF(K7=0,"",(N7-K7)/K7*100) | V7: =J7*(1+$AH$19) | W7: =AI14 | X7: =AI15 | Y7: =AI16 | AA7: =AI17 | AC7: =V7*(1-$W$7-$X$7-$Y$7*$Z$7-$AA$7*$AB$7) | AH7: 毛利率采用加权平均数计算=[（A1-B1）+(A23-B2)]/(A1+A2)
O8: =IF(K8=0,"",(N8-K8)/K8*100) | V8: =J8*(1+$AH$19) | AC8: =V8*(1-$W$7-$X$7-$Y$7*$Z$7-$AA$7*$AB$7)
O9: =IF(K9=0,"",(N9-K9)/K9*100) | V9: =J9*(1+$AH$19) | AC9: =V9*(1-$W$7-$X$7-$Y$7*$Z$7-$AA$7*$AB$7) | AD9: A | AE9: 营业收入 | AH9: =AF9+AG9
O10: =IF(K10=0,"",(N10-K10)/K10*100) | V10: =J10*(1+$AH$19) | AC10: =V10*(1-$W$7-$X$7-$Y$7*$Z$7-$AA$7*$AB$7) | AE10: 营业税金及附加
O11: =IF(K11=0,"",(N11-K11)/K11*100) | V11: =J11*(1+$AH$19) | AC11: =V11*(1-$W$7-$X$7-$Y$7*$Z$7-$AA$7*$AB$7) | AE11: 销售费用
O12: =IF(K12=0,"",(N12-K12)/K12*100) | V12: =J12*(1+$AH$19) | AC12: =V12*(1-$W$7-$X$7-$Y$7*$Z$7-$AA$7*$AB$7) | AE12: 营业利润
O13: =IF(K13=0,"",(N13-K13)/K13*100) | V13: =J13*(1+$AH$19) | AC13: =V13*(1-$W$7-$X$7-$Y$7*$Z$7-$AA$7*$AB$7) | AE13: 净利润
O14: =IF(K14=0,"",(N14-K14)/K14*100) | V14: =J14*(1+$AH$19) | AC14: =V14*(1-$W$7-$X$7-$Y$7*$Z$7-$AA$7*$AB$7) | AE14: 税金及附加率 | AF14: =AF10/AF9 | AG14: =AG10/AG9 | AI14: =(AF14+AG14+AH14)/2
O15: =IF(K15=0,"",(N15-K15)/K15*100) | V15: =J15*(1+$AH$19) | AC15: =V15*(1-$W$7-$X$7-$Y$7*$Z$7-$AA$7*$AB$7) | AE15: 销售费用率 | AF15: =AF11/AF9 | AG15: =AG11/AG9 | AI15: =(AF15+AG15+AH15)/2
O16: =IF(K16=0,"",(N16-K16)/K16*100) | V16: =J16*(1+$AH$19) | AC16: =V16*(1-$W$7-$X$7-$Y$7*$Z$7-$AA$7*$AB$7) | AE16: 营业利润率 | AF16: =AF12/AF9 | AG16: =AG12/AG9 | AI16: =(AF16+AG16+AH16)/2
O17: =IF(K17=0,"",(N17-K17)/K17*100) | V17: =J17*(1+$AH$19) | AC17: =V17*(1-$W$7-$X$7-$Y$7*$Z$7-$AA$7*$AB$7) | AE17: 净利润率 | AF17: =AF13/AF9 | AG17: =AG13/AG9 | AI17: =(AF17+AG17+AH17)/2
O18: =IF(K18=0,"",(N18-K18)/K18*100) | V18: =J18*(1+$AH$19) | AC18: =V18*(1-$W$7-$X$7-$Y$7*$Z$7-$AA$7*$AB$7) | AD18: B | AE18: 营业成本 | AH18: =AF18+AG18
O19: =IF(K19=0,"",(N19-K19)/K19*100) | V19: =J19*(1+$AH$19) | AC19: =V19*(1-$W$7-$X$7-$Y$7*$Z$7-$AA$7*$AB$7) | AF19: =(AF9-AF18)/AF9 | AG19: =(AG9-AG18)/AG9 | AH19: =0.3
O20: =IF(K20=0,"",(N20-K20)/K20*100) | V20: =J20*(1+$AH$19) | AC20: =V20*(1-$W$7-$X$7-$Y$7*$Z$7-$AA$7*$AB$7)
O21: =IF(K21=0,"",(N21-K21)/K21*100) | V21: =J21*(1+$AH$19) | AC21: =V21*(1-$W$7-$X$7-$Y$7*$Z$7-$AA$7*$AB$7)
O22: =IF(K22=0,"",(N22-K22)/K22*100) | V22: =J22*(1+$AH$19) | AC22: =V22*(1-$W$7-$X$7-$Y$7*$Z$7-$AA$7*$AB$7)
O23: =IF(K23=0,"",(N23-K23)/K23*100) | V23: =J23*(1+$AH$19) | AC23: =V23*(1-$W$7-$X$7-$Y$7*$Z$7-$AA$7*$AB$7)
O24: =IF(K24=0,"",(N24-K24)/K24*100) | V24: =J24*(1+$AH$19) | AC24: =V24*(1-$W$7-$X$7-$Y$7*$Z$7-$AA$7*$AB$7)
O25: =IF(K25=0,"",(N25-K25)/K25*100) | V25: =J25*(1+$AH$19) | AC25: =V25*(1-$W$7-$X$7-$Y$7*$Z$7-$AA$7*$AB$7)
O26: =IF(K26=0,"",(N26-K26)/K26*100) | V26: =J26*(1+$AH$19) | AC26: =V26*(1-$W$7-$X$7-$Y$7*$Z$7-$AA$7*$AB$7)
O27: =IF(K27=0,"",(N27-K27)/K27*100) | V27: =J27*(1+$AH$19) | AC27: =V27*(1-$W$7-$X$7-$Y$7*$Z$7-$AA$7*$AB$7)
O28: =IF(K28=0,"",(N28-K28)/K28*100) | V28: =J28*(1+$AH$19) | AC28: =V28*(1-$W$7-$X$7-$Y$7*$Z$7-$AA$7*$AB$7)
O29: =IF(K29=0,"",(N29-K29)/K29*100) | V29: =J29*(1+$AH$19) | AC29: =V29*(1-$W$7-$X$7-$Y$7*$Z$7-$AA$7*$AB$7)
O30: =IF(K30=0,"",(N30-K30)/K30*100) | V30: =J30*(1+$AH$19) | AC30: =V30*(1-$W$7-$X$7-$Y$7*$Z$7-$AA$7*$AB$7)
O31: =IF(K31=0,"",(N31-K31)/K31*100) | V31: =J31*(1+$AH$19) | AC31: =V31*(1-$W$7-$X$7-$Y$7*$Z$7-$AA$7*$AB$7)
... O34: =IF(K34=0,"",(N34-K34)/K34*100) | V34: =J34*(1+$AH$19) | AC34: =V34*(1-$W$7-$X$7-$Y$7*$Z$7-$AA$7*$AB$7)
F35: =IF(E35=0,"",G35/E35) | O35: =IF(K35=0,"",(N35-K35)/K35*100) | V35: =J36
V36: =J37
A37: 合 计 | G37: =SUM(G7:G36) | V37: =J38
A38: =封面!D11&封面!G11 | K38: ="评估人员："&封面!G20 | V38: =J39
A39: =CONCATENATE(封面!D13,封面!F13,封面!G13,封面!H13,封面!I13,封面!J13,封面!K13) | V39: =J40
V40: =J41
V41: =J42
V42: =J43
V43: =J44
V44: =J45
V45: =J46
V46: =J47
V47: =J48
V48: =J49
V49: =J50
V50: =J51
V51: =J52
... V98: =J99

Sheet 在用周转材料
A1: 返回索引页 | B1: 返回
A2: 存货—在用周转材料评估明细表
A3: =CONCATENATE(封面!D9,封面!F9,封面!G9,封面!H9,封面!I9,封面!J9,封面!K9)
A4: =封面!D7&封面!F7 | P4: 金额单位：人民币元
A5: 序号 | B5: 名称及规格型号 | C5: 启用日期 | D5: 原始入账价值 | E5: 计量单位 | F5: 审计前账面值 | H5: 审计调整 | I5: 账面价值 | K5: 实际数量 | L5: 评估价值 | O5: 增值率% | P5: 备注
F6: 数量 | G6: 金额 | I6: 数量 | J6: 金额 | L6: 单价 | M6: 成新率% | N6: 金额
N7: =K7*L7*M7/100 | O7: =IF(J7=0,"",(N7-J7)/J7*100)
N8: =K8*L8*M8/100 | O8: =IF(J8=0,"",(N8-J8)/J8*100)
N9: =K9*L9*M9/100 | O9: =IF(J9=0,"",(N9-J9)/J9*100)
N10: =K10*L10*M10/100 | O10: =IF(J10=0,"",(N10-J10)/J10*100)
N11: =K11*L11*M11/100 | O11: =IF(J11=0,"",(N11-J11)/J11*100)
N12: =K12*L12*M12/100 | O12: =IF(J12=0,"",(N12-J12)/J12*100)
N13: =K13*L13*M13/100 | O13: =IF(J13=0,"",(N13-J13)/J13*100)
N14: =K14*L14*M14/100 | O14: =IF(J14=0,"",(N14-J14)/J14*100)
N15: =K15*L15*M15/100 | O15: =IF(J15=0,"",(N15-J15)/J15*100)
N16: =K16*L16*M16/100 | O16: =IF(J16=0,"",(N16-J16)/J16*100)
N17: =K17*L17*M17/100 | O17: =IF(J17=0,"",(N17-J17)/J17*100)
N18: =K18*L18*M18/100 | O18: =IF(J18=0,"",(N18-J18)/J18*100)
... N25: =K25*L25*M25/100 | O25: =IF(J25=0,"",(N25-J25)/J25*100)
A27: 合 计 | G27: =SUM(G7:G26) | J27: =SUM(J7:J26) | N27: =SUM(N7:N26) | O27: =IF(J27=0,"",(N27-J27)/J27*100)
A28: =封面!D11&封面!G11 | J28: ="评估人员："&封面!G20
A29: =CONCATENATE(封面!D13,封面!F13,封面!G13,封面!H13,封面!I13,封面!J13,封面!K13)

Sheet 一年到期非流动资产
A1: 返回索引页 | B1: 返回
A2: 一年内到期的非流动资产评估明细表
A3: =CONCATENATE(封面!D9,封面!F9,封面!G9,封面!H9,封面!I9,封面!J9,封面!K9)
A4: =封面!D7&封面!F7 | J4: 金额单位：人民币元
A5: 序号 | B5: 项目及内容 | C5: 发生日期 | D5: 结算内容 | E5: 审计前账面值 | F5: 审计调整 | G5: 账面价值 | H5: 评估价值 | I5: 增值率% | J5: 备注
I6: =IF(G6=0,"",(H6-G6)/G6*100)
I7: =IF(G7=0,"",(H7-G7)/G7*100)
I8: =IF(G8=0,"",(H8-G8)/G8*100)
I9: =IF(G9=0,"",(H9-G9)/G9*100)
I10: =IF(G10=0,"",(H10-G10)/G10*100)
I11: =IF(G11=0,"",(H11-G11)/G11*100)
I12: =IF(G12=0,"",(H12-G12)/G12*100)
I13: =IF(G13=0,"",(H13-G13)/G13*100)
I14: =IF(G14=0,"",(H14-G14)/G14*100)
I15: =IF(G15=0,"",(H15-G15)/G15*100)
I16: =IF(G16=0,"",(H16-G16)/G16*100)
I17: =IF(G17=0,"",(H17-G17)/G17*100)
... I25: =IF(G25=0,"",(H25-G25)/G25*100)
A27: 合 计 | E27: =SUM(E6:E26) | G27: =SUM(G6:G26) | H27: =SUM(H6:H26) | I27: =IF(G27=0,"",(H27-G27)/G27*100)
A28: =封面!D11&封面!G11 | G28: ="评估人员："&封面!G20
A29: =CONCATENATE(封面!D13,封面!F13,封面!G13,封面!H13,封面!I13,封面!J13,封面!K13)

Sheet 其他流动资产
A1: 返回索引页 | B1: 返回
A2: 其他流动资产评估明细表
A3: =CONCATENATE(封面!D9,封面!F9,封面!G9,封面!H9,封面!I9,封面!J9,封面!K9)
A4: =封面!D7&封面!F7 | J4: 金额单位：人民币元
A5: 序号 | B5: 项目及内容 | C5: 发生日期 | D5: 结算内容 | E5: 审计前账面值 | F5: 审计调整 | G5: 账面价值 | H5: 评估价值 | I5: 增值率% | J5: 备注
I6: =IF(G6=0,"",(H6-G6)/G6*100)
I7: =IF(G7=0,"",(H7-G7)/G7*100)
I8: =IF(G8=0,"",(H8-G8)/G8*100)
I9: =IF(G9=0,"",(H9-G9)/G9*100)
I10: =IF(G10=0,"",(H10-G10)/G10*100)
I11: =IF(G11=0,"",(H11-G11)/G11*100)
I12: =IF(G12=0,"",(H12-G12)/G12*100)
I13: =IF(G13=0,"",(H13-G13)/G13*100)
I14: =IF(G14=0,"",(H14-G14)/G14*100)
I15: =IF(G15=0,"",(H15-G15)/G15*100)
I16: =IF(G16=0,"",(H16-G16)/G16*100)
I17: =IF(G17=0,"",(H17-G17)/G17*100)
... I25: =IF(G25=0,"",(H25-G25)/G25*100)
A27: 合 计 | E27: =SUM(E6:E26) | G27: =SUM(G6:G26) | H27: =SUM(H6:H26) | I27: =IF(G27=0,"",(H27-G27)/G27*100)
A28: =封面!D11&封面!G11 | G28: ="评估人员："&封面!G20
A29: =CONCATENATE(封面!D13,封面!F13,封面!G13,封面!H13,封面!I13,封面!J13,封面!K13)

Sheet 非流动资产汇总
A1: 返回索引页 | B1: 返回
A2: 非流动资产评估汇总表
A3: =CONCATENATE(封面!D9,封面!F9,封面!G9,封面!H9,封面!I9,封面!J9,封面!K9)
A4: =封面!D7&封面!F7 | G4: 金额单位：人民币元
A5: 编号 | B5: 科目名称 | C5: 审计前账面值 | D5: 账面价值 | E5: 评估价值 | F5: 增值额 | G5: 增值率%
A6: 4-1 | B6: 可供出售金融资产 | C6: =可供出售金融资产汇总!C27 | D6: =可供出售金融资产汇总!E27 | E6: =可供出售金融资产汇总!F27 | F6: =E6-D6 | G6: =IF(D6=0,"",F6/D6*100)
A7: 4-2 | B7: 持有至到期投资 | C7: =持有到期投资!H27 | D7: =持有到期投资!J27 | E7: =持有到期投资!K27 | F7: =E7-D7 | G7: =IF(D7=0,"",F7/D7*100)
A8: 4-3 | B8: 长期应收款 | C8: =长期应收!E27 | D8: =长期应收!G27 | E8: =长期应收!H27 | F8: =E8-D8 | G8: =IF(D8=0,"",F8/D8*100)
A9: 4-4 | B9: 长期股权投资 | C9: =股权投资!G27 | D9: =股权投资!I27 | E9: =股权投资!J27 | F9: =E9-D9 | G9: =IF(D9=0,"",F9/D9*100)
A10: 4-5 | B10: 投资性房地产 | C10: ='4-5-1投资性房地产'!K27+'4-5-2投资性房地产'!L27+'4-5-3投资性地产'!M27+'4-5-4投资性地产'!M27 | D10: ='4-5-1投资性房地产'!O27+'4-5-2投资性房地产'!N27+'4-5-3投资性地产'!O27+'4-5-4投资性地产'!O27 | E10: ='4-5-1投资性房地产'!R27+'4-5-2投资性房地产'!O27+'4-5-3投资性地产'!P27+'4-5-4投资性地产'!P27 | F10: =E10-D10 | G10: =IF(D10=0,"",F10/D10*100)
A11: 4-6 | B11: 固定资产 | C11: =固定资产汇总!D22 | D11: =固定资产汇总!F22 | E11: =固定资产汇总!H22 | F11: =E11-D11 | G11: =IF(D11=0,"",F11/D11*100)
A12: 4-7 | B12: 在建工程 | C12: =在建工程汇总!C27 | D12: =在建工程汇总!D27 | E12: =在建工程汇总!E27 | F12: =E12-D12 | G12: =IF(D12=0,"",F12/D12*100)
A13: 4-8 | B13: 工程物资 | C13: =工程物资!G27 | D13: =工程物资!K27 | E13: =工程物资!N27 | F13: =E13-D13 | G13: =IF(D13=0,"",F13/D13*100)
A14: 4-9 | B14: 固定资产清理 | C14: =固定资产清理!D27 | D14: =固定资产清理!F27 | E14: =固定资产清理!G27 | F14: =E14-D14 | G14: =IF(D14=0,"",F14/D14*100)
A15: 4-10 | B15: 生产性生物资产 | C15: =生产性生物资产!I27 | D15: =生产性生物资产!M27 | E15: =生产性生物资产!P27 | F15: =E15-D15 | G15: =IF(D15=0,"",F15/D15*100)
A16: 4-11 | B16: 油气资产 | C16: =油气资产!J27 | D16: =油气资产!N27 | E16: =油气资产!Q27 | F16: =E16-D16 | G16: =IF(D16=0,"",F16/D16*100)
A17: 4-12 | B17: 使用权资产 | D17: =使用权资产!H27 | E17: =使用权资产!J27 | F17: =使用权资产!K27
A18: 4-13 | B18: 无形资产 | C18: =无形资产汇总!C27 | D18: =无形资产汇总!D27 | E18: =无形资产汇总!E27 | F18: =E18-D18 | G18: =IF(D18=0,"",F18/D18*100)
A19: 4-14 | B19: 开发支出 | C19: =开发支出!D27 | D19: =开发支出!F27 | E19: =开发支出!G27 | F19: =E19-D19 | G19: =IF(D19=0,"",F19/D19*100)
A20: 4-15 | B20: 商誉 | C20: =商誉!D27 | D20: =商誉!F27 | E20: =商誉!G27 | F20: =E20-D20 | G20: =IF(D20=0,"",F20/D20*100)
A21: 4-16 | B21: 长期待摊费用 | C21: =长期待摊费用!F27 | D21: =长期待摊费用!H27 | E21: =长期待摊费用!J27 | F21: =E21-D21 | G21: =IF(D21=0,"",F21/D21*100)
A22: 4-17 | B22: 递延所得税资产 | C22: =递延所得税资产!D27 | D22: =递延所得税资产!F27 | E22: =递延所得税资产!G27 | F22: =E22-D22 | G22: =IF(D22=0,"",F22/D22*100)
A23: 4-18 | B23: 其他非流动资产 | C23: =其他非流动资产!D27 | D23: =其他非流动资产!F27 | E23: =其他非流动资产!G27 | F23: =E23-D23 | G23: =IF(D23=0,"",F23/D23*100)
A28: 4 | B28: 合计 | C28: =SUM(C6:C27) | D28: =SUM(D6:D27) | E28: =SUM(E6:E27) | F28: =SUM(F6:F27) | G28: =IF(D28=0,"",F28/D28*100)
A29: =封面!D11&封面!G11 | E29: ="评估人员："&封面!G22
A30: =CONCATENATE(封面!D13,封面!F13,封面!G13,封面!H13,封面!I13,封面!J13,封面!K13)
D32: =D11/10000 | E32: =E11/10000 | F32: =F11/10000
D33: =D18/10000 | E33: =E18/10000 | F33: =F18/10000
D34: =D28/10000 | E34: =E28/10000 | F34: =F28/10000

Sheet 可供出售金融资产汇总
A1: 返回索引页 | B1: 返回
A2: 可供出售金融资产评估汇总表
A3: =CONCATENATE(封面!D9,封面!F9,封面!G9,封面!H9,封面!I9,封面!J9,封面!K9)
A4: =封面!D7&封面!F7 | H4: 金额单位：人民币元
A5: 编号 | B5: 科目名称 | C5: 审计前账面值 | D5: 审计调整 | E5: 账面价值 | F5: 评估价值 | G5: 增值额 | H5: 增值率%
A6: 4-1-1 | B6: 可供出售金融资产-股票投资 | C6: ='可出售-股票'!I27 | E6: ='可出售-股票'!K27 | F6: ='可出售-股票'!L27 | G6: =F6-E6 | H6: =IF(E6=0,"",G6/E6*100)
A7: 4-1-2 | B7: 可供出售金融资产-债券投资 | C7: ='可出售-债券'!H27 | E7: ='可出售-债券'!J27 | F7: ='可出售-债券'!K27 | G7: =F7-E7 | H7: =IF(E7=0,"",G7/E7*100)
A8: 4-1-3 | B8: 可供出售金融资产-其他投资 | C8: ='可出售-其他'!H27 | E8: ='可出售-其他'!J27 | F8: ='可出售-其他'!K27 | G8: =F8-E8 | H8: =IF(E8=0,"",G8/E8*100)
A25: 4 | B25: 可供出售金融资产合计 | C25: =SUM(C6:C24) | E25: =SUM(E6:E24) | F25: =SUM(F6:F24) | G25: =SUM(G6:G24) | H25: =IF(E25=0,"",G25/E25*100)
A26: 4 | B26: 减：可供出售金融资产减值准备 | E26: =C26 | F26: 0 | G26: =F26-E26 | H26: =IF(E26=0,"",G26/E26*100)
A27: 4 | B27: 可供出售金融资产净额 | C27: =C25-C26 | E27: =E25-E26 | F27: =F25-F26 | G27: =G25-G26 | H27: =IF(E27=0,"",G27/E27*100)
A28: =封面!D11&封面!G11 | F28: ="评估人员："&封面!G22
A29: =CONCATENATE(封面!D13,封面!F13,封面!G13,封面!H13,封面!I13,封面!J13,封面!K13)

Sheet 可出售-股票
A1: 返回索引页 | B1: 返回
A2: 可供出售金融资产—股票投资评估明细表
A3: =CONCATENATE(封面!D9,封面!F9,封面!G9,封面!H9,封面!I9,封面!J9,封面!K9)
A4: =封面!D7&封面!F7 | N4: 金额单位：人民币元
A5: 序号 | B5: 被投资单位名称 | C5: 股票性质 | D5: 投资日期 | E5: 持股数量 | F5: 持股比例% | G5: 基准日市价 | H5: 取得成本 | I5: 审计前账面值 | J5: 审计调整 | K5: 账面价值 | L5: 评估价值 | M5: 增值率% | N5: 备注
M6: =IF(K6=0,"",(L6-K6)/K6*100)
M7: =IF(K7=0,"",(L7-K7)/K7*100)
M8: =IF(K8=0,"",(L8-K8)/K8*100)
M9: =IF(K9=0,"",(L9-K9)/K9*100)
M10: =IF(K10=0,"",(L10-K10)/K10*100)
M11: =IF(K11=0,"",(L11-K11)/K11*100)
M12: =IF(K12=0,"",(L12-K12)/K12*100)
M13: =IF(K13=0,"",(L13-K13)/K13*100)
M14: =IF(K14=0,"",(L14-K14)/K14*100)
M15: =IF(K15=0,"",(L15-K15)/K15*100)
M16: =IF(K16=0,"",(L16-K16)/K16*100)
M17: =IF(K17=0,"",(L17-K17)/K17*100)
... M25: =IF(K25=0,"",(L25-K25)/K25*100)
A27: 合 计 | I27: =SUM(I6:I26) | K27: =SUM(K6:K26) | L27: =SUM(L6:L26) | M27: =IF(K27=0,"",(L27-K27)/K27*100)
A28: =封面!D11&封面!G11 | K28: ="评估人员："&封面!G22
A29: =CONCATENATE(封面!D13,封面!F13,封面!G13,封面!H13,封面!I13,封面!J13,封面!K13)

Sheet 可出售-债券
A1: 返回索引页 | B1: 返回
A2: 可供出售金融资产—债券投资评估明细表
A3: =CONCATENATE(封面!D9,封面!F9,封面!G9,封面!H9,封面!I9,封面!J9,封面!K9)
A4: =封面!D7&封面!F7 | M4: 金额单位：人民币元
A5: 序号 | B5: 被投资单位名称 | C5: 债券种类 | D5: 发行日期 | E5: 到期日 | F5: 票面利率% | G5: 成本（面值） | H5: 审计前账面值 | I5: 审计调整 | J5: 账面价值 | K5: 评估价值 | L5: 增值率% | M5: 备注
L6: =IF(J6=0,"",(K6-J6)/J6*100)
L7: =IF(J7=0,"",(K7-J7)/J7*100)
L8: =IF(J8=0,"",(K8-J8)/J8*100)
L9: =IF(J9=0,"",(K9-J9)/J9*100)
L10: =IF(J10=0,"",(K10-J10)/J10*100)
L11: =IF(J11=0,"",(K11-J11)/J11*100)
L12: =IF(J12=0,"",(K12-J12)/J12*100)
L13: =IF(J13=0,"",(K13-J13)/J13*100)
L14: =IF(J14=0,"",(K14-J14)/J14*100)
L15: =IF(J15=0,"",(K15-J15)/J15*100)
L16: =IF(J16=0,"",(K16-J16)/J16*100)
L17: =IF(J17=0,"",(K17-J17)/J17*100)
... L25: =IF(J25=0,"",(K25-J25)/J25*100)
A27: 合 计 | H27: =SUM(H6:H26) | J27: =SUM(J6:J26) | K27: =SUM(K6:K26) | L27: =IF(J27=0,"",(K27-J27)/J27*100)
A28: =封面!D11&封面!G11 | J28: ="评估人员："&封面!G22
A29: =CONCATENATE(封面!D13,封面!F13,封面!G13,封面!H13,封面!I13,封面!J13,封面!K13)

Sheet 可出售-其他
A1: 返回索引页 | B1: 返回
A2: 可供出售金融资产—其他投资评估明细表
A3: =CONCATENATE(封面!D9,封面!F9,封面!G9,封面!H9,封面!I9,封面!J9,封面!K9)
A4: =封面!D7&封面!F7 | M4: 金额单位：人民币元
A5: 序号 | B5: 被投资单位名称 | C5: 金融资产名称 | D5: 投资日期 | E5: 持有数量 | F5: 基准日市价 | G5: 成本 | H5: 审计前账面值 | I5: 审计调整 | J5: 账面价值 | K5: 评估价值 | L5: 增值率% | M5: 备注
L6: =IF(J6=0,"",(K6-J6)/J6*100)
L7: =IF(J7=0,"",(K7-J7)/J7*100)
L8: =IF(J8=0,"",(K8-J8)/J8*100)
L9: =IF(J9=0,"",(K9-J9)/J9*100)
L10: =IF(J10=0,"",(K10-J10)/J10*100)
L11: =IF(J11=0,"",(K11-J11)/J11*100)
L12: =IF(J12=0,"",(K12-J12)/J12*100)
L13: =IF(J13=0,"",(K13-J13)/J13*100)
L14: =IF(J14=0,"",(K14-J14)/J14*100)
L15: =IF(J15=0,"",(K15-J15)/J15*100)
L16: =IF(J16=0,"",(K16-J16)/J16*100)
L17: =IF(J17=0,"",(K17-J17)/J17*100)
... L25: =IF(J25=0,"",(K25-J25)/J25*100)
A27: 合 计 | H27: =SUM(H6:H26) | J27: =SUM(J6:J26) | K27: =SUM(K6:K26) | L27: =IF(J27=0,"",(K27-J27)/J27*100)
A28: =封面!D11&封面!G11 | J28: ="评估人员："&封面!G22
A29: =CONCATENATE(封面!D13,封面!F13,封面!G13,封面!H13,封面!I13,封面!J13,封面!K13)

Sheet 持有到期投资
A1: 返回索引页 | B1: 返回
A2: 持有至到期投资评估明细表
A3: =CONCATENATE(封面!D9,封面!F9,封面!G9,封面!H9,封面!I9,封面!J9,封面!K9)
A4: =封面!D7&封面!F7 | M4: 金额单位：人民币元
A5: 序号 | B5: 被投资单位名称 | C5: 投资类别 | D5: 投资日期 | E5: 到期日 | F5: 票面利率% | G5: 投资成本 | H5: 审计前账面值 | I5: 审计调整 | J5: 账面价值 | K5: 评估价值 | L5: 增值率% | M5: 备注
L6: =IF(J6=0,"",(K6-J6)/J6*100)
L7: =IF(J7=0,"",(K7-J7)/J7*100)
L8: =IF(J8=0,"",(K8-J8)/J8*100)
L9: =IF(J9=0,"",(K9-J9)/J9*100)
L10: =IF(J10=0,"",(K10-J10)/J10*100)
L11: =IF(J11=0,"",(K11-J11)/J11*100)
L12: =IF(J12=0,"",(K12-J12)/J12*100)
L13: =IF(J13=0,"",(K13-J13)/J13*100)
L14: =IF(J14=0,"",(K14-J14)/J14*100)
L15: =IF(J15=0,"",(K15-J15)/J15*100)
L16: =IF(J16=0,"",(K16-J16)/J16*100)
L17: =IF(J17=0,"",(K17-J17)/J17*100)
... L24: =IF(J24=0,"",(K24-J24)/J24*100)
A25: 合 计 | H25: =SUM(H6:H24) | J25: =SUM(J6:J24) | K25: =SUM(K6:K24) | L25: =IF(J25=0,"",(K25-J25)/J25*100)
A26: 减：持有至到期投资减值准备 | J26: =H26 | L26: =IF(J26=0,"",(K26-J26)/J26*100)
A27: 净 额 | H27: =H25-H26 | J27: =J25-J26 | K27: =K25-K26 | L27: =IF(J27=0,"",(K27-J27)/J27*100)
A28: =封面!D11&封面!G11 | J28: ="评估人员："&封面!G22
A29: =CONCATENATE(封面!D13,封面!F13,封面!G13,封面!H13,封面!I13,封面!J13,封面!K13)

Sheet 长期应收
A1: 返回索引页 | B1: 返回
A2: 长期应收款评估明细表
A3: =CONCATENATE(封面!D9,封面!F9,封面!G9,封面!H9,封面!I9,封面!J9,封面!K9)
A4: =封面!D7&封面!F7 | J4: 金额单位：人民币元
A5: 序号 | B5: 欠款单位名称（结算对象） | C5: 业务内容 | D5: 发生日期 | E5: 审计前账面值 | F5: 审计调整 | G5: 账面价值 | H5: 评估价值 | I5: 增值率% | J5: 备注
H6: =G6 | I6: =IF(G6=0,"",(H6-G6)/G6*100)
I7: =IF(G7=0,"",(H7-G7)/G7*100)
I8: =IF(G8=0,"",(H8-G8)/G8*100)
I9: =IF(G9=0,"",(H9-G9)/G9*100)
I10: =IF(G10=0,"",(H10-G10)/G10*100)
I11: =IF(G11=0,"",(H11-G11)/G11*100)
I12: =IF(G12=0,"",(H12-G12)/G12*100)
I13: =IF(G13=0,"",(H13-G13)/G13*100)
I14: =IF(G14=0,"",(H14-G14)/G14*100)
I15: =IF(G15=0,"",(H15-G15)/G15*100)
I16: =IF(G16=0,"",(H16-G16)/G16*100)
I17: =IF(G17=0,"",(H17-G17)/G17*100)
I18: =IF(G18=0,"",(H18-G18)/G18*100)
... I23: =IF(G23=0,"",(H23-G23)/G23*100)
A24: 合 计 | E24: =SUM(E6:E23) | G24: =SUM(G6:G23) | H24: =SUM(H6:H23) | I24: =IF(G24=0,"",(H24-G24)/G24*100)
A25: 减：坏账准备 | G25: =E25 | I25: =IF(G25=0,"",(H25-G25)/G25*100)
A26: 减：评估风险损失 | I26: =IF(G26=0,"",(H26-G26)/G26*100)
A27: 净 额 | E27: =E24-E25-E26 | G27: =G24-G25-G26 | H27: =H24-H25-H26 | I27: =IF(G27=0,"",(H27-G27)/G27*100)
A28: =封面!D11&封面!G11 | G28: ="评估人员："&封面!G22
A29: =CONCATENATE(封面!D13,封面!F13,封面!G13,封面!H13,封面!I13,封面!J13,封面!K13)
B30: 注1： | C30: 注明账齡在一年以上的账款的可收回性，若有部分可能不能收回，请估计不能收回的金額，以供评估时作參考。
B31: 注2：“备注”栏填写方法： | C31: 1）欠款单位为关联方、总公司内部或本公司内部单位的，应在备注栏注明“关联方”、“总公司内部”、“内部单位”；
C32: 2） 涉诉款项应在备注中标明“涉诉”；
C33: 3）评估基准日后已部分或全部收回款项的，应注明日期及金额，如“2003年2月4日收回8,530.00元”；
C34: 4）填表单位认为其他应说明的事项

Sheet 股权投资
A1: 返回索引页 | B1: 返回
A2: 长期股权投资评估明细表
A3: =CONCATENATE(封面!D9,封面!F9,封面!G9,封面!H9,封面!I9,封面!J9,封面!K9)
A4: =封面!D7&封面!F7 | L4: 金额单位：人民币元
A5: 序号 | B5: 被投资单位名称 | C5: 投资日期 | D5: 协议投资期限 | E5: 持股比例% | F5: 投资成本 | G5: 审计前账面值 | H5: 审计调整 | I5: 账面价值 | J5: 评估价值 | K5: 增值率% | L5: 备注
K6: =IF(I6=0,"",(J6-I6)/I6*100)
K7: =IF(I7=0,"",(J7-I7)/I7*100)
K8: =IF(I8=0,"",(J8-I8)/I8*100)
K9: =IF(I9=0,"",(J9-I9)/I9*100)
K10: =IF(I10=0,"",(J10-I10)/I10*100)
K11: =IF(I11=0,"",(J11-I11)/I11*100)
K12: =IF(I12=0,"",(J12-I12)/I12*100)
K13: =IF(I13=0,"",(J13-I13)/I13*100)
K14: =IF(I14=0,"",(J14-I14)/I14*100)
K15: =IF(I15=0,"",(J15-I15)/I15*100)
K16: =IF(I16=0,"",(J16-I16)/I16*100)
K17: =IF(I17=0,"",(J17-I17)/I17*100)
... K24: =IF(I24=0,"",(J24-I24)/I24*100)
A25: 合 计 | G25: =SUM(G6:G24) | I25: =SUM(I6:I24) | J25: =SUM(J6:J24) | K25: =IF(I25=0,"",(J25-I25)/I25*100)
A26: 减：长期股权投资减值准备 | I26: =G26 | K26: =IF(I26=0,"",(J26-I26)/I26*100)
A27: 净 额 | G27: =G25-G26 | I27: =I25-I26 | J27: =J25-J26 | K27: =IF(I27=0,"",(J27-I27)/I27*100)
A28: =封面!D11&封面!G11 | I28: ="评估人员："&封面!G22
A29: =CONCATENATE(封面!D13,封面!F13,封面!G13,封面!H13,封面!I13,封面!J13,封面!K13)

Sheet 4-5-1投资性房地产
A1: 返回索引页 | B1: 返回
A2: 投资性房地产——房屋评估明细表
A3: （采用成本模式计量）
A4: =股权投资!A3
A5: 被评估单位（或者产权持有单位）： | S5: 金额单位：人民币元
A6: 序号
S8: =IF(Q8=0,"",(R8-O8)/O8*100)
S9: =IF(Q9=0,"",(R9-O9)/O9*100)
S10: =IF(Q10=0,"",(R10-O10)/O10*100)
S11: =IF(Q11=0,"",(R11-O11)/O11*100)
S12: =IF(Q12=0,"",(R12-O12)/O12*100)
S13: =IF(Q13=0,"",(R13-O13)/O13*100)
S14: =IF(Q14=0,"",(R14-O14)/O14*100)
S15: =IF(Q15=0,"",(R15-O15)/O15*100)
S16: =IF(Q16=0,"",(R16-O16)/O16*100)
S17: =IF(Q17=0,"",(R17-O17)/O17*100)
S18: =IF(Q18=0,"",(R18-O18)/O18*100)
S19: =IF(Q19=0,"",(R19-O19)/O19*100)
... S24: =IF(Q24=0,"",(R24-O24)/O24*100)
A25: 合 计 | J25: =SUM(J8:J24) | K25: =SUM(K8:K24) | L25: =SUM(L8:L24) | M25: =SUM(M8:M24) | N25: =SUM(N8:N24) | O25: =SUM(O8:O24) | P25: =SUM(P8:P24) | R25: =SUM(R8:R24) | S25: =IF(Q25=0,"",(R25-O25)/O25*100)
A26: 减：投资性房地产减值准备
A27: 合 计 | J27: =J25-J26 | K27: =K25-K26 | L27: =L25-L26 | M27: =M25-M26 | N27: =N25-N26 | O27: =O25-O26 | P27: =P25-P26 | R27: =R25-R26 | S27: =IF(Q27=0,"",(R27-O27)/O27*100)
A28: =封面!D11&封面!G11 | N28: ="评估人员："&封面!L22
A29: =CONCATENATE(封面!D13,封面!F13,封面!G13,封面!H13,封面!I13,封面!J13,封面!K13)

Sheet 4-5-2投资性房地产
A1: 返回索引页 | B1: 返回
A2: 投资性房地产——房屋评估明细表
A3: （采用公允价值模式计量）
A4: ='4-5-1投资性房地产'!A4:U4
A5: 被评估单位（或者产权持有单位）： | R5: 金额单位：人民币元
A6: 序号
A27: 合 计 | L27: =SUM(L8:L26) | N27: =SUM(N8:N26) | O27: =SUM(O8:O26)
A28: =封面!D11&封面!G11 | N28: ="评估人员："&封面!L22
A29: =CONCATENATE(封面!D13,封面!F13,封面!G13,封面!H13,封面!I13,封面!J13,封面!K13)

Sheet 4-5-3投资性地产
A1: 返回索引页 | B1: 返回
A2: 投资性房地产——土地使用权评估明细表
A3: （采用成本模式计量）
A4: ='4-5-2投资性房地产'!A4:R4
A5: 被评估单位（或者产权持有单位）： | S5: 金额单位：人民币元
A6: 序号
A25: 合 计
A26: 减：投资性房地产减值准备
A27: 合 计 | M27: =SUM(M7:M26) | O27: =SUM(O7:O26) | P27: =SUM(P7:P26)
A28: =封面!D11&封面!G11 | O28: ="评估人员："&封面!L22
A29: =CONCATENATE(封面!D13,封面!F13,封面!G13,封面!H13,封面!I13,封面!J13,封面!K13)

Sheet 4-5-4投资性地产
A1: 返回索引页 | B1: 返回
A2: 投资性房地产——土地使用权评估明细表
A3: （采用公允价值模式计量）
A4: ='4-5-3投资性地产'!A4:S4
A5: 被评估单位（或者产权持有单位）： | S5: 金额单位：人民币元
A6: 序号
A27: 合 计 | M27: =SUM(M7:M26) | O27: =SUM(O7:O26) | P27: =SUM(P7:P26)
A28: =封面!D11&封面!G11 | O28: ="评估人员："&封面!M22
A29: =CONCATENATE(封面!D13,封面!F13,封面!G13,封面!H13,封面!I13,封面!J13,封面!K13)

Sheet 固定资产汇总
A1: 返回索引页 | B1: 返回
A2: 固定资产评估汇总表
A3: =CONCATENATE(封面!D9,封面!F9,封面!G9,封面!H9,封面!I9,封面!J9,封面!K9)
A4: =封面!D7&封面!F7 | L4: 金额单位：人民币元
A5: 编号 | B5: 科目名称 | C5: 审计前账面值 | E5: 账面价值 | G5: 评估价值 | I5: 增值额 | K5: 增值率%
C6: 原值 | D6: 净值 | E6: 原值 | F6: 净值 | G6: 原值 | H6: 净值 | I6: 原值 | J6: 净值 | K6: 原值 | L6: 净值
B7: 房屋建筑物类合计 | C7: =SUM(C8:C10) | D7: =SUM(D8:D10) | E7: =SUM(E8:E10) | F7: =SUM(F8:F10) | G7: =SUM(G8:G10) | H7: =SUM(H8:H10) | I7: =SUM(I8:I10) | J7: =SUM(J8:J10) | K7: =IF(E7=0,"",I7/E7*100) | L7: =IF(F7=0,"",J7/F7*100)
A8: 4-6-1 | B8: 固定资产-房屋建筑物 | C8: =房屋建筑物!U35 | D8: =房屋建筑物!V35 | E8: =房屋建筑物!Y35 | F8: =房屋建筑物!Z35 | G8: =房屋建筑物!AA35 | H8: =房屋建筑物!AC35 | I8: =G8-E8 | J8: =H8-F8 | K8: =IF(E8=0,"",I8/E8*100) | L8: =IF(F8=0,"",J8/F8*100)
A9: 4-6-2 | B9: 固定资产-构筑物及其他辅助设施 | C9: =构筑物!J47 | D9: =构筑物!K47 | E9: =构筑物!N47 | F9: =构筑物!O47 | G9: =构筑物!P47 | H9: =构筑物!R47 | I9: =G9-E9 | J9: =H9-F9 | K9: =IF(E9=0,"",I9/E9*100) | L9: =IF(F9=0,"",J9/F9*100)
A10: 4-6-3 | B10: 固定资产-管道及沟槽 | C10: =管道沟槽!J27 | D10: =管道沟槽!K27 | E10: =管道沟槽!N27 | F10: =管道沟槽!O27 | G10: =管道沟槽!P27 | H10: =管道沟槽!R27 | I10: =G10-E10 | J10: =H10-F10 | K10: =IF(E10=0,"",I10/E10*100) | L10: =IF(F10=0,"",J10/F10*100)
A11: 4-6-4 | B11: 固定资产-井巷 | C11: =井巷!AI26 | D11: =井巷!AJ26 | E11: =井巷!AM26 | F11: =井巷!AN26
B13: 设备类合计 | C13: =SUM(C14:C16) | D13: =SUM(D14:D16) | E13: =SUM(E14:E16) | F13: =SUM(F14:F16) | G13: =SUM(G14:G16) | H13: =SUM(H14:H16) | I13: =SUM(I14:I16) | J13: =SUM(J14:J16) | K13: =IF(E13=0,"",I13/E13*100) | L13: =IF(F13=0,"",J13/F13*100)
A14: 4-6-4 | B14: 固定资产-机器设备 | C14: =机器设备!K234 | D14: =机器设备!L234 | E14: =机器设备!O234 | F14: =机器设备!P234 | G14: =机器设备!Q234 | H14: =机器设备!S234 | I14: =G14-E14 | J14: =H14-F14 | K14: =IF(E14=0,"",I14/E14*100) | L14: =IF(F14=0,"",J14/F14*100)
A15: 4-6-5 | B15: 固定资产-车辆 | C15: =车辆!K27 | D15: =车辆!L27 | E15: =车辆!O27 | F15: =车辆!P27 | G15: =车辆!Q27 | H15: =车辆!S27 | I15: =G15-E15 | J15: =H15-F15 | K15: =IF(E15=0,"",I15/E15*100) | L15: =IF(F15=0,"",J15/F15*100)
A16: 4-6-6 | B16: 固定资产-电子设备 | C16: =电子设备!L449 | D16: =电子设备!M449 | E16: =电子设备!P449 | F16: =电子设备!Q449 | G16: =电子设备!R449 | H16: =电子设备!T449 | I16: =G16-E16 | J16: =H16-F16 | K16: =IF(E16=0,"",I16/E16*100) | L16: =IF(F16=0,"",J16/F16*100)
A19: 4-6-7 | B19: 土地 | C19: =土地!J28 | D19: =土地!K28 | E19: =土地!N28 | F19: =土地!O28 | G19: =土地!P28 | H19: =土地!Q28 | I19: =G19-E19 | J19: =H19-F19 | K19: =IF(E19=0,"",I19/E19*100) | L19: =IF(F19=0,"",J19/F19*100)
B20: 固定资产合计 | C20: =SUM(C7,C13,C19) | D20: =SUM(D7,D13,D19) | E20: =SUM(E7,E13,E19) | F20: =SUM(F7,F13,F19) | G20: =SUM(G7,G13,G19) | H20: =SUM(H7,H13,H19) | I20: =SUM(I7,I13,I19) | J20: =SUM(J7,J13,J19) | K20: =IF(E20=0,"",I20/E20*100) | L20: =IF(F20=0,"",J20/F20*100)
B21: 减：固定资产减值准备 | F21: =D21 | H21: 0 | J21: =H21-F21 | K21: =IF(E21=0,"",I21/E21*100) | L21: =IF(F21=0,"",J21/F21*100)
B22: 固定资产 | C22: =C20-C21 | D22: =D20-D21 | E22: =E20-E21 | F22: =F20-F21 | G22: =G20-G21 | H22: =H20-H21 | I22: =I20-I21 | J22: =J20-J21 | K22: =IF(E22=0,"",I22/E22*100) | L22: =IF(F22=0,"",J22/F22*100)
A23: =封面!D11&封面!G11 | G23: ="评估人员："&封面!G24&" "
A24: =CONCATENATE(封面!D13,封面!F13,封面!G13,封面!H13,封面!I13,封面!J13,封面!K13)

Sheet 房屋建筑物
A1: 返回索引页 | B1: 返回
A2: 固定资产—房屋建筑物评估明细表
A3: =CONCATENATE(封面!D9,封面!F9,封面!G9,封面!H9,封面!I9,封面!J9,封面!K9)
A4: =封面!D7&封面!F7 | AF4: 金额单位：人民币元
A5: 序号 | B5: 权证编号 | C5: 建筑物名称 | D5: 位置 | E5: 对应土地证号 | F5: 结构 | G5: 檐高(m) | H5: 层高(m) | I5: 总层数 | J5: 所在层数 | K5: 朝向 | L5: 吊车吨位 | M5: 跨度(m) | N5: 柱距(m) | O5: 使用单位 | P5: 开工年月 | Q5: 建成 年月 | R5: 计量单位 | S5: 建筑 面积/容积 | T5: 成本单价(元/m2) | U5: 审计前账面值 | W5: 审计调整 | Y5: 账面价值 | AA5: 评估价值 | AD5: 增值率% | AE5: 评估单价(元/m2) | AF5: 备注 | AG5: 现场勘察简单记录 | AH5: 证载权利人
A7: 1 | AC7: =ROUND(S7*AE7,-1) | AD7: =IF(Z7=0,"",(AC7-Z7)/Z7*100) | AE7: =ROUND(2215.16,-1)
A8: 2 | AC8: =ROUND(S8*AE8,-1) | AD8: =IF(Z8=0,"",(AC8-Z8)/Z8*100) | AE8: =ROUND(1985,-1)
A9: 3 | AC9: =ROUND(S9*AE9,-1) | AD9: =IF(Z9=0,"",(AC9-Z9)/Z9*100) | AE9: =ROUND(1717.24,-1)
A10: 4 | AC10: =ROUND(S10*AE10,-1) | AD10: =IF(Z10=0,"",(AC10-Z10)/Z10*100) | AE10: =ROUND(2176.76,-1)
A11: 5 | AC11: =ROUND(S11*AE11,-1) | AD11: =IF(Z11=0,"",(AC11-Z11)/Z11*100) | AE11: =ROUND(3849.26,-1)
A12: 6 | AC12: =ROUND(S12*AE12,-1) | AD12: =IF(Z12=0,"",(AC12-Z12)/Z12*100) | AE12: =ROUND(AVERAGE(AE10:AE11),-1)
A13: 7 | AC13: =ROUND(S13*AE13,-1) | AD13: =IF(Z13=0,"",(AC13-Z13)/Z13*100) | AE13: =ROUND((AE9+AE8)/2,-1)
AA14: =ROUND(S14*AE14,-1) | AC14: =ROUND(AA14*AB14/100,0) | AD14: =IF(Z14=0,"",(AC14-Z14)/Z14*100)
AA15: =ROUND(S15*AE15,-1) | AC15: =ROUND(AA15*AB15/100,0) | AD15: =IF(Z15=0,"",(AC15-Z15)/Z15*100)
AA16: =ROUND(S16*AE16,-1) | AC16: =ROUND(AA16*AB16/100,0) | AD16: =IF(Z16=0,"",(AC16-Z16)/Z16*100)
AA17: =ROUND(S17*AE17,-1) | AC17: =ROUND(AA17*AB17/100,0) | AD17: =IF(Z17=0,"",(AC17-Z17)/Z17*100)
AA18: =ROUND(S18*AE18,-1) | AC18: =ROUND(AA18*AB18/100,0) | AD18: =IF(Z18=0,"",(AC18-Z18)/Z18*100)
AA19: =ROUND(S19*AE19,-1) | AC19: =ROUND(AA19*AB19/100,0) | AD19: =IF(Z19=0,"",(AC19-Z19)/Z19*100)
AA20: =ROUND(S20*AE20,-1) | AC20: =ROUND(AA20*AB20/100,0) | AD20: =IF(Z20=0,"",(AC20-Z20)/Z20*100)
AA21: =ROUND(S21*AE21,-1) | AC21: =ROUND(AA21*AB21/100,0) | AD21: =IF(Z21=0,"",(AC21-Z21)/Z21*100)
AA22: =ROUND(S22*AE22,-1) | AC22: =ROUND(AA22*AB22/100,0) | AD22: =IF(Z22=0,"",(AC22-Z22)/Z22*100)
AA23: =ROUND(S23*AE23,-1) | AC23: =ROUND(AA23*AB23/100,0) | AD23: =IF(Z23=0,"",(AC23-Z23)/Z23*100)
AA24: =ROUND(S24*AE24,-1) | AC24: =ROUND(AA24*AB24/100,0) | AD24: =IF(Z24=0,"",(AC24-Z24)/Z24*100)
AA25: =ROUND(S25*AE25,-1) | AC25: =ROUND(AA25*AB25/100,0) | AD25: =IF(Z25=0,"",(AC25-Z25)/Z25*100)
... AA28: =ROUND(S28*AE28,-1) | AC28: =ROUND(AA28*AB28/100,0) | AD28: =IF(Z28=0,"",(AC28-Z28)/Z28*100)
T29: =IF(S29=0,"",U29/S29) | AA29: =ROUND(S29*AE29,-1) | AC29: =ROUND(AA29*AB29/100,0) | AD29: =IF(Z29=0,"",(AC29-Z29)/Z29*100)
T30: =IF(S30=0,"",U30/S30) | AA30: =ROUND(S30*AE30,-1) | AC30: =ROUND(AA30*AB30/100,0) | AD30: =IF(Z30=0,"",(AC30-Z30)/Z30*100)
T31: =IF(S31=0,"",U31/S31) | AA31: =ROUND(S31*AE31,-1) | AC31: =ROUND(AA31*AB31/100,0) | AD31: =IF(Z31=0,"",(AC31-Z31)/Z31*100)
T32: =IF(S32=0,"",U32/S32) | AA32: =ROUND(S32*AE32,-1) | AC32: =ROUND(AA32*AB32/100,0) | AD32: =IF(Z32=0,"",(AC32-Z32)/Z32*100)
T33: =IF(S33=0,"",U33/S33) | AA33: =ROUND(S33*AE33,-1) | AC33: =ROUND(AA33*AB33/100,0) | AD33: =IF(Z33=0,"",(AC33-Z33)/Z33*100)
A35: 合 计 | U35: =SUM(U7:U34) | V35: =SUM(V7:V34) | Y35: =SUM(Y7:Y34) | Z35: =SUM(Z7:Z34) | AA35: =SUM(AA7:AA34) | AC35: =SUM(AC7:AC34) | AD35: =IF(Z35=0,"",(AC35-Z35)/Z35*100)
A36: =封面!D11&封面!G11 | Y36: ="评估人员："&封面!G24
A37: =CONCATENATE(封面!D13,封面!F13,封面!G13,封面!H13,封面!I13,封面!J13,封面!K13)

Sheet 构筑物
A1: 返回索引页 | B1: 返回
A2: 固定资产—构筑物及其他辅助设施评估明细表
A3: =CONCATENATE(封面!D9,封面!F9,封面!G9,封面!H9,封面!I9,封面!J9,封面!K9)
A4: =封面!D7&封面!F7 | U4: 金额单位：人民币元
A5: 序号 | B5: 名称 | C5: 结构 | D5: 使用单位 | E5: 建成 年月 | F5: 长度 (m) | G5: 宽度 (m) | H5: 计量单位 | I5: 面积体积m2或m3 | J5: 审计前账面值 | L5: 审计调整 | N5: 账面价值 | P5: 评估价值 | S5: 增值率% | T5: 评估单价(元/m2) | U5: 备注
J6: 原值 | K6: 净值 | L6: 原值 | M6: 净值 | N6: 原值 | O6: 净值 | P6: 原值 | Q6: 成新率% | R6: 净值
R7: =ROUND(P7*Q7/100,0) | S7: =IF(O7=0,"",(R7-O7)/O7*100)
R8: =ROUND(P8*Q8/100,0) | S8: =IF(O8=0,"",(R8-O8)/O8*100)
R9: =ROUND(P9*Q9/100,0) | S9: =IF(O9=0,"",(R9-O9)/O9*100)
R10: =ROUND(P10*Q10/100,0) | S10: =IF(O10=0,"",(R10-O10)/O10*100)
R11: =ROUND(P11*Q11/100,0) | S11: =IF(O11=0,"",(R11-O11)/O11*100)
R12: =ROUND(P12*Q12/100,0) | S12: =IF(O12=0,"",(R12-O12)/O12*100)
R13: =ROUND(P13*Q13/100,0) | S13: =IF(O13=0,"",(R13-O13)/O13*100)
R14: =ROUND(P14*Q14/100,0) | S14: =IF(O14=0,"",(R14-O14)/O14*100)
R15: =ROUND(P15*Q15/100,0) | S15: =IF(O15=0,"",(R15-O15)/O15*100)
R16: =ROUND(P16*Q16/100,0) | S16: =IF(O16=0,"",(R16-O16)/O16*100)
R17: =ROUND(P17*Q17/100,0) | S17: =IF(O17=0,"",(R17-O17)/O17*100)
R18: =ROUND(P18*Q18/100,0) | S18: =IF(O18=0,"",(R18-O18)/O18*100)
... R45: =ROUND(P45*Q45/100,0) | S45: =IF(O45=0,"",(R45-O45)/O45*100)
A47: 合 计 | J47: =SUM(J7:J46) | K47: =SUM(K7:K46) | N47: =SUM(N7:N46) | O47: =SUM(O7:O46) | P47: =SUM(P7:P46) | R47: =SUM(R7:R46) | S47: =IF(O47=0,"",(R47-O47)/O47*100)
A48: =封面!D11&封面!G11 | N48: ="评估人员："&封面!G24
A49: =CONCATENATE(封面!D13,封面!F13,封面!G13,封面!H13,封面!I13,封面!J13,封面!K13)

Sheet 井巷
A1: 返回索引页 | B1: 返回 | C1: 返回
A2: 固定资产—井巷工程清查评估明细表
A3: 评估基准日：2009年10月31日
A4: 被评估单位： | AS4: 金额单位：人民币元
A5: 序号 | B5: 资产编号 | C5: 井巷工程名称 | D5: 施工阶段 | E5: 巷道类型 | F5: 井筒斜长（m) | G5: 煤岩类别 | H5: 岩石硬度系数 | I5: 支护方式 | J5: 材质 | K5: 锚杆 | M5: 锚索 | O5: 网片(张数/m) | S5: 轨型kg/m | T5: 轨距㎜ | U5: 轨枕 | V5: 掘进直径 | W5: 掘进断面高度(m) | X5: 掘进断面宽度(m) | Y5: 支护厚度(㎜) | Z5: 掘进断面(㎡) | AA5: 巷道倾角(度) | AB5: 巷道长度(m) | AC5: 硐室掘进体积(m3) | AD5: 竣工年月 | AE5: 尚可使用年限 | AF5: 该井项已经开采储量 | AG5: 该井巷尚可开采储量(保有储量） | AH5: 标记 | AI5: 审计前账面价值 | AK5: 调整分录 | AM5: 账面价值 | AO5: 评估价值 | AR5: 增值率% | AS5: 备注
AM7: =AI7+AK7 | AN7: =AJ7+AL7
AM8: =AI8+AK8 | AN8: =AJ8+AL8
AM9: =AI9+AK9 | AN9: =AJ9+AL9
AM10: =AI10+AK10 | AN10: =AJ10+AL10
AM11: =AI11+AK11 | AN11: =AJ11+AL11
AM12: =AI12+AK12 | AN12: =AJ12+AL12
AM13: =AI13+AK13 | AN13: =AJ13+AL13
AM14: =AI14+AK14 | AN14: =AJ14+AL14
AM15: =AI15+AK15 | AN15: =AJ15+AL15
AM16: =AI16+AK16 | AN16: =AJ16+AL16
AM17: =AI17+AK17 | AN17: =AJ17+AL17
AM18: =AI18+AK18 | AN18: =AJ18+AL18
... AM24: =AI24+AK24 | AN24: =AJ24+AL24
AM25: =AI25+AK25 | AN25: =AJ25+AL25 | AR25: =IF(AN25=0,"",(AQ25-AN25)/AN25*100)
A26: 合 计 | AI26: =SUM(AI9:AI25) | AJ26: =SUM(AJ9:AJ25) | AM26: =SUM(AM9:AM25) | AN26: =SUM(AN9:AN25) | AO26: =SUM(AO25:AO25) | AQ26: =SUM(AQ25:AQ25) | AR26: =IF(AN26=0,"",(AQ26-AN26)/AN26*100)
A27: 被评估单位填表人： | AO27: 评估人员：
A28: 填表日期：2009年11月5日

Sheet Sheet1

Sheet 管道沟槽
A1: 返回索引页 | B1: 返回
A2: 固定资产—管道和沟槽评估明细表
A3: =CONCATENATE(封面!D9,封面!F9,封面!G9,封面!H9,封面!I9,封面!J9,封面!K9)
A4: =封面!D7&封面!F7 | T4: 金额单位：人民币元
A5: 序号 | B5: 名称 | C5: 使用单位 | D5: 长度 (m) | E5: 漕深 (m) | F5: 沟宽*沟厚(mm*mm) 管径*壁厚(mm*mm) | G5: 材质 | H5: 绝缘方式 | I5: 建成年月 | J5: 审计前账面值 | L5: 审计调整 | N5: 账面价值 | P5: 评估价值 | S5: 增值率% | T5: 备注
J6: 原值 | K6: 净值 | L6: 原值 | M6: 净值 | N6: 原值 | O6: 净值 | P6: 原值 | Q6: 成新率% | R6: 净值
R7: =ROUND(P7*Q7/100,0) | S7: =IF(O7=0,"",(R7-O7)/O7*100)
R8: =ROUND(P8*Q8/100,0) | S8: =IF(O8=0,"",(R8-O8)/O8*100)
R9: =ROUND(P9*Q9/100,0) | S9: =IF(O9=0,"",(R9-O9)/O9*100)
R10: =ROUND(P10*Q10/100,0) | S10: =IF(O10=0,"",(R10-O10)/O10*100)
R11: =ROUND(P11*Q11/100,0) | S11: =IF(O11=0,"",(R11-O11)/O11*100)
R12: =ROUND(P12*Q12/100,0) | S12: =IF(O12=0,"",(R12-O12)/O12*100)
R13: =ROUND(P13*Q13/100,0) | S13: =IF(O13=0,"",(R13-O13)/O13*100)
R14: =ROUND(P14*Q14/100,0) | S14: =IF(O14=0,"",(R14-O14)/O14*100)
R15: =ROUND(P15*Q15/100,0) | S15: =IF(O15=0,"",(R15-O15)/O15*100)
R16: =ROUND(P16*Q16/100,0) | S16: =IF(O16=0,"",(R16-O16)/O16*100)
R17: =ROUND(P17*Q17/100,0) | S17: =IF(O17=0,"",(R17-O17)/O17*100)
R18: =ROUND(P18*Q18/100,0) | S18: =IF(O18=0,"",(R18-O18)/O18*100)
... R25: =ROUND(P25*Q25/100,0) | S25: =IF(O25=0,"",(R25-O25)/O25*100)
A27: 合 计 | J27: =SUM(J7:J26) | K27: =SUM(K7:K26) | N27: =SUM(N7:N26) | O27: =SUM(O7:O26) | P27: =SUM(P7:P26) | R27: =SUM(R7:R26) | S27: =IF(O27=0,"",(R27-O27)/O27*100)
A28: =封面!D11&封面!G11 | N28: ="评估人员："&封面!G24
A29: =CONCATENATE(封面!D13,封面!F13,封面!G13,封面!H13,封面!I13,封面!J13,封面!K13)

Sheet 机器设备
A1: 返回索引页 | B1: 返回
A2: 固定资产—机器设备评估明细表
A3: =CONCATENATE(封面!D9,封面!F9,封面!G9,封面!H9,封面!I9,封面!J9,封面!K9)
A4: =封面!D7&封面!F7 | U4: 金额单位：人民币元
A5: 序号 | B5: 设备编号 | C5: 设备名称 | D5: 规格型号 | E5: 使用单位 | F5: 生产厂家 | G5: 计量单位 | H5: 数量 | I5: 购置日期 | J5: 启用日期 | K5: 审计前账面值 | M5: 审计调整 | O5: 账面价值 | Q5: 评估价值 | T5: 增值率% | U5: 备注 | W5: 已使用 | X5: 理论成新率 | Y5: 账面单价 | Z5: 购置单价(含税) | AC5: 增值税进项税额 | AD5: 不含税重置单价 | AE5: 含税重置全价 | AF5: 不含税重置全价
K6: 原值 | L6: 净值 | M6: 原值 | N6: 净值 | O6: 原值 | P6: 净值 | Q6: 原值 | R6: 成新率% | S6: 净值 | V6: 经济年限 | AA6: 物价指数 | AB6: 贬值率
R7: =X7*100 | S7: =ROUND(Q7*R7/100,0) | T7: =IF(P7=0,"",(S7-P7)/P7*100) | W7: =($V$5-J7)/365 | X7: =(V7-W7)/V7 | Z7: =Y7 | AC7: =Z7*0.13/(1+0.13) | AD7: =Z7-AC7 | AE7: =Z7*H7 | AF7: =ROUND(AD7*H7,-2) | AG7: https://b2b.baidu.com/land?url=https%3A%2F%2Fwww.912688.com%2Fsupply%2F339710698.html%3Fbdb2b8a2d%3D2439046228181354518&query=%E5%9B%9B%E6%9F%B1%E8%A3%81%E5%88%87%E6%9C%BAXclp3&category=%E6%9C%BA%E6%A2%B0%E5%B7%A5%E4%B8%9A%3B%E7%9A%AE%E9%9D%A9%E5%8A%A0%E5%B7%A5%E8%AE%BE%E5%A4%87%3B%E8%A3%81%E6%96%AD%E6%9C%BA
R8: =X8*100 | S8: =ROUND(Q8*R8/100,0) | T8: =IF(P8=0,"",(S8-P8)/P8*100) | W8: =($V$5-J8)/365 | X8: =(V8-W8)/V8 | Z8: =Y8 | AC8: =Z8*0.13/(1+0.13) | AD8: =Z8-AC8 | AE8: =Z8*H8 | AF8: =ROUND(AD8*H8,-2) | AG8: https://b2b.baidu.com/land?url=https%3A%2F%2Fwww.china.cn%2Frongjieji%2F3740659375.html%3Fbdb2b8a2d%3D2438987942149274047&query=高周波油压机8kw&category=机械工业%3B电子产品制造设备%3B熔接机
R9: =X9*100 | S9: =ROUND(Q9*R9/100,0) | T9: =IF(P9=0,"",(S9-P9)/P9*100) | W9: =($V$5-J9)/365 | X9: =(V9-W9)/V9 | Z9: =Y9 | AC9: =Z9*0.13/(1+0.13) | AD9: =Z9-AC9 | AE9: =Z9*H9 | AF9: =ROUND(AD9*H9,-2) | AG9: https://b2b.baidu.com/land?url=https%3A%2F%2Fwww.912688.com%2Fsupply%2F104657120.html%3Fbdb2b8a2d%3D2438915230767428949&query=%E7%94%B5%E8%84%91%E8%8A%B1%E6%A0%B7%E6%9C%BA&category=%E6%9C%BA%E6%A2%B0%E5%B7%A5%E4%B8%9A%3B%E6%9C%8D%E8%A3%85%E6%9C%BA%E6%A2%B0%E8%AE%BE%E5%A4%87%3B%E7%BC%9D%E4%B8%AD%E8%AE%BE%E5%A4%87
R10: =X10*100 | S10: =ROUND(Q10*R10/100,0) | T10: =IF(P10=0,"",(S10-P10)/P10*100) | W10: =($V$5-J10)/365 | X10: =(V10-W10)/V10 | Z10: =Y10 | AC10: =Z10*0.13/(1+0.13) | AD10: =Z10-AC10 | AE10: =Z10*H10 | AF10: =ROUND(AD10*H10,-2) | AG10: https://detail.1688.com/offer/609784199942.html?spm=a261b.2187593.1998088710.31.6dd25256uj9vDD
R11: =X11*100 | S11: =ROUND(Q11*R11/100,0) | T11: =IF(P11=0,"",(S11-P11)/P11*100) | W11: =($V$5-J11)/365 | X11: =(V11-W11)/V11 | Z11: =Y11 | AC11: =Z11*0.13/(1+0.13) | AD11: =Z11-AC11 | AE11: =Z11*H11 | AF11: =ROUND(AD11*H11,-2) | AG11: https://detail.1688.com/offer/533989812836.html?spm=a261b.2187593.1998088710.1.7fed147csppu9q&tracelog=p4p&clickid=e1b987a899564175a53991eb3d153598&sessionid=c37e2129882030ed537098fd0c9482d8
T12: =IF(P12=0,"",(S12-P12)/P12*100) | W12: =($V$5-J12)/365 | X12: =(V12-W12)/V12 | Z12: =Y12 | AC12: =Z12*0.13/(1+0.13) | AD12: =Z12-AC12 | AE12: =Z12*H12 | AF12: =ROUND(AD12*H12,-2)
T13: =IF(P13=0,"",(S13-P13)/P13*100) | W13: =($V$5-J13)/365 | X13: =(V13-W13)/V13 | Z13: =Y13 | AC13: =Z13*0.13/(1+0.13) | AD13: =Z13-AC13 | AE13: =Z13*H13 | AF13: =ROUND(AD13*H13,-2)
T14: =IF(P14=0,"",(S14-P14)/P14*100) | W14: =($V$5-J14)/365 | X14: =(V14-W14)/V14 | Z14: =Y14 | AC14: =Z14*0.13/(1+0.13) | AD14: =Z14-AC14 | AE14: =Z14*H14 | AF14: =ROUND(AD14*H14,-2)
T15: =IF(P15=0,"",(S15-P15)/P15*100) | W15: =($V$5-J15)/365 | X15: =(V15-W15)/V15 | Z15: =Y15 | AC15: =Z15*0.13/(1+0.13) | AD15: =Z15-AC15 | AE15: =Z15*H15 | AF15: =ROUND(AD15*H15,-2)
T16: =IF(P16=0,"",(S16-P16)/P16*100) | W16: =($V$5-J16)/365 | X16: =(V16-W16)/V16 | Z16: =Y16 | AC16: =Z16*0.13/(1+0.13) | AD16: =Z16-AC16 | AE16: =Z16*H16 | AF16: =ROUND(AD16*H16,-2)
T17: =IF(P17=0,"",(S17-P17)/P17*100) | W17: =($V$5-J17)/365 | X17: =(V17-W17)/V17 | Z17: =Y17 | AC17: =Z17*0.13/(1+0.13) | AD17: =Z17-AC17 | AE17: =Z17*H17 | AF17: =ROUND(AD17*H17,-2)
T18: =IF(P18=0,"",(S18-P18)/P18*100) | W18: =($V$5-J18)/365 | X18: =(V18-W18)/V18 | Z18: =Y18 | AC18: =Z18*0.13/(1+0.13) | AD18: =Z18-AC18 | AE18: =Z18*H18 | AF18: =ROUND(AD18*H18,-2)
T19: =IF(P19=0,"",(S19-P19)/P19*100) | W19: =($V$5-J19)/365 | X19: =(V19-W19)/V19 | Z19: =Y19 | AC19: =Z19*0.13/(1+0.13) | AD19: =Z19-AC19 | AE19: =Z19*H19 | AF19: =ROUND(AD19*H19,-2)
T20: =IF(P20=0,"",(S20-P20)/P20*100) | W20: =($V$5-J20)/365 | X20: =(V20-W20)/V20 | Z20: =Y20 | AC20: =Z20*0.13/(1+0.13) | AD20: =Z20-AC20 | AE20: =Z20*H20 | AF20: =ROUND(AD20*H20,-2)
T21: =IF(P21=0,"",(S21-P21)/P21*100) | W21: =($V$5-J21)/365 | X21: =(V21-W21)/V21 | Z21: =Y21 | AC21: =Z21*0.13/(1+0.13) | AD21: =Z21-AC21 | AE21: =Z21*H21 | AF21: =ROUND(AD21*H21,-2)
T22: =IF(P22=0,"",(S22-P22)/P22*100) | W22: =($V$5-J22)/365 | X22: =(V22-W22)/V22 | Z22: =Y22 | AC22: =Z22*0.13/(1+0.13) | AD22: =Z22-AC22 | AE22: =Z22*H22 | AF22: =ROUND(AD22*H22,-2)
T23: =IF(P23=0,"",(S23-P23)/P23*100) | W23: =($V$5-J23)/365 | X23: =(V23-W23)/V23 | Z23: =Y23 | AC23: =Z23*0.13/(1+0.13) | AD23: =Z23-AC23 | AE23: =Z23*H23 | AF23: =ROUND(AD23*H23,-2)
W24: =($V$5-J24)/365 | X24: =(V24-W24)/V24 | Z24: =Y24 | AC24: =Z24*0.13/(1+0.13) | AD24: =Z24-AC24 | AE24: =Z24*H24 | AF24: =ROUND(AD24*H24,-2)
W25: =($V$5-J25)/365 | X25: =(V25-W25)/V25 | Z25: =Y25 | AC25: =Z25*0.13/(1+0.13) | AD25: =Z25-AC25 | AE25: =Z25*H25 | AF25: =ROUND(AD25*H25,-2)
T26: =IF(P26=0,"",(S26-P26)/P26*100) | W26: =($V$5-J26)/365 | X26: =(V26-W26)/V26 | Z26: =Y26 | AC26: =Z26*0.13/(1+0.13) | AD26: =Z26-AC26 | AE26: =Z26*H26 | AF26: =ROUND(AD26*H26,-2)
W27: =($V$5-J27)/365 | X27: =(V27-W27)/V27 | Z27: =Y27 | AC27: =Z27*0.13/(1+0.13) | AD27: =Z27-AC27 | AE27: =Z27*H27 | AF27: =ROUND(AD27*H27,-2)
W28: =($V$5-J28)/365 | X28: =(V28-W28)/V28 | Z28: =Y28 | AC28: =Z28*0.13/(1+0.13) | AD28: =Z28-AC28 | AE28: =Z28*H28 | AF28: =ROUND(AD28*H28,-2)
W29: =($V$5-J29)/365 | X29: =(V29-W29)/V29 | Z29: =Y29 | AC29: =Z29*0.13/(1+0.13) | AD29: =Z29-AC29 | AE29: =Z29*H29 | AF29: =ROUND(AD29*H29,-2)
W30: =($V$5-J30)/365 | X30: =(V30-W30)/V30 | Z30: =Y30 | AC30: =Z30*0.13/(1+0.13) | AD30: =Z30-AC30 | AE30: =Z30*H30 | AF30: =ROUND(AD30*H30,-2)
W31: =($V$5-J31)/365 | X31: =(V31-W31)/V31 | Z31: =Y31 | AC31: =Z31*0.13/(1+0.13) | AD31: =Z31-AC31 | AE31: =Z31*H31 | AF31: =ROUND(AD31*H31,-2)
W32: =($V$5-J32)/365 | X32: =(V32-W32)/V32 | Z32: =Y32 | AC32: =Z32*0.13/(1+0.13) | AD32: =Z32-AC32 | AE32: =Z32*H32 | AF32: =ROUND(AD32*H32,-2)
W33: =($V$5-J33)/365 | X33: =(V33-W33)/V33 | Z33: =Y33 | AC33: =Z33*0.13/(1+0.13) | AD33: =Z33-AC33 | AE33: =Z33*H33 | AF33: =ROUND(AD33*H33,-2)
W34: =($V$5-J34)/365 | X34: =(V34-W34)/V34 | Z34: =Y34 | AC34: =Z34*0.13/(1+0.13) | AD34: =Z34-AC34 | AE34: =Z34*H34 | AF34: =ROUND(AD34*H34,-2)
W35: =($V$5-J35)/365 | X35: =(V35-W35)/V35 | Z35: =Y35 | AC35: =Z35*0.13/(1+0.13) | AD35: =Z35-AC35 | AE35: =Z35*H35 | AF35: =ROUND(AD35*H35,-2)
W36: =($V$5-J36)/365 | X36: =(V36-W36)/V36 | Z36: =Y36 | AC36: =Z36*0.13/(1+0.13) | AD36: =Z36-AC36 | AE36: =Z36*H36 | AF36: =ROUND(AD36*H36,-2)
W37: =($V$5-J37)/365 | X37: =(V37-W37)/V37 | Z37: =Y37 | AC37: =Z37*0.13/(1+0.13) | AD37: =Z37-AC37 | AE37: =Z37*H37 | AF37: =ROUND(AD37*H37,-2)
W38: =($V$5-J38)/365 | X38: =(V38-W38)/V38 | Z38: =Y38 | AC38: =Z38*0.13/(1+0.13) | AD38: =Z38-AC38 | AE38: =Z38*H38 | AF38: =ROUND(AD38*H38,-2)
... W232: =($V$5-J232)/365 | X232: =(V232-W232)/V232 | Z232: =Y232 | AC232: =Z232*0.13/(1+0.13) | AD232: =Z232-AC232 | AE232: =Z232*H232 | AF232: =ROUND(AD232*H232,-2)
A234: 合 计 | K234: =SUM(K7:K233) | L234: =SUM(L7:L233) | O234: =SUM(O7:O233) | P234: =SUM(P7:P233) | Q234: =SUM(Q7:Q233) | S234: =SUM(S7:S233) | T234: =IF(P234=0,"",(S234-P234)/P234*100)
A235: =封面!D11&封面!G11 | O235: ="评估人员："&封面!G26
A236: =CONCATENATE(封面!D13,封面!F13,封面!G13,封面!H13,封面!I13,封面!J13,封面!K13)

Sheet 车辆
A1: 返回索引页 | B1: 返回
A2: 固定资产—车辆评估明细表
A3: =CONCATENATE(封面!D9,封面!F9,封面!G9,封面!H9,封面!I9,封面!J9,封面!K9)
A4: =封面!D7&封面!F7 | U4: 金额单位：人民币元
A5: 序号 | B5: 车辆牌号 | C5: 车辆名称 及规格型号 | D5: 使用单位 | E5: 生产厂家 | F5: 计量单位 | G5: 数量 | H5: 购置日期 | I5: 启用日期 | J5: 已行驶里程(公里) | K5: 审计前账面值 | M5: 审计调整 | O5: 账面价值 | Q5: 评估价值 | T5: 增值率% | U5: 备注 | W5: 规定行驶里程 | X5: 已工作里程 | Y5: 里程成新率（%） | Z5: 观察成新率（%） | AA5: 成新率（%） | AB5: 购置价格（含税） | AC5: 增值税进项税额 | AD5: 购置价格（不含税） | AE5: 购置税 | AF5: 地区牌照费 | AG5: 重置全价
K6: 原值 | L6: 净值 | M6: 原值 | N6: 净值 | O6: 原值 | P6: 净值 | Q6: 原值 | R6: 成新率% | S6: 净值
A7: 1 | S7: =ROUND(Q7*R7/100,-2) | T7: =IF(P7=0,"",(S7-P7)/P7*100) | X7: =J7 | Y7: =(W7-X7)/W7 | Z7: =Y7-0.1 | AA7: =(Y7*0.6+Z7*0.4) | AC7: =AB7*0.13/(1+0.13) | AD7: =AB7/1.13 | AE7: =AD7*10% | AG7: =ROUND(AD7+AE7+AF7,-2) | AH7: https://www.che168.com/dealer/255777/36677775.html?pvareaid=100519&userpid=0&usercid=0#pos=5#page=1#rtype=10#isrecom=0#filter=63a448a0_0a0_0a0_0#module=10#refreshid=0#recomid=0#queryid=1587813166$11$e48f2cbd-d2f9-467b-865a-471a44289f31$25729#cartype=10
T8: =IF(P8=0,"",(S8-P8)/P8*100)
T9: =IF(P9=0,"",(S9-P9)/P9*100)
T10: =IF(P10=0,"",(S10-P10)/P10*100)
T11: =IF(P11=0,"",(S11-P11)/P11*100)
T12: =IF(P12=0,"",(S12-P12)/P12*100)
T13: =IF(P13=0,"",(S13-P13)/P13*100)
T14: =IF(P14=0,"",(S14-P14)/P14*100)
T15: =IF(P15=0,"",(S15-P15)/P15*100)
T16: =IF(P16=0,"",(S16-P16)/P16*100)
T17: =IF(P17=0,"",(S17-P17)/P17*100)
T18: =IF(P18=0,"",(S18-P18)/P18*100)
T19: =IF(P19=0,"",(S19-P19)/P19*100)
... T25: =IF(P25=0,"",(S25-P25)/P25*100)
A27: 合 计 | K27: =SUM(K7:K26) | L27: =SUM(L7:L26) | O27: =SUM(O7:O26) | P27: =SUM(P7:P26) | Q27: =SUM(Q7:Q26) | S27: =SUM(S7:S26) | T27: =IF(P27=0,"",(S27-P27)/P27*100)
A28: =封面!D11&封面!G11 | O28: ="评估人员："&封面!G26
A29: =CONCATENATE(封面!D13,封面!F13,封面!G13,封面!H13,封面!I13,封面!J13,封面!K13)

Sheet 电子设备
A1: 返回索引页 | B1: 返回
A2: 固定资产—电子设备评估明细表
A3: =CONCATENATE(封面!D9,封面!F9,封面!G9,封面!H9,封面!I9,封面!J9,封面!K9)
A4: =封面!D7&封面!F7 | V4: 金额单位：人民币元
A5: 序号 | B5: PO号 | D5: 设备名称 | E5: 规格型号 | F5: 使用单位 | G5: 生产厂家 | H5: 计量单位 | I5: 数量 | J5: 购置日期 | K5: 启用日期 | L5: 审计前账面值 | N5: 审计调整 | P5: 账面价值 | R5: 评估价值 | U5: 增值率% | V5: 备注 | X5: 已使用 | Y5: 理论成新率 | Z5: 年限成新率 | AA5: 综合成新率 | AB5: 账面单价 | AC5: 购置单价(含税) | AF5: 增值税进项税额 | AG5: 不含税重置单价 | AH5: 含税重置全价 | AI5: 不含税重置全价
L6: 原值 | M6: 净值 | N6: 原值 | O6: 净值 | P6: 原值 | Q6: 净值 | R6: 原值 | S6: 成新率% | T6: 净值 | W6: 经济年限 | AD6: 物价指数 | AE6: 贬值率
R7: =AI7 | S7: =Y7*100 | T7: =ROUND(R7*S7/100,-1) | U7: =IF(Q7=0,"",(T7-Q7)/Q7*100) | X7: =($W$5-K7)/365 | Y7: =(W7-X7)/W7 | AA7: =Y7/2+Z7/2 | AB7: =P7/I7 | AC7: =AB7*AD7 | AF7: =AC7*0.13/(1+0.13) | AG7: =AC7-AF7 | AH7: =AC7*I7 | AI7: =ROUND(AG7*I7,-1)
R8: =AI8 | S8: =Y8*100 | T8: =ROUND(R8*S8/100,-1) | U8: =IF(Q8=0,"",(T8-Q8)/Q8*100) | X8: =($W$5-K8)/365 | Y8: =(W8-X8)/W8 | AA8: =Y8/2+Z8/2 | AB8: =P8/I8 | AC8: =AB8*AD8 | AF8: =AC8*0.13/(1+0.13) | AG8: =AC8-AF8 | AH8: =AC8*I8 | AI8: =ROUND(AG8*I8,-1)
R9: =AI9 | S9: =Y9*100 | T9: =ROUND(R9*S9/100,-1) | U9: =IF(Q9=0,"",(T9-Q9)/Q9*100) | X9: =($W$5-K9)/365 | Y9: =(W9-X9)/W9 | AA9: =Y9/2+Z9/2 | AB9: =P9/I9 | AC9: =AB9*AD9 | AF9: =AC9*0.13/(1+0.13) | AG9: =AC9-AF9 | AH9: =AC9*I9 | AI9: =ROUND(AG9*I9,-1)
R10: =AI10 | S10: =Y10*100 | T10: =ROUND(R10*S10/100,-1) | U10: =IF(Q10=0,"",(T10-Q10)/Q10*100) | X10: =($W$5-K10)/365 | Y10: =(W10-X10)/W10 | AA10: =Y10/2+Z10/2 | AB10: =P10/I10 | AC10: =AB10*AD10 | AF10: =AC10*0.13/(1+0.13) | AG10: =AC10-AF10 | AH10: =AC10*I10 | AI10: =ROUND(AG10*I10,-1)
R11: =AI11 | S11: =Y11*100 | T11: =ROUND(R11*S11/100,-1) | U11: =IF(Q11=0,"",(T11-Q11)/Q11*100) | X11: =($W$5-K11)/365 | Y11: =(W11-X11)/W11 | AA11: =Y11/2+Z11/2 | AB11: =P11/I11 | AC11: =AB11*AD11 | AF11: =AC11*0.13/(1+0.13) | AG11: =AC11-AF11 | AH11: =AC11*I11 | AI11: =ROUND(AG11*I11,-1)
R12: =AI12 | S12: =Y12*100 | T12: =ROUND(R12*S12/100,-1) | U12: =IF(Q12=0,"",(T12-Q12)/Q12*100) | X12: =($W$5-K12)/365 | Y12: =(W12-X12)/W12 | AA12: =Y12/2+Z12/2 | AB12: =P12/I12 | AC12: =AB12*AD12 | AF12: =AC12*0.13/(1+0.13) | AG12: =AC12-AF12 | AH12: =AC12*I12 | AI12: =ROUND(AG12*I12,-1)
R13: =AI13 | S13: =Y13*100 | T13: =ROUND(R13*S13/100,-1) | U13: =IF(Q13=0,"",(T13-Q13)/Q13*100) | X13: =($W$5-K13)/365 | Y13: =(W13-X13)/W13 | AA13: =Y13/2+Z13/2 | AB13: =P13/I13 | AC13: =AB13*AD13 | AF13: =AC13*0.13/(1+0.13) | AG13: =AC13-AF13 | AH13: =AC13*I13 | AI13: =ROUND(AG13*I13,-1)
R14: =AI14 | S14: =Y14*100 | T14: =ROUND(R14*S14/100,-1) | U14: =IF(Q14=0,"",(T14-Q14)/Q14*100) | X14: =($W$5-K14)/365 | Y14: =(W14-X14)/W14 | AA14: =Y14/2+Z14/2 | AB14: =P14/I14 | AC14: =AB14*AD14 | AF14: =AC14*0.13/(1+0.13) | AG14: =AC14-AF14 | AH14: =AC14*I14 | AI14: =ROUND(AG14*I14,-1)
R15: =AI15 | S15: =Y15*100 | T15: =ROUND(R15*S15/100,-1) | U15: =IF(Q15=0,"",(T15-Q15)/Q15*100) | X15: =($W$5-K15)/365 | Y15: =(W15-X15)/W15 | AA15: =Y15/2+Z15/2 | AB15: =P15/I15 | AC15: =AB15*AD15 | AF15: =AC15*0.13/(1+0.13) | AG15: =AC15-AF15 | AH15: =AC15*I15 | AI15: =ROUND(AG15*I15,-1)
R16: =AI16 | S16: =Y16*100 | T16: =ROUND(R16*S16/100,-1) | U16: =IF(Q16=0,"",(T16-Q16)/Q16*100) | X16: =($W$5-K16)/365 | Y16: =(W16-X16)/W16 | AA16: =Y16/2+Z16/2 | AB16: =P16/I16 | AC16: =AB16*AD16 | AF16: =AC16*0.13/(1+0.13) | AG16: =AC16-AF16 | AH16: =AC16*I16 | AI16: =ROUND(AG16*I16,-1)
R17: =AI17 | S17: =Y17*100 | T17: =ROUND(R17*S17/100,-1) | U17: =IF(Q17=0,"",(T17-Q17)/Q17*100) | X17: =($W$5-K17)/365 | Y17: =(W17-X17)/W17 | AA17: =Y17/2+Z17/2 | AB17: =P17/I17 | AC17: =AB17*AD17 | AF17: =AC17*0.13/(1+0.13) | AG17: =AC17-AF17 | AH17: =AC17*I17 | AI17: =ROUND(AG17*I17,-1)
R18: =AI18 | S18: =Y18*100 | T18: =ROUND(R18*S18/100,-1) | U18: =IF(Q18=0,"",(T18-Q18)/Q18*100) | X18: =($W$5-K18)/365 | Y18: =(W18-X18)/W18 | AA18: =Y18/2+Z18/2 | AB18: =P18/I18 | AC18: =AB18*AD18 | AF18: =AC18*0.13/(1+0.13) | AG18: =AC18-AF18 | AH18: =AC18*I18 | AI18: =ROUND(AG18*I18,-1)
... R394: =AI394 | S394: =Y394*100 | T394: =ROUND(R394*S394/100,-1) | U394: =IF(Q394=0,"",(T394-Q394)/Q394*100) | X394: =($W$5-K394)/365 | Y394: =(W394-X394)/W394 | AA394: =Y394/2+Z394/2 | AB394: =P394/I394 | AC394: =AB394*AD394 | AF394: =AC394*0.13/(1+0.13) | AG394: =AC394-AF394 | AH394: =AC394*I394 | AI394: =ROUND(AG394*I394,-1)
R395: =AI395 | S395: =Y395*100 | T395: =ROUND(R395*S395/100,-1) | U395: =IF(Q395=0,"",(T395-Q395)/Q395*100) | X395: =($W$5-K395)/365 | Y395: =(W395-X395)/W395 | AA395: =Y395/2+Z395/2 | AB395: =P395/I395 | AF395: =AC395*0.13/(1+0.13) | AG395: =AC395-AF395 | AH395: =AC395*I395 | AI395: =ROUND(AG395*I395,-1) | AJ395: https://item.jd.com/10040654779710.html?uabt=872_12138_1_0&pcdk=axGR2EOPw-_wPmzq0SmLBnuKYeK_U_-N7fR-Ux5hrCI%3D.ZNqn.8PYs&cu=true&utm_source=lianmeng__10__kong__go.smzdm.com&utm_medium=tuiguang&utm_campaign=t_1000089893_156_0_184__1aaf00ca47fff68a&utm_term=94b28be62c82be968d3d00523e5376e8&purchasetab=gfgm
R396: =AI396 | S396: =Y396*100 | T396: =ROUND(R396*S396/100,-1) | U396: =IF(Q396=0,"",(T396-Q396)/Q396*100) | X396: =($W$5-K396)/365 | Y396: =(W396-X396)/W396 | AA396: =Y396/2+Z396/2 | AB396: =P396/I396 | AF396: =AC396*0.13/(1+0.13) | AG396: =AC396-AF396 | AH396: =AC396*I396 | AI396: =ROUND(AG396*I396,-1) | AJ396: https://item.jd.com/10052392698142.html?uabt=872_12138_1_0&pcdk=Mf8Zq4cBIGXbrTRXqs8OiNMCHbX1Gi9qkPMbX8oJ9rI%3D.ZNqn.8PYs&cu=true&utm_source=lianmeng__10__kong__detail.zol.com.cn&utm_medium=jingfen&utm_campaign=t_2032288013_&utm_term=9769d5671ef2ddcc39dbb7edc8a9b3d1&purchasetab=gfgm
R397: =AI397 | S397: =Y397*100 | T397: =ROUND(R397*S397/100,-1) | U397: =IF(Q397=0,"",(T397-Q397)/Q397*100) | X397: =($W$5-K397)/365 | Y397: =(W397-X397)/W397 | AA397: =Y397/2+Z397/2 | AB397: =P397/I397 | AF397: =AC397*0.13/(1+0.13) | AG397: =AC397-AF397 | AH397: =AC397*I397 | AI397: =ROUND(AG397*I397,-1) | AJ397: https://item.jd.com/10040654779710.html?uabt=872_12138_1_0&pcdk=axGR2EOPw-_wPmzq0SmLBnuKYeK_U_-N7fR-Ux5hrCI%3D.ZNqn.8PYs&cu=true&utm_source=lianmeng__10__kong__go.smzdm.com&utm_medium=tuiguang&utm_campaign=t_1000089893_156_0_184__1aaf00ca47fff68a&utm_term=94b28be62c82be968d3d00523e5376e8&purchasetab=gfgm
R398: =AI398 | S398: =Y398*100 | T398: =ROUND(R398*S398/100,-1) | U398: =IF(Q398=0,"",(T398-Q398)/Q398*100) | X398: =($W$5-K398)/365 | Y398: =(W398-X398)/W398 | AA398: =Y398/2+Z398/2 | AB398: =P398/I398 | AF398: =AC398*0.13/(1+0.13) | AG398: =AC398-AF398 | AH398: =AC398*I398 | AI398: =ROUND(AG398*I398,-1) | AJ398: https://item.jd.com/10040654779710.html?uabt=872_12138_1_0&pcdk=axGR2EOPw-_wPmzq0SmLBnuKYeK_U_-N7fR-Ux5hrCI%3D.ZNqn.8PYs&cu=true&utm_source=lianmeng__10__kong__go.smzdm.com&utm_medium=tuiguang&utm_campaign=t_1000089893_156_0_184__1aaf00ca47fff68a&utm_term=94b28be62c82be968d3d00523e5376e8&purchasetab=gfgm
R399: =AI399 | S399: =Y399*100 | T399: =ROUND(R399*S399/100,-1) | U399: =IF(Q399=0,"",(T399-Q399)/Q399*100) | X399: =($W$5-K399)/365 | Y399: =(W399-X399)/W399 | AA399: =Y399/2+Z399/2 | AB399: =P399/I399 | AF399: =AC399*0.13/(1+0.13) | AG399: =AC399-AF399 | AH399: =AC399*I399 | AI399: =ROUND(AG399*I399,-1) | AJ399: https://item.jd.com/10052392698142.html?uabt=872_12138_1_0&pcdk=Mf8Zq4cBIGXbrTRXqs8OiNMCHbX1Gi9qkPMbX8oJ9rI%3D.ZNqn.8PYs&cu=true&utm_source=lianmeng__10__kong__detail.zol.com.cn&utm_medium=jingfen&utm_campaign=t_2032288013_&utm_term=9769d5671ef2ddcc39dbb7edc8a9b3d1&purchasetab=gfgm
R400: =AI400 | S400: =Y400*100 | T400: =ROUND(R400*S400/100,-1) | U400: =IF(Q400=0,"",(T400-Q400)/Q400*100) | X400: =($W$5-K400)/365 | Y400: =(W400-X400)/W400 | AA400: =Y400/2+Z400/2 | AB400: =P400/I400 | AF400: =AC400*0.13/(1+0.13) | AG400: =AC400-AF400 | AH400: =AC400*I400 | AI400: =ROUND(AG400*I400,-1) | AJ400: https://item.jd.com/10052392698142.html?uabt=872_12138_1_0&pcdk=Mf8Zq4cBIGXbrTRXqs8OiNMCHbX1Gi9qkPMbX8oJ9rI%3D.ZNqn.8PYs&cu=true&utm_source=lianmeng__10__kong__detail.zol.com.cn&utm_medium=jingfen&utm_campaign=t_2032288013_&utm_term=9769d5671ef2ddcc39dbb7edc8a9b3d1&purchasetab=gfgm
R401: =AI401 | S401: =Y401*100 | T401: =ROUND(R401*S401/100,-1) | U401: =IF(Q401=0,"",(T401-Q401)/Q401*100) | X401: =($W$5-K401)/365 | Y401: =(W401-X401)/W401 | AA401: =Y401/2+Z401/2 | AB401: =P401/I401 | AF401: =AC401*0.13/(1+0.13) | AG401: =AC401-AF401 | AH401: =AC401*I401 | AI401: =ROUND(AG401*I401,-1) | AJ401: https://item.jd.com/10052392698142.html?uabt=872_12138_1_0&pcdk=Mf8Zq4cBIGXbrTRXqs8OiNMCHbX1Gi9qkPMbX8oJ9rI%3D.ZNqn.8PYs&cu=true&utm_source=lianmeng__10__kong__detail.zol.com.cn&utm_medium=jingfen&utm_campaign=t_2032288013_&utm_term=9769d5671ef2ddcc39dbb7edc8a9b3d1&purchasetab=gfgm
R402: =AI402 | S402: =Y402*100 | T402: =ROUND(R402*S402/100,-1) | U402: =IF(Q402=0,"",(T402-Q402)/Q402*100) | X402: =($W$5-K402)/365 | Y402: =(W402-X402)/W402 | AA402: =Y402/2+Z402/2 | AB402: =P402/I402 | AC402: =AB402*AD402 | AF402: =AC402*0.13/(1+0.13) | AG402: =AC402-AF402 | AH402: =AC402*I402 | AI402: =ROUND(AG402*I402,-1)
R403: =AI403 | S403: =Y403*100 | T403: =ROUND(R403*S403/100,-1) | U403: =IF(Q403=0,"",(T403-Q403)/Q403*100) | X403: =($W$5-K403)/365 | Y403: =(W403-X403)/W403 | AA403: =Y403/2+Z403/2 | AB403: =P403/I403 | AC403: =AB403*AD403 | AF403: =AC403*0.13/(1+0.13) | AG403: =AC403-AF403 | AH403: =AC403*I403 | AI403: =ROUND(AG403*I403,-1)
R404: =AI404 | S404: =Y404*100 | T404: =ROUND(R404*S404/100,-1) | U404: =IF(Q404=0,"",(T404-Q404)/Q404*100) | X404: =($W$5-K404)/365 | Y404: =(W404-X404)/W404 | AA404: =Y404/2+Z404/2 | AB404: =P404/I404 | AC404: =AB404*AD404 | AF404: =AC404*0.13/(1+0.13) | AG404: =AC404-AF404 | AH404: =AC404*I404 | AI404: =ROUND(AG404*I404,-1)
R405: =AI405 | S405: =Y405*100 | T405: =ROUND(R405*S405/100,-1) | U405: =IF(Q405=0,"",(T405-Q405)/Q405*100) | X405: =($W$5-K405)/365 | Y405: =(W405-X405)/W405 | AA405: =Y405/2+Z405/2 | AB405: =P405/I405 | AC405: =AB405*AD405 | AF405: =AC405*0.13/(1+0.13) | AG405: =AC405-AF405 | AH405: =AC405*I405 | AI405: =ROUND(AG405*I405,-1)
R406: =AI406 | S406: =Y406*100 | T406: =ROUND(R406*S406/100,-1) | U406: =IF(Q406=0,"",(T406-Q406)/Q406*100) | X406: =($W$5-K406)/365 | Y406: =(W406-X406)/W406 | AA406: =Y406/2+Z406/2 | AB406: =P406/I406 | AC406: =AB406*AD406 | AF406: =AC406*0.13/(1+0.13) | AG406: =AC406-AF406 | AH406: =AC406*I406 | AI406: =ROUND(AG406*I406,-1)
R407: =AI407 | S407: =Y407*100 | T407: =ROUND(R407*S407/100,-1) | U407: =IF(Q407=0,"",(T407-Q407)/Q407*100) | X407: =($W$5-K407)/365 | Y407: =(W407-X407)/W407 | AA407: =Y407/2+Z407/2 | AB407: =P407/I407 | AC407: =AB407*AD407 | AF407: =AC407*0.13/(1+0.13) | AG407: =AC407-AF407 | AH407: =AC407*I407 | AI407: =ROUND(AG407*I407,-1)
R408: =AI408 | S408: =Y408*100 | T408: =ROUND(R408*S408/100,-1) | U408: =IF(Q408=0,"",(T408-Q408)/Q408*100) | X408: =($W$5-K408)/365 | Y408: =(W408-X408)/W408 | AA408: =Y408/2+Z408/2 | AB408: =P408/I408 | AF408: =AC408*0.13/(1+0.13) | AG408: =AC408-AF408 | AH408: =AC408*I408 | AI408: =ROUND(AG408*I408,-1) | AJ408: https://item.jd.com/10052392698142.html?uabt=872_12138_1_0&pcdk=Mf8Zq4cBIGXbrTRXqs8OiNMCHbX1Gi9qkPMbX8oJ9rI%3D.ZNqn.8PYs&cu=true&utm_source=lianmeng__10__kong__detail.zol.com.cn&utm_medium=jingfen&utm_campaign=t_2032288013_&utm_term=9769d5671ef2ddcc39dbb7edc8a9b3d1&purchasetab=gfgm
R409: =AI409 | S409: =Y409*100 | T409: =ROUND(R409*S409/100,-1) | U409: =IF(Q409=0,"",(T409-Q409)/Q409*100) | X409: =($W$5-K409)/365 | Y409: =(W409-X409)/W409 | AA409: =Y409/2+Z409/2 | AB409: =P409/I409 | AC409: =AB409*AD409 | AF409: =AC409*0.13/(1+0.13) | AG409: =AC409-AF409 | AH409: =AC409*I409 | AI409: =ROUND(AG409*I409,-1)
R410: =AI410 | S410: =Y410*100 | T410: =ROUND(R410*S410/100,-1) | U410: =IF(Q410=0,"",(T410-Q410)/Q410*100) | X410: =($W$5-K410)/365 | Y410: =(W410-X410)/W410 | AA410: =Y410/2+Z410/2 | AB410: =P410/I410 | AF410: =AC410*0.13/(1+0.13) | AG410: =AC410-AF410 | AH410: =AC410*I410 | AI410: =ROUND(AG410*I410,-1) | AJ410: https://item.jd.com/10052392698142.html?uabt=872_12138_1_0&pcdk=Mf8Zq4cBIGXbrTRXqs8OiNMCHbX1Gi9qkPMbX8oJ9rI%3D.ZNqn.8PYs&cu=true&utm_source=lianmeng__10__kong__detail.zol.com.cn&utm_medium=jingfen&utm_campaign=t_2032288013_&utm_term=9769d5671ef2ddcc39dbb7edc8a9b3d1&purchasetab=gfgm
R411: =AI411 | S411: =Y411*100 | T411: =ROUND(R411*S411/100,-1) | U411: =IF(Q411=0,"",(T411-Q411)/Q411*100) | X411: =($W$5-K411)/365 | Y411: =(W411-X411)/W411 | AA411: =Y411/2+Z411/2 | AB411: =P411/I411 | AF411: =AC411*0.13/(1+0.13) | AG411: =AC411-AF411 | AH411: =AC411*I411 | AI411: =ROUND(AG411*I411,-1) | AJ411: https://www.bing.com/?scope=web&FORM=ANAB01&pc=NMTS
R412: =AI412 | S412: =Y412*100 | T412: =ROUND(R412*S412/100,-1) | U412: =IF(Q412=0,"",(T412-Q412)/Q412*100) | X412: =($W$5-K412)/365 | Y412: =(W412-X412)/W412 | AA412: =Y412/2+Z412/2 | AB412: =P412/I412 | AC412: =AB412*AD412 | AF412: =AC412*0.13/(1+0.13) | AG412: =AC412-AF412 | AH412: =AC412*I412 | AI412: =ROUND(AG412*I412,-1)
R413: =AI413 | S413: =Y413*100 | T413: =ROUND(R413*S413/100,-1) | U413: =IF(Q413=0,"",(T413-Q413)/Q413*100) | X413: =($W$5-K413)/365 | Y413: =(W413-X413)/W413 | AA413: =Y413/2+Z413/2 | AB413: =P413/I413 | AC413: =AB413*AD413 | AF413: =AC413*0.13/(1+0.13) | AG413: =AC413-AF413 | AH413: =AC413*I413 | AI413: =ROUND(AG413*I413,-1)
R414: =AI414 | S414: =Y414*100 | T414: =ROUND(R414*S414/100,-1) | U414: =IF(Q414=0,"",(T414-Q414)/Q414*100) | X414: =($W$5-K414)/365 | Y414: =(W414-X414)/W414 | AA414: =Y414/2+Z414/2 | AB414: =P414/I414 | AC414: =AB414*AD414 | AF414: =AC414*0.13/(1+0.13) | AG414: =AC414-AF414 | AH414: =AC414*I414 | AI414: =ROUND(AG414*I414,-1)
R415: =AI415 | S415: =Y415*100 | T415: =ROUND(R415*S415/100,-1) | U415: =IF(Q415=0,"",(T415-Q415)/Q415*100) | X415: =($W$5-K415)/365 | Y415: =(W415-X415)/W415 | AA415: =Y415/2+Z415/2 | AB415: =P415/I415 | AC415: =AB415*AD415 | AF415: =AC415*0.13/(1+0.13) | AG415: =AC415-AF415 | AH415: =AC415*I415 | AI415: =ROUND(AG415*I415,-1)
R416: =AI416 | S416: =Y416*100 | T416: =ROUND(R416*S416/100,-1) | U416: =IF(Q416=0,"",(T416-Q416)/Q416*100) | X416: =($W$5-K416)/365 | Y416: =(W416-X416)/W416 | AA416: =Y416/2+Z416/2 | AB416: =P416/I416 | AC416: =AB416*AD416 | AF416: =AC416*0.13/(1+0.13) | AG416: =AC416-AF416 | AH416: =AC416*I416 | AI416: =ROUND(AG416*I416,-1)
R417: =AI417 | S417: =Y417*100 | T417: =ROUND(R417*S417/100,-1) | U417: =IF(Q417=0,"",(T417-Q417)/Q417*100) | X417: =($W$5-K417)/365 | Y417: =(W417-X417)/W417 | AA417: =Y417/2+Z417/2 | AB417: =P417/I417 | AC417: =AB417*AD417 | AF417: =AC417*0.13/(1+0.13) | AG417: =AC417-AF417 | AH417: =AC417*I417 | AI417: =ROUND(AG417*I417,-1)
R418: =AI418 | S418: =Y418*100 | T418: =ROUND(R418*S418/100,-1) | U418: =IF(Q418=0,"",(T418-Q418)/Q418*100) | X418: =($W$5-K418)/365 | Y418: =(W418-X418)/W418 | AA418: =Y418/2+Z418/2 | AB418: =P418/I418 | AC418: =AB418*AD418 | AF418: =AC418*0.13/(1+0.13) | AG418: =AC418-AF418 | AH418: =AC418*I418 | AI418: =ROUND(AG418*I418,-1)
R419: =AI419 | S419: =Y419*100 | T419: =ROUND(R419*S419/100,-1) | U419: =IF(Q419=0,"",(T419-Q419)/Q419*100) | X419: =($W$5-K419)/365 | Y419: =(W419-X419)/W419 | AA419: =Y419/2+Z419/2 | AB419: =P419/I419 | AC419: =AB419*AD419 | AF419: =AC419*0.13/(1+0.13) | AG419: =AC419-AF419 | AH419: =AC419*I419 | AI419: =ROUND(AG419*I419,-1)
R420: =AI420 | S420: =Y420*100 | T420: =ROUND(R420*S420/100,-1) | U420: =IF(Q420=0,"",(T420-Q420)/Q420*100) | X420: =($W$5-K420)/365 | Y420: =(W420-X420)/W420 | AA420: =Y420/2+Z420/2 | AB420: =P420/I420 | AC420: =AB420*AD420 | AF420: =AC420*0.13/(1+0.13) | AG420: =AC420-AF420 | AH420: =AC420*I420 | AI420: =ROUND(AG420*I420,-1)
R421: =AI421 | S421: =Y421*100 | T421: =ROUND(R421*S421/100,-1) | U421: =IF(Q421=0,"",(T421-Q421)/Q421*100) | X421: =($W$5-K421)/365 | Y421: =(W421-X421)/W421 | AA421: =Y421/2+Z421/2 | AB421: =P421/I421 | AC421: =AB421*AD421 | AF421: =AC421*0.13/(1+0.13) | AG421: =AC421-AF421 | AH421: =AC421*I421 | AI421: =ROUND(AG421*I421,-1)
R422: =AI422 | S422: =Y422*100 | T422: =ROUND(R422*S422/100,-1) | U422: =IF(Q422=0,"",(T422-Q422)/Q422*100) | X422: =($W$5-K422)/365 | Y422: =(W422-X422)/W422 | AA422: =Y422/2+Z422/2 | AB422: =P422/I422 | AC422: =AB422*AD422 | AF422: =AC422*0.13/(1+0.13) | AG422: =AC422-AF422 | AH422: =AC422*I422 | AI422: =ROUND(AG422*I422,-1)
R423: =AI423 | S423: =Y423*100 | T423: =ROUND(R423*S423/100,-1) | U423: =IF(Q423=0,"",(T423-Q423)/Q423*100) | X423: =($W$5-K423)/365 | Y423: =(W423-X423)/W423 | AA423: =Y423/2+Z423/2 | AB423: =P423/I423 | AC423: =AB423*AD423 | AF423: =AC423*0.13/(1+0.13) | AG423: =AC423-AF423 | AH423: =AC423*I423 | AI423: =ROUND(AG423*I423,-1)
... R447: =AI447 | S447: =Y447*100 | T447: =ROUND(R447*S447/100,-1) | U447: =IF(Q447=0,"",(T447-Q447)/Q447*100) | X447: =($W$5-K447)/365 | Y447: =(W447-X447)/W447 | AA447: =Y447/2+Z447/2 | AB447: =P447/I447 | AC447: =AB447*AD447 | AF447: =AC447*0.13/(1+0.13) | AG447: =AC447-AF447 | AH447: =AC447*I447 | AI447: =ROUND(AG447*I447,-1)
A449: 合 计 | L449: =SUM(L7:L448) | M449: =SUM(M7:M448) | P449: =SUM(P7:P448) | Q449: =SUM(Q7:Q448) | R449: =SUM(R7:R448) | T449: =SUM(T7:T448) | U449: =IF(Q449=0,"",(T449-Q449)/Q449*100)
A450: =封面!D11&封面!G11 | P450: ="评估人员："&封面!G26
A451: =CONCATENATE(封面!D13,封面!F13,封面!G13,封面!H13,封面!I13,封面!J13,封面!K13)

Sheet 土地
A1: 返回索引页 | B1: 返回
A2: 固定资产—土地评估明细表
A3: =CONCATENATE(封面!D9,封面!F9,封面!G9,封面!H9,封面!I9,封面!J9,封面!K9)
A4: =封面!D7&封面!F7 | S4: 金额单位：人民币元
A5: 序号 | B5: 土地权证编号 | C5: 宗地名称 | D5: 土地位置 | E5: 取得日期 | F5: 用地性质 | G5: 准用年限 | H5: 开发程度 | I5: 面积(m2) | J5: 审计前账面值 | L5: 审计调整 | N5: 账面价值 | P5: 评估价值 | R5: 增值率% | S5: 备注 | T5: 证载权利人
J6: 原值 | K6: 净值 | L6: 原值 | M6: 净值 | N6: 原值 | O6: 净值 | P6: 原值 | Q6: 净值
A7: 1 | R7: =IF(O7=0,"",(Q7-O7)/O7*100)
R8: =IF(O8=0,"",(Q8-O8)/O8*100)
R9: =IF(O9=0,"",(Q9-O9)/O9*100)
R10: =IF(O10=0,"",(Q10-O10)/O10*100)
R11: =IF(O11=0,"",(Q11-O11)/O11*100)
R12: =IF(O12=0,"",(Q12-O12)/O12*100)
R13: =IF(O13=0,"",(Q13-O13)/O13*100)
R14: =IF(O14=0,"",(Q14-O14)/O14*100)
R15: =IF(O15=0,"",(Q15-O15)/O15*100)
R16: =IF(O16=0,"",(Q16-O16)/O16*100)
R17: =IF(O17=0,"",(Q17-O17)/O17*100)
R18: =IF(O18=0,"",(Q18-O18)/O18*100)
R19: =IF(O19=0,"",(Q19-O19)/O19*100)
... R26: =IF(O26=0,"",(Q26-O26)/O26*100)
A28: 合 计 | J28: =SUM(J7:J27) | K28: =SUM(K7:K27) | N28: =SUM(N8:N27) | O28: =SUM(O7:O27) | P28: =SUM(P7:P27) | Q28: =SUM(Q7:Q27) | R28: =IF(O28=0,"",(Q28-O28)/O28*100)
A29: =封面!D11&封面!G11 | N29: ="评估人员："&封面!G28
A30: =CONCATENATE(封面!D13,封面!F13,封面!G13,封面!H13,封面!I13,封面!J13,封面!K13)

Sheet 在建工程汇总
A1: 返回索引页 | B1: 返回
A2: 在建工程评估汇总表
A3: =CONCATENATE(封面!D9,封面!F9,封面!G9,封面!H9,封面!I9,封面!J9,封面!K9)
A4: =封面!D7&封面!F7 | G4: 金额单位：人民币元
A5: 编号 | B5: 科目名称 | C5: 审计前账面值 | D5: 账面价值 | E5: 评估价值 | F5: 增值额 | G5: 增值率%
A6: 4-7-1 | B6: 在建工程-土建工程 | C6: ='在建（土建）'!I27 | D6: ='在建（土建）'!K27 | E6: ='在建（土建）'!L27 | F6: =E6-D6 | G6: =IF(D6=0,"",F6/D6*100)
A7: 4-7-2 | B7: 在建工程-设备安装工程 | C7: ='在建（设备）'!K27 | D7: ='在建（设备）'!P27 | E7: ='在建（设备）'!T27 | F7: =E7-D7 | G7: =IF(D7=0,"",F7/D7*100)
A25: 5-4 | B25: 在建工程合计 | C25: =SUM(C6:C24) | D25: =SUM(D6:D24) | E25: =SUM(E6:E24) | F25: =SUM(F6:F24) | G25: =IF(D25=0,"",F25/D25*100)
A26: 5-4 | B26: 减：在建工程减值准备 | D26: =C26 | E26: 0 | F26: =E26-D26 | G26: =IF(D26=0,"",F26/D26*100)
A27: 5-4 | B27: 在建工程净额 | C27: =C25-C26 | D27: =D25-D26 | E27: =E25-E26 | F27: =F25-F26 | G27: =IF(D27=0,"",F27/D27*100)
A28: =封面!D11&封面!G11 | E28: ="评估人员："&封面!G24&" "&封面!G26
A29: =CONCATENATE(封面!D13,封面!F13,封面!G13,封面!H13,封面!I13,封面!J13,封面!K13)

Sheet 在建（土建）
A1: 返回索引页 | B1: 返回
A2: 在建工程—土建工程评估明细表
A3: =CONCATENATE(封面!D9,封面!F9,封面!G9,封面!H9,封面!I9,封面!J9,封面!K9)
A4: =封面!D7&封面!F7 | O4: 金额单位：人民币元
A5: 序号 | B5: 项目名称 | C5: 结构 | D5: 建筑面积/容积 | E5: 开工日期 | F5: 预计完工日期 | G5: 形象进度 | H5: 付款比例 | I5: 审计前账面值 | J5: 审计调整 | K5: 账面价值 | L5: 评估价值 | M5: 增减值 | N5: 增值率% | O5: 备注
M6: =IF(K6=0,"",(L6-K6)) | N6: =IF(K6=0,"",(L6-K6)/K6*100)
M7: =IF(K7=0,"",(L7-K7)) | N7: =IF(K7=0,"",(L7-K7)/K7*100)
M8: =IF(K8=0,"",(L8-K8)) | N8: =IF(K8=0,"",(L8-K8)/K8*100)
M9: =IF(K9=0,"",(L9-K9)) | N9: =IF(K9=0,"",(L9-K9)/K9*100)
M10: =IF(K10=0,"",(L10-K10)) | N10: =IF(K10=0,"",(L10-K10)/K10*100)
M11: =IF(K11=0,"",(L11-K11)) | N11: =IF(K11=0,"",(L11-K11)/K11*100)
M12: =IF(K12=0,"",(L12-K12)) | N12: =IF(K12=0,"",(L12-K12)/K12*100)
M13: =IF(K13=0,"",(L13-K13)) | N13: =IF(K13=0,"",(L13-K13)/K13*100)
M14: =IF(K14=0,"",(L14-K14)) | N14: =IF(K14=0,"",(L14-K14)/K14*100)
M15: =IF(K15=0,"",(L15-K15)) | N15: =IF(K15=0,"",(L15-K15)/K15*100)
M16: =IF(K16=0,"",(L16-K16)) | N16: =IF(K16=0,"",(L16-K16)/K16*100)
M17: =IF(K17=0,"",(L17-K17)) | N17: =IF(K17=0,"",(L17-K17)/K17*100)
... M25: =IF(K25=0,"",(L25-K25)) | N25: =IF(K25=0,"",(L25-K25)/K25*100)
M26: =IF(K26=0,"",(L26-K26))
A27: 合 计 | I27: =SUM(I6:I26) | K27: =SUM(K6:K26) | L27: =SUM(L6:L26) | M27: =IF(K27=0,"",(L27-K27)) | N27: =IF(K27=0,"",(L27-K27)/K27*100)
A28: =封面!D11&封面!G11 | K28: ="评估人员："&封面!G24
A29: =CONCATENATE(封面!D13,封面!F13,封面!G13,封面!H13,封面!I13,封面!J13,封面!K13)

Sheet 在建（设备）
A1: 返回索引页 | B1: 返回
A2: 在建工程—设备安装工程评估明细表
A3: =CONCATENATE(封面!D9,封面!F9,封面!G9,封面!H9,封面!I9,封面!J9,封面!K9)
A4: =封面!D7&封面!F7 | W4: 金额单位：人民币元
A5: 序号 | B5: 项目名称 | C5: 规格型号 | D5: 数量 | E5: 计量单位 | F5: 开工 日期 | G5: 预计完 工日期 | H5: 审计前账面值 | L5: 审计调整 | M5: 账面价值 | Q5: 评估价值 | U5: 增减值 | V5: 增值率% | W5: 备注
U7: =IF(P7=0,"",(T7-P7)) | V7: =IF(P7=0,"",(T7-P7)/P7*100)
U8: =IF(P8=0,"",(T8-P8)) | V8: =IF(P8=0,"",(T8-P8)/P8*100)
U9: =IF(P9=0,"",(T9-P9)) | V9: =IF(P9=0,"",(T9-P9)/P9*100)
U10: =IF(P10=0,"",(T10-P10)) | V10: =IF(P10=0,"",(T10-P10)/P10*100)
U11: =IF(P11=0,"",(T11-P11)) | V11: =IF(P11=0,"",(T11-P11)/P11*100)
U12: =IF(P12=0,"",(T12-P12)) | V12: =IF(P12=0,"",(T12-P12)/P12*100)
U13: =IF(P13=0,"",(T13-P13)) | V13: =IF(P13=0,"",(T13-P13)/P13*100)
U14: =IF(P14=0,"",(T14-P14)) | V14: =IF(P14=0,"",(T14-P14)/P14*100)
U15: =IF(P15=0,"",(T15-P15)) | V15: =IF(P15=0,"",(T15-P15)/P15*100)
U16: =IF(P16=0,"",(T16-P16)) | V16: =IF(P16=0,"",(T16-P16)/P16*100)
U17: =IF(P17=0,"",(T17-P17)) | V17: =IF(P17=0,"",(T17-P17)/P17*100)
U18: =IF(P18=0,"",(T18-P18)) | V18: =IF(P18=0,"",(T18-P18)/P18*100)
... U25: =IF(P25=0,"",(T25-P25)) | V25: =IF(P25=0,"",(T25-P25)/P25*100)
U26: =IF(P26=0,"",(T26-P26))
A27: 合 计 | K27: =SUM(K7:K26) | P27: =SUM(P7:P26) | T27: =SUM(T7:T26) | U27: =IF(P27=0,"",(T27-P27)) | V27: =IF(P27=0,"",(T27-P27)/P27*100)
A28: =封面!D11&封面!G11 | P28: ="评估人员："&封面!G26
A29: =CONCATENATE(封面!D13,封面!F13,封面!G13,封面!H13,封面!I13,封面!J13,封面!K13)

Sheet 工程物资
A1: 返回索引页 | B1: 返回
A2: 工程物资评估明细表
A3: =CONCATENATE(封面!D9,封面!F9,封面!G9,封面!H9,封面!I9,封面!J9,封面!K9)
A4: =封面!D7&封面!F7 | Q4: 金额单位：人民币元
A5: 序号 | B5: 名称 | C5: 工程项目 | D5: 计量 单位 | E5: 审计前账面值 | H5: 审计调整 | I5: 账面价值 | L5: 实际数量 | M5: 评估价值 | O5: 增减值 | P5: 增值率 % | Q5: 备注
E6: 数量 | F6: 单价 | G6: 金额 | I6: 数量 | J6: 单价 | K6: 金额 | M6: 单价 | N6: 金额
O7: =IF(K7=0,"",(N7-K7)) | P7: =IF(K7=0,"",(N7-K7)/K7*100)
O8: =IF(K8=0,"",(N8-K8)) | P8: =IF(K8=0,"",(N8-K8)/K8*100)
O9: =IF(K9=0,"",(N9-K9)) | P9: =IF(K9=0,"",(N9-K9)/K9*100)
O10: =IF(K10=0,"",(N10-K10)) | P10: =IF(K10=0,"",(N10-K10)/K10*100)
O11: =IF(K11=0,"",(N11-K11)) | P11: =IF(K11=0,"",(N11-K11)/K11*100)
O12: =IF(K12=0,"",(N12-K12)) | P12: =IF(K12=0,"",(N12-K12)/K12*100)
O13: =IF(K13=0,"",(N13-K13)) | P13: =IF(K13=0,"",(N13-K13)/K13*100)
O14: =IF(K14=0,"",(N14-K14)) | P14: =IF(K14=0,"",(N14-K14)/K14*100)
O15: =IF(K15=0,"",(N15-K15)) | P15: =IF(K15=0,"",(N15-K15)/K15*100)
O16: =IF(K16=0,"",(N16-K16)) | P16: =IF(K16=0,"",(N16-K16)/K16*100)
O17: =IF(K17=0,"",(N17-K17)) | P17: =IF(K17=0,"",(N17-K17)/K17*100)
O18: =IF(K18=0,"",(N18-K18)) | P18: =IF(K18=0,"",(N18-K18)/K18*100)
... O24: =IF(K24=0,"",(N24-K24)) | P24: =IF(K24=0,"",(N24-K24)/K24*100)
A25: 合 计 | G25: =SUM(G7:G24) | K25: =SUM(K7:K24) | N25: =SUM(N7:N24) | O25: =IF(K25=0,"",(N25-K25)) | P25: =IF(K25=0,"",(N25-K25)/K25*100)
A26: 减：工程物资减值准备 | K26: =G26 | O26: =IF(K26=0,"",(N26-K26)) | P26: =IF(K26=0,"",(N26-K26)/K26*100)
A27: 净 额 | G27: =G25-G26 | K27: =K25-K26 | N27: =N25-N26 | O27: =IF(K27=0,"",(N27-K27)) | P27: =IF(K27=0,"",(N27-K27)/K27*100)
A28: =封面!D11&封面!G11 | L28: ="评估人员："&封面!G20
A29: =CONCATENATE(封面!D13,封面!F13,封面!G13,封面!H13,封面!I13,封面!J13,封面!K13)

Sheet 固定资产清理
A1: 返回索引页 | B1: 返回
A2: 固定资产清理评估明细表
A3: =CONCATENATE(封面!D9,封面!F9,封面!G9,封面!H9,封面!I9,封面!J9,封面!K9)
A4: =封面!D7&封面!F7 | J4: 金额单位：人民币元
A5: 序号 | B5: 待处理资产名称 | C5: 发生日期 | D5: 审计前账面值 | E5: 审计调整 | F5: 账面价值 | G5: 评估价值 | H5: 增减值 | I5: 增值率% | J5: 备注
H6: =IF(F6=0,"",(G6-F6)) | I6: =IF(F6=0,"",(G6-F6)/F6*100)
H7: =IF(F7=0,"",(G7-F7)) | I7: =IF(F7=0,"",(G7-F7)/F7*100)
H8: =IF(F8=0,"",(G8-F8)) | I8: =IF(F8=0,"",(G8-F8)/F8*100)
H9: =IF(F9=0,"",(G9-F9)) | I9: =IF(F9=0,"",(G9-F9)/F9*100)
H10: =IF(F10=0,"",(G10-F10)) | I10: =IF(F10=0,"",(G10-F10)/F10*100)
H11: =IF(F11=0,"",(G11-F11)) | I11: =IF(F11=0,"",(G11-F11)/F11*100)
H12: =IF(F12=0,"",(G12-F12)) | I12: =IF(F12=0,"",(G12-F12)/F12*100)
H13: =IF(F13=0,"",(G13-F13)) | I13: =IF(F13=0,"",(G13-F13)/F13*100)
H14: =IF(F14=0,"",(G14-F14)) | I14: =IF(F14=0,"",(G14-F14)/F14*100)
H15: =IF(F15=0,"",(G15-F15)) | I15: =IF(F15=0,"",(G15-F15)/F15*100)
H16: =IF(F16=0,"",(G16-F16)) | I16: =IF(F16=0,"",(G16-F16)/F16*100)
H17: =IF(F17=0,"",(G17-F17)) | I17: =IF(F17=0,"",(G17-F17)/F17*100)
... H26: =IF(F26=0,"",(G26-F26)) | I26: =IF(F26=0,"",(G26-F26)/F26*100)
A27: 合 计 | D27: =SUM(D6:D26) | F27: =SUM(F6:F26) | G27: =SUM(G6:G26) | H27: =IF(F27=0,"",(G27-F27)) | I27: =IF(F27=0,"",(G27-F27)/F27*100)
A28: =封面!D11&封面!G11 | G28: ="评估人员："&封面!G20
A29: =CONCATENATE(封面!D13,封面!F13,封面!G13,封面!H13,封面!I13,封面!J13,封面!K13)

Sheet 生产性生物资产
A1: 返回索引页 | B1: 返回
A2: 生产性生物资产评估明细表
A3: =CONCATENATE(封面!D9,封面!F9,封面!G9,封面!H9,封面!I9,封面!J9,封面!K9)
A4: =封面!D7&封面!F7 | R4: 金额单位：人民币元
A5: 序号 | B5: 种类 | C5: 群别 | D5: 使用单位 | E5: 计量单位 | F5: 数量 | G5: 购置日期 | H5: 审计前账面值 | J5: 审计调整 | L5: 账面价值 | N5: 评估价值 | Q5: 增值率% | R5: 备注
H6: 原值 | I6: 净值 | J6: 原值 | K6: 净值 | L6: 原值 | M6: 净值 | N6: 原值 | O6: 成新率% | P6: 净值
P7: =ROUND(N7*O7/100,0) | Q7: =IF(M7=0,"",(P7-M7)/M7*100)
P8: =ROUND(N8*O8/100,0) | Q8: =IF(M8=0,"",(P8-M8)/M8*100)
P9: =ROUND(N9*O9/100,0) | Q9: =IF(M9=0,"",(P9-M9)/M9*100)
P10: =ROUND(N10*O10/100,0) | Q10: =IF(M10=0,"",(P10-M10)/M10*100)
P11: =ROUND(N11*O11/100,0) | Q11: =IF(M11=0,"",(P11-M11)/M11*100)
P12: =ROUND(N12*O12/100,0) | Q12: =IF(M12=0,"",(P12-M12)/M12*100)
P13: =ROUND(N13*O13/100,0) | Q13: =IF(M13=0,"",(P13-M13)/M13*100)
P14: =ROUND(N14*O14/100,0) | Q14: =IF(M14=0,"",(P14-M14)/M14*100)
P15: =ROUND(N15*O15/100,0) | Q15: =IF(M15=0,"",(P15-M15)/M15*100)
P16: =ROUND(N16*O16/100,0) | Q16: =IF(M16=0,"",(P16-M16)/M16*100)
P17: =ROUND(N17*O17/100,0) | Q17: =IF(M17=0,"",(P17-M17)/M17*100)
P18: =ROUND(N18*O18/100,0) | Q18: =IF(M18=0,"",(P18-M18)/M18*100)
... P24: =ROUND(N24*O24/100,0) | Q24: =IF(M24=0,"",(P24-M24)/M24*100)
A25: 合 计 | H25: =SUM(H7:H24) | I25: =SUM(I7:I24) | L25: =SUM(L7:L24) | M25: =SUM(M7:M24) | N25: =SUM(N7:N24) | P25: =SUM(P7:P24) | Q25: =IF(M25=0,"",(P25-M25)/M25*100)
A26: 减：生产性生物资产减值准备 | M26: =I26 | Q26: =IF(M26=0,"",(P26-M26)/M26*100)
A27: 净 额 | H27: =H25-H26 | I27: =I25-I26 | L27: =L25-L26 | M27: =M25-M26 | N27: =N25-N26 | P27: =P25-P26 | Q27: =IF(M27=0,"",(P27-M27)/M27*100)
A28: =封面!D11&封面!G11 | L28: ="评估人员："&封面!G30
A29: =CONCATENATE(封面!D13,封面!F13,封面!G13,封面!H13,封面!I13,封面!J13,封面!K13)

Sheet 油气资产
A1: 返回索引页 | B1: 返回
A2: 油气资产评估明细表
A3: =CONCATENATE(封面!D9,封面!F9,封面!G9,封面!H9,封面!I9,封面!J9,封面!K9)
A4: =封面!D7&封面!F7 | S4: 金额单位：人民币元
A5: 序号 | B5: 类别 | C5: 矿区（或油田) | D5: 使用单位 | E5: 计量单位 | F5: 数量 | G5: 形成日期 | H5: 来源（购入、自行建造） | I5: 审计前账面值 | K5: 审计调整 | M5: 账面价值 | O5: 评估价值 | R5: 增值率% | S5: 备注
I6: 原值 | J6: 净值 | K6: 原值 | L6: 净值 | M6: 原值 | N6: 净值 | O6: 原值 | P6: 成新率% | Q6: 净值
Q7: =ROUND(O7*P7/100,0) | R7: =IF(N7=0,"",(Q7-N7)/N7*100)
Q8: =ROUND(O8*P8/100,0) | R8: =IF(N8=0,"",(Q8-N8)/N8*100)
Q9: =ROUND(O9*P9/100,0) | R9: =IF(N9=0,"",(Q9-N9)/N9*100)
Q10: =ROUND(O10*P10/100,0) | R10: =IF(N10=0,"",(Q10-N10)/N10*100)
Q11: =ROUND(O11*P11/100,0) | R11: =IF(N11=0,"",(Q11-N11)/N11*100)
Q12: =ROUND(O12*P12/100,0) | R12: =IF(N12=0,"",(Q12-N12)/N12*100)
Q13: =ROUND(O13*P13/100,0) | R13: =IF(N13=0,"",(Q13-N13)/N13*100)
Q14: =ROUND(O14*P14/100,0) | R14: =IF(N14=0,"",(Q14-N14)/N14*100)
Q15: =ROUND(O15*P15/100,0) | R15: =IF(N15=0,"",(Q15-N15)/N15*100)
Q16: =ROUND(O16*P16/100,0) | R16: =IF(N16=0,"",(Q16-N16)/N16*100)
Q17: =ROUND(O17*P17/100,0) | R17: =IF(N17=0,"",(Q17-N17)/N17*100)
Q18: =ROUND(O18*P18/100,0) | R18: =IF(N18=0,"",(Q18-N18)/N18*100)
... Q24: =ROUND(O24*P24/100,0) | R24: =IF(N24=0,"",(Q24-N24)/N24*100)
A25: 合 计 | I25: =SUM(I7:I24) | J25: =SUM(J7:J24) | M25: =SUM(M7:M24) | N25: =SUM(N7:N24) | O25: =SUM(O7:O24) | Q25: =SUM(Q7:Q24) | R25: =IF(N25=0,"",(Q25-N25)/N25*100)
A26: 减：生产性生物资产减值准备 | N26: =J26 | R26: =IF(N26=0,"",(Q26-N26)/N26*100)
A27: 净 额 | I27: =I25-I26 | J27: =J25-J26 | M27: =M25-M26 | N27: =N25-N26 | O27: =O25-O26 | Q27: =Q25-Q26 | R27: =IF(N27=0,"",(Q27-N27)/N27*100)
A28: =封面!D11&封面!G11 | M28: ="评估人员："&封面!G32
A29: =CONCATENATE(封面!D13,封面!F13,封面!G13,封面!H13,封面!I13,封面!J13,封面!K13)

Sheet 使用权资产
A1: 返回索引页 | B1: 返回
A2: 使用权资产评估明细表
A3: =CONCATENATE(封面!D9,封面!F9,封面!G9,封面!H9,封面!I9,封面!J9,封面!K9)
A4: =封面!D7&封面!F7 | M4: 金额单位：人民币元
A5: 序号 | B5: 使用权资产名称 | C5: 形成日期 | D5: 原始发生额 | E5: 预计使用权月数 | F5: 审计前账面值 | G5: 审计调整 | H5: 账面价值 | I5: 尚存受 益月数 | J5: 评估价值 | K5: 增减值 | L5: 增值率% | M5: 备注
K6: =IF(H6=0,"",(J6-H6)) | L6: =IF(H6=0,"",(J6-H6)/H6*100)
K7: =IF(H7=0,"",(J7-H7)) | L7: =IF(H7=0,"",(J7-H7)/H7*100)
K8: =IF(H8=0,"",(J8-H8)) | L8: =IF(H8=0,"",(J8-H8)/H8*100)
K9: =IF(H9=0,"",(J9-H9)) | L9: =IF(H9=0,"",(J9-H9)/H9*100)
K10: =IF(H10=0,"",(J10-H10)) | L10: =IF(H10=0,"",(J10-H10)/H10*100)
K11: =IF(H11=0,"",(J11-H11)) | L11: =IF(H11=0,"",(J11-H11)/H11*100)
K12: =IF(H12=0,"",(J12-H12)) | L12: =IF(H12=0,"",(J12-H12)/H12*100)
K13: =IF(H13=0,"",(J13-H13)) | L13: =IF(H13=0,"",(J13-H13)/H13*100)
K14: =IF(H14=0,"",(J14-H14)) | L14: =IF(H14=0,"",(J14-H14)/H14*100)
K15: =IF(H15=0,"",(J15-H15)) | L15: =IF(H15=0,"",(J15-H15)/H15*100)
K16: =IF(H16=0,"",(J16-H16)) | L16: =IF(H16=0,"",(J16-H16)/H16*100)
K17: =IF(H17=0,"",(J17-H17)) | L17: =IF(H17=0,"",(J17-H17)/H17*100)
... K25: =IF(H25=0,"",(J25-H25)) | L25: =IF(H25=0,"",(J25-H25)/H25*100)
K26: =IF(H26=0,"",(J26-H26))
A27: 合 计 | F27: =SUM(F6:F26) | H27: =SUM(H6:H26) | J27: =SUM(J6:J26) | K27: =IF(H27=0,"",(J27-H27)) | L27: =IF(H27=0,"",(J27-H27)/H27*100)
A28: =封面!D11&封面!G11 | H28: ="评估人员："&封面!G36
A29: =CONCATENATE(封面!D13,封面!F13,封面!G13,封面!H13,封面!I13,封面!J13,封面!K13)

Sheet 无形资产汇总
A1: 返回索引页 | B1: 返回
A2: 无形资产评估汇总表
A3: =CONCATENATE(封面!D9,封面!F9,封面!G9,封面!H9,封面!I9,封面!J9,封面!K9)
A4: =封面!D7&封面!F7 | G4: 金额单位：人民币元
A5: 编号 | B5: 科目名称 | C5: 审计前账面值 | D5: 账面价值 | E5: 评估价值 | F5: 增值额 | G5: 增值率%
A6: 4-12-1 | B6: 无形资产-土地使用权 | C6: ='无形-土地'!K27 | D6: ='无形-土地'!M27 | E6: ='无形-土地'!N27 | F6: =E6-D6 | G6: =IF(D6=0,"",F6/D6*100)
A7: 4-12-2 | B7: 无形资产-矿业权 | C7: ='无形-矿业权'!J27 | D7: ='无形-矿业权'!L27 | E7: ='无形-矿业权'!M27
A8: 4-12-3 | B8: 无形资产-其他无形资产 | C8: ='无形-其他'!H23 | D8: ='无形-其他'!J23 | E8: ='无形-其他'!L23 | F8: =E8-D8 | G8: =IF(D8=0,"",F8/D8*100)
A25: 无形资产合计 | C25: =SUM(C6:C8) | D25: =SUM(D6:D8) | E25: =SUM(E6:E8) | F25: =SUM(F6:F8) | G25: =IF(D25=0,"",F25/D25*100)
A26: 减：无形资产减值准备 | D26: =C26 | E26: 0 | F26: =E26-D26 | G26: =IF(D26=0,"",F26/D26*100)
A27: 6 | B27: 总计 | C27: =C25-C26 | D27: =D25-D26 | E27: =E25-E26 | F27: =E27-D27 | G27: =IF(D27=0,"",F27/D27*100)
A28: =封面!D11&封面!G11 | E28: ="评估人员："&封面!G28&" "&封面!G34
A29: =CONCATENATE(封面!D13,封面!F13,封面!G13,封面!H13,封面!I13,封面!J13,封面!K13)

Sheet 无形-土地
A1: 返回索引页 | B1: 返回
A2: 无形资产—土地使用权评估明细表
A3: =CONCATENATE(封面!D9,封面!F9,封面!G9,封面!H9,封面!I9,封面!J9,封面!K9)
A4: =封面!D7&封面!F7 | Q4: 金额单位：人民币元
A5: 序号 | B5: 土地权证编号 | C5: 宗地名称 | D5: 土地位置 | E5: 取得日期 | F5: 用地性质 | G5: 准用年限 | H5: 开发程度 | I5: 面积(m2) | J5: 原始入账价值 | K5: 审计前账面值 | L5: 审计调整 | M5: 账面价值 | N5: 评估价值 | O5: 增减值 | P5: 增值率% | Q5: 备注 | R5: 证载权利人
O6: =IF(M6=0,"",(N6-M6)) | P6: =IF(M6=0,"",(N6-M6)/M6*100)
O7: =IF(M7=0,"",(N7-M7)) | P7: =IF(M7=0,"",(N7-M7)/M7*100)
O8: =IF(M8=0,"",(N8-M8)) | P8: =IF(M8=0,"",(N8-M8)/M8*100)
O9: =IF(M9=0,"",(N9-M9)) | P9: =IF(M9=0,"",(N9-M9)/M9*100)
O10: =IF(M10=0,"",(N10-M10)) | P10: =IF(M10=0,"",(N10-M10)/M10*100)
O11: =IF(M11=0,"",(N11-M11)) | P11: =IF(M11=0,"",(N11-M11)/M11*100)
O12: =IF(M12=0,"",(N12-M12)) | P12: =IF(M12=0,"",(N12-M12)/M12*100)
O13: =IF(M13=0,"",(N13-M13)) | P13: =IF(M13=0,"",(N13-M13)/M13*100)
O14: =IF(M14=0,"",(N14-M14)) | P14: =IF(M14=0,"",(N14-M14)/M14*100)
O15: =IF(M15=0,"",(N15-M15)) | P15: =IF(M15=0,"",(N15-M15)/M15*100)
O16: =IF(M16=0,"",(N16-M16)) | P16: =IF(M16=0,"",(N16-M16)/M16*100)
O17: =IF(M17=0,"",(N17-M17)) | P17: =IF(M17=0,"",(N17-M17)/M17*100)
... O25: =IF(M25=0,"",(N25-M25)) | P25: =IF(M25=0,"",(N25-M25)/M25*100)
O26: =IF(M26=0,"",(N26-M26))
A27: 合 计 | J27: =SUM(J6:J26) | K27: =SUM(K6:K26) | M27: =SUM(M6:M26) | N27: =SUM(N6:N26) | O27: =IF(M27=0,"",(N27-M27)) | P27: =IF(M27=0,"",(N27-M27)/M27*100)
A28: =封面!D11&封面!G11 | M28: ="评估人员："&封面!G28
A29: =CONCATENATE(封面!D13,封面!F13,封面!G13,封面!H13,封面!I13,封面!J13,封面!K13)

Sheet 无形-矿业权
A1: 返回索引页 | B1: 返回
A2: 无形资产—矿业权评估明细表
A3: =无形资产汇总!A3
A4: =封面!D7&封面!F7 | P4: 金额单位：人民币元
A5: 序号 | B5: 名称、种类（探矿权/采矿权） | C5: 勘查（采矿）许可证编号 | D5: 取得方式 | E5: 取得日期 | F5: 剩余有效年限 | G5: 勘查开发阶段 | H5: 核定（批准）生产规模 | I5: 原始入账价值 | J5: 审计前账面值 | K5: 审计调整 | L5: 账面价值 | M5: 评估价值 | N5: 增减值 | O5: 增值率% | P5: 备注
N6: =IF(L6=0,"",(M6-L6)) | O6: =IF(L6=0,"",(M6-L6)/L6*100)
N7: =IF(L7=0,"",(M7-L7)) | O7: =IF(L7=0,"",(M7-L7)/L7*100)
N8: =IF(L8=0,"",(M8-L8)) | O8: =IF(L8=0,"",(M8-L8)/L8*100)
N9: =IF(L9=0,"",(M9-L9)) | O9: =IF(L9=0,"",(M9-L9)/L9*100)
N10: =IF(L10=0,"",(M10-L10)) | O10: =IF(L10=0,"",(M10-L10)/L10*100)
N11: =IF(L11=0,"",(M11-L11)) | O11: =IF(L11=0,"",(M11-L11)/L11*100)
N12: =IF(L12=0,"",(M12-L12)) | O12: =IF(L12=0,"",(M12-L12)/L12*100)
N13: =IF(L13=0,"",(M13-L13)) | O13: =IF(L13=0,"",(M13-L13)/L13*100)
N14: =IF(L14=0,"",(M14-L14)) | O14: =IF(L14=0,"",(M14-L14)/L14*100)
N15: =IF(L15=0,"",(M15-L15)) | O15: =IF(L15=0,"",(M15-L15)/L15*100)
N16: =IF(L16=0,"",(M16-L16)) | O16: =IF(L16=0,"",(M16-L16)/L16*100)
N17: =IF(L17=0,"",(M17-L17)) | O17: =IF(L17=0,"",(M17-L17)/L17*100)
... N26: =IF(L26=0,"",(M26-L26)) | O26: =IF(L26=0,"",(M26-L26)/L26*100)
A27: 合 计 | J27: =SUM(J6:J26) | L27: =SUM(L6:L26) | M27: =SUM(M6:M26) | N27: =IF(L27=0,"",(M27-L27)) | O27: =IF(L27=0,"",(M27-L27)/L27*100)
A28: 被评估企业或产权持有单位填表人： | L28: ="评估人员："&封面!O29&" "&封面!O35
A29: =CONCATENATE(封面!D13,封面!F13,封面!G13,封面!H13,封面!I13,封面!J13,封面!K13)

Sheet 无形-其他
A1: 返回索引页 | B1: 返回
A2: 无形资产—其他无形资产评估明细表
A3: =CONCATENATE(封面!D9,封面!F9,封面!G9,封面!H9,封面!I9,封面!J9,封面!K9)
A4: =封面!D7&封面!F7 | O4: 金额单位：人民币元
A5: 序号 | B5: 内容或名称 | C5: 无形资产类型 | D5: 产权证号 | E5: 证载/实际取得日期 | F5: 法定/预计使用年限 | G5: 原始入账价值 | H5: 审计前账面值 | I5: 审计调整 | J5: 账面价值 | K5: 尚可使用 年限 | L5: 评估价值 | M5: 增减值 | N5: 增值率% | O5: 备注
M22: =IF(J22=0,"",(L22-J22))
A23: 合 计 | G23: =SUM(G6:G22) | H23: =SUM(H6:H22) | I23: =SUM(I6:I22) | J23: =SUM(J6:J22) | L23: =SUM(L6:L22) | M23: =IF(J23=0,"",(L23-J23)) | N23: =IF(J23=0,"",(L23-J23)/J23*100)
A24: =封面!D11&封面!G11 | J24: ="评估人员："&封面!G34
A25: =CONCATENATE(封面!D13,封面!F13,封面!G13,封面!H13,封面!I13,封面!J13,封面!K13)
L28: =L23/10000

Sheet Sheet2
A1: 序号 | B1: 内容或名称 | C1: 无形资产类型 | D1: 产权证号 | E1: 证载/实际取得日期 | F1: 备注
A2: 1
A3: 2
A4: 3
A5: 4
A6: 5
A7: 6
A8: 7
A9: 8
A10: 9
A11: 10
A12: 11
A13: 12
A14: 13

Sheet 开发支出
A1: 返回索引页 | B1: 返回
A2: 开发支出评估明细表
A3: =CONCATENATE(封面!D9,封面!F9,封面!G9,封面!H9,封面!I9,封面!J9,封面!K9)
A4: =封面!D7&封面!F7 | J4: 金额单位：人民币元
A5: 序号 | B5: 内容或名称 | C5: 发生日期 | D5: 审计前账面值 | E5: 审计调整 | F5: 账面价值 | G5: 评估价值 | H5: 增减值 | I5: 增值率% | J5: 备注
H6: =IF(F6=0,"",(G6-F6)/F6*100) | I6: =IF(F6=0,"",(G6-F6)/F6*100)
H7: =IF(F7=0,"",(G7-F7)/F7*100) | I7: =IF(F7=0,"",(G7-F7)/F7*100)
H8: =IF(F8=0,"",(G8-F8)/F8*100) | I8: =IF(F8=0,"",(G8-F8)/F8*100)
H9: =IF(F9=0,"",(G9-F9)/F9*100) | I9: =IF(F9=0,"",(G9-F9)/F9*100)
H10: =IF(F10=0,"",(G10-F10)/F10*100) | I10: =IF(F10=0,"",(G10-F10)/F10*100)
H11: =IF(F11=0,"",(G11-F11)/F11*100) | I11: =IF(F11=0,"",(G11-F11)/F11*100)
H12: =IF(F12=0,"",(G12-F12)/F12*100) | I12: =IF(F12=0,"",(G12-F12)/F12*100)
H13: =IF(F13=0,"",(G13-F13)/F13*100) | I13: =IF(F13=0,"",(G13-F13)/F13*100)
H14: =IF(F14=0,"",(G14-F14)/F14*100) | I14: =IF(F14=0,"",(G14-F14)/F14*100)
H15: =IF(F15=0,"",(G15-F15)/F15*100) | I15: =IF(F15=0,"",(G15-F15)/F15*100)
H16: =IF(F16=0,"",(G16-F16)/F16*100) | I16: =IF(F16=0,"",(G16-F16)/F16*100)
H17: =IF(F17=0,"",(G17-F17)/F17*100) | I17: =IF(F17=0,"",(G17-F17)/F17*100)
... H25: =IF(F25=0,"",(G25-F25)/F25*100) | I25: =IF(F25=0,"",(G25-F25)/F25*100)
H26: =IF(F26=0,"",(G26-F26)/F26*100)
A27: 合 计 | D27: =SUM(D6:D26) | F27: =SUM(F6:F26) | G27: =SUM(G6:G26) | H27: =IF(F27=0,"",(G27-F27)/F27*100) | I27: =IF(F27=0,"",(G27-F27)/F27*100)
A28: =封面!D11&封面!G11 | F28: ="评估人员："&封面!G34
A29: =CONCATENATE(封面!D13,封面!F13,封面!G13,封面!H13,封面!I13,封面!J13,封面!K13)

Sheet 商誉
A1: 返回索引页 | B1: 返回
A2: 商誉评估明细表
A3: =CONCATENATE(封面!D9,封面!F9,封面!G9,封面!H9,封面!I9,封面!J9,封面!K9)
A4: =封面!D7&封面!F7 | J4: 金额单位：人民币元
A5: 序号 | B5: 内容或名称 | C5: 取得日期 | D5: 审计前账面值 | E5: 审计调整 | F5: 账面价值 | G5: 评估价值 | H5: 增减值 | I5: 增值率% | J5: 备注
H6: =IF(F6=0,"",(G6-F6)) | I6: =IF(F6=0,"",(G6-F6)/F6*100)
H7: =IF(F7=0,"",(G7-F7)) | I7: =IF(F7=0,"",(G7-F7)/F7*100)
H8: =IF(F8=0,"",(G8-F8)) | I8: =IF(F8=0,"",(G8-F8)/F8*100)
H9: =IF(F9=0,"",(G9-F9)) | I9: =IF(F9=0,"",(G9-F9)/F9*100)
H10: =IF(F10=0,"",(G10-F10)) | I10: =IF(F10=0,"",(G10-F10)/F10*100)
H11: =IF(F11=0,"",(G11-F11)) | I11: =IF(F11=0,"",(G11-F11)/F11*100)
H12: =IF(F12=0,"",(G12-F12)) | I12: =IF(F12=0,"",(G12-F12)/F12*100)
H13: =IF(F13=0,"",(G13-F13)) | I13: =IF(F13=0,"",(G13-F13)/F13*100)
H14: =IF(F14=0,"",(G14-F14)) | I14: =IF(F14=0,"",(G14-F14)/F14*100)
H15: =IF(F15=0,"",(G15-F15)) | I15: =IF(F15=0,"",(G15-F15)/F15*100)
H16: =IF(F16=0,"",(G16-F16)) | I16: =IF(F16=0,"",(G16-F16)/F16*100)
H17: =IF(F17=0,"",(G17-F17)) | I17: =IF(F17=0,"",(G17-F17)/F17*100)
... H24: =IF(F24=0,"",(G24-F24)) | I24: =IF(F24=0,"",(G24-F24)/F24*100)
A25: 合 计 | D25: =SUM(D6:D24) | F25: =SUM(F6:F24) | G25: =SUM(G6:G24) | H25: =IF(F25=0,"",(G25-F25)) | I25: =IF(F25=0,"",(G25-F25)/F25*100)
A26: 减：商誉减值准备 | F26: =D26 | H26: =IF(F26=0,"",(G26-F26)) | I26: =IF(F26=0,"",(G26-F26)/F26*100)
A27: 净 额 | D27: =D25-D26 | F27: =F25-F26 | G27: =G25-G26 | H27: =IF(F27=0,"",(G27-F27)) | I27: =IF(F27=0,"",(G27-F27)/F27*100)
A28: =封面!D11&封面!G11 | G28: ="评估人员："&封面!G34
A29: =CONCATENATE(封面!D13,封面!F13,封面!G13,封面!H13,封面!I13,封面!J13,封面!K13)

Sheet 长期待摊费用
A1: 返回索引页 | B1: 返回
A2: 长期待摊费用评估明细表
A3: =CONCATENATE(封面!D9,封面!F9,封面!G9,封面!H9,封面!I9,封面!J9,封面!K9)
A4: =封面!D7&封面!F7 | M4: 金额单位：人民币元
A5: 序号 | B5: 费用名称或内容 | C5: 形成日期 | D5: 原始发生额 | E5: 预计摊 销月数 | F5: 审计前账面值 | G5: 审计调整 | H5: 账面价值 | I5: 尚存受 益月数 | J5: 评估价值 | K5: 增减值 | L5: 增值率% | M5: 备注
J6: =H6 | K6: =IF(H6=0,"",(J6-H6)) | L6: =IF(H6=0,"",(J6-H6)/H6*100)
K7: =IF(H7=0,"",(J7-H7)) | L7: =IF(H7=0,"",(J7-H7)/H7*100)
K8: =IF(H8=0,"",(J8-H8)) | L8: =IF(H8=0,"",(J8-H8)/H8*100)
K9: =IF(H9=0,"",(J9-H9)) | L9: =IF(H9=0,"",(J9-H9)/H9*100)
K10: =IF(H10=0,"",(J10-H10)) | L10: =IF(H10=0,"",(J10-H10)/H10*100)
K11: =IF(H11=0,"",(J11-H11)) | L11: =IF(H11=0,"",(J11-H11)/H11*100)
K12: =IF(H12=0,"",(J12-H12)) | L12: =IF(H12=0,"",(J12-H12)/H12*100)
K13: =IF(H13=0,"",(J13-H13)) | L13: =IF(H13=0,"",(J13-H13)/H13*100)
K14: =IF(H14=0,"",(J14-H14)) | L14: =IF(H14=0,"",(J14-H14)/H14*100)
K15: =IF(H15=0,"",(J15-H15)) | L15: =IF(H15=0,"",(J15-H15)/H15*100)
K16: =IF(H16=0,"",(J16-H16)) | L16: =IF(H16=0,"",(J16-H16)/H16*100)
K17: =IF(H17=0,"",(J17-H17)) | L17: =IF(H17=0,"",(J17-H17)/H17*100)
K18: =IF(H18=0,"",(J18-H18)) | L18: =IF(H18=0,"",(J18-H18)/H18*100)
... K25: =IF(H25=0,"",(J25-H25)) | L25: =IF(H25=0,"",(J25-H25)/H25*100)
K26: =IF(H26=0,"",(J26-H26))
A27: 合 计 | F27: =SUM(F6:F26) | H27: =SUM(H6:H26) | J27: =SUM(J6:J26) | K27: =IF(H27=0,"",(J27-H27)) | L27: =IF(H27=0,"",(J27-H27)/H27*100)
A28: =封面!D11&封面!G11 | H28: ="评估人员："&封面!G36
A29: =CONCATENATE(封面!D13,封面!F13,封面!G13,封面!H13,封面!I13,封面!J13,封面!K13)

Sheet 递延所得税资产
A1: 返回索引页 | B1: 返回
A2: 递延所得税资产评估明细表
A3: =CONCATENATE(封面!D9,封面!F9,封面!G9,封面!H9,封面!I9,封面!J9,封面!K9)
A4: =封面!D7&封面!F7 | H4: 金额单位：人民币元
A5: 序号 | B5: 内容或名称 | C5: 取得日期 | D5: 审计前账面值 | E5: 审计调整 | F5: 账面价值 | G5: 评估价值 | H5: 备注
A27: 合 计 | D27: =SUM(D6:D26) | F27: =SUM(F6:F26) | G27: =SUM(G6:G26)
A28: =封面!D11&封面!G11 | F28: ="评估人员："&封面!G36
A29: =CONCATENATE(封面!D13,封面!F13,封面!G13,封面!H13,封面!I13,封面!J13,封面!K13)

Sheet 其他非流动资产
A1: 返回索引页 | B1: 返回
A2: 其他非流动资产评估明细表
A3: =CONCATENATE(封面!D9,封面!F9,封面!G9,封面!H9,封面!I9,封面!J9,封面!K9)
A4: =封面!D7&封面!F7 | I4: 金额单位：人民币元
A5: 序号 | B5: 内容或名称 | C5: 取得日期 | D5: 审计前账面值 | E5: 审计调整 | F5: 账面价值 | G5: 评估价值 | H5: 增值率% | I5: 备注
H6: =IF(F6=0,"",(G6-F6)/F6*100)
H7: =IF(F7=0,"",(G7-F7)/F7*100)
H8: =IF(F8=0,"",(G8-F8)/F8*100)
H9: =IF(F9=0,"",(G9-F9)/F9*100)
H10: =IF(F10=0,"",(G10-F10)/F10*100)
H11: =IF(F11=0,"",(G11-F11)/F11*100)
H12: =IF(F12=0,"",(G12-F12)/F12*100)
H13: =IF(F13=0,"",(G13-F13)/F13*100)
H14: =IF(F14=0,"",(G14-F14)/F14*100)
H15: =IF(F15=0,"",(G15-F15)/F15*100)
H16: =IF(F16=0,"",(G16-F16)/F16*100)
H17: =IF(F17=0,"",(G17-F17)/F17*100)
... H25: =IF(F25=0,"",(G25-F25)/F25*100)
A27: 合 计 | D27: =SUM(D6:D26) | F27: =SUM(F6:F26) | G27: =SUM(G6:G26) | H27: =IF(F27=0,"",(G27-F27)/F27*100)
A28: =封面!D11&封面!G11 | G28: ="评估人员："&封面!G36
A29: =CONCATENATE(封面!D13,封面!F13,封面!G13,封面!H13,封面!I13,封面!J13,封面!K13)

Sheet 流动负债汇总
A1: 返回索引页 | B1: 返回
A2: 流动负债评估汇总表
A3: =CONCATENATE(封面!D9,封面!F9,封面!G9,封面!H9,封面!I9,封面!J9,封面!K9)
A4: =封面!D7&封面!F7 | G4: 金额单位：人民币元
A5: 编号 | B5: 科目名称 | C5: 审计前账面值 | D5: 账面价值 | E5: 评估价值 | F5: 增值额 | G5: 增值率%
A6: 5-1 | B6: 短期借款 | C6: =短期借款!H27 | D6: =短期借款!J27 | E6: =短期借款!L27 | F6: =E6-D6 | G6: =IF(D6=0,"",F6/D6*100)
A7: 5-2 | B7: 交易性金融负债 | C7: =交易性金融负债!E27 | D7: =交易性金融负债!G27 | E7: =交易性金融负债!H27 | F7: =E7-D7 | G7: =IF(D7=0,"",F7/D7*100)
A8: 5-3 | B8: 应付票据 | C8: =应付票据!F27 | D8: =应付票据!H27 | E8: =应付票据!I27 | F8: =E8-D8 | G8: =IF(D8=0,"",F8/D8*100)
A9: 5-4 | B9: 应付账款 | C9: =应付账款!E28 | D9: =应付账款!G28 | E9: =应付账款!H28 | F9: =E9-D9 | G9: =IF(D9=0,"",F9/D9*100)
A10: 5-5 | B10: 预收款项 | C10: =预收账款!E27 | D10: =预收账款!G27 | E10: =预收账款!H27 | F10: =E10-D10 | G10: =IF(D10=0,"",F10/D10*100)
A11: 5-6 | B11: 应付职工薪酬 | C11: =职工薪酬!D27 | D11: =职工薪酬!F27 | E11: =职工薪酬!G27 | F11: =E11-D11 | G11: =IF(D11=0,"",F11/D11*100)
A12: 5-7 | B12: 应交税费 | C12: =应交税费!E27 | D12: =应交税费!G27 | E12: =应交税费!H27 | F12: =E12-D12 | G12: =IF(D12=0,"",F12/D12*100)
A13: 5-8 | B13: 应付利息 | C13: =应付利息!G27 | D13: =应付利息!I27 | E13: =应付利息!J27 | F13: =E13-D13 | G13: =IF(D13=0,"",F13/D13*100)
A14: 5-9 | B14: 应付股利（应付利润） | C14: ='应付股利（利润）'!E27 | D14: ='应付股利（利润）'!G27 | E14: ='应付股利（利润）'!H27 | F14: =E14-D14 | G14: =IF(D14=0,"",F14/D14*100)
A15: 5-10 | B15: 其他应付款 | C15: =其他应付款!E51 | D15: =其他应付款!G51 | E15: =其他应付款!H51 | F15: =E15-D15 | G15: =IF(D15=0,"",F15/D15*100)
A16: 5-11 | B16: 一年内到期的非流动负债 | C16: =一年到期非流动负债!F27 | D16: =一年到期非流动负债!H27 | E16: =一年到期非流动负债!I27 | F16: =E16-D16 | G16: =IF(D16=0,"",F16/D16*100)
A17: 5-12 | B17: 其他流动负债 | C17: =其他流动负债!E27 | D17: =其他流动负债!G27 | E17: =其他流动负债!H27 | F17: =E17-D17 | G17: =IF(D17=0,"",F17/D17*100)
G18: =IF(D18=0,"",F18/D18*100)
G19: =IF(D19=0,"",F19/D19*100)
G22: =IF(D22=0,"",F22/D22*100)
G23: =IF(D23=0,"",F23/D23*100)
G24: =IF(D24=0,"",F24/D24*100)
G25: =IF(D25=0,"",F25/D25*100)
G26: =IF(D26=0,"",F26/D26*100)
A27: 9 | B27: 流动负债合计 | C27: =SUM(C6:C26) | D27: =SUM(D6:D26) | E27: =SUM(E6:E26) | F27: =SUM(F6:F26) | G27: =IF(D27=0,"",F27/D27*100)
A28: =封面!D11&封面!G11 | E28: ="评估人员："&封面!G38
A29: =CONCATENATE(封面!D13,封面!F13,封面!G13,封面!H13,封面!I13,封面!J13,封面!K13)

Sheet 短期借款
A1: 返回索引页 | B1: 返回
A2: 短期借款评估明细表
A3: =CONCATENATE(封面!D9,封面!F9,封面!G9,封面!H9,封面!I9,封面!J9,封面!K9)
A4: =封面!D7&封面!F7 | M4: 金额单位：人民币元
A5: 序号 | B5: 放款银行或机构名称 | C5: 发生日期 | D5: 到期日 | E5: 月利率% | F5: 币种 | G5: 外币金额 | H5: 审计前账面值 | I5: 审计调整 | J5: 账面价值 | K5: 外币基准日汇率 | L5: 评估价值 | M5: 备注
A27: 合 计 | H27: =SUM(H6:H26) | J27: =SUM(J6:J26) | L27: =SUM(L6:L26)
A28: =封面!D11&封面!G11 | J28: ="评估人员："&封面!G38
A29: =CONCATENATE(封面!D13,封面!F13,封面!G13,封面!H13,封面!I13,封面!J13,封面!K13)

Sheet 交易性金融负债
A1: 返回索引页 | B1: 返回
A2: 交易性金融负债评估明细表
A3: =CONCATENATE(封面!D9,封面!F9,封面!G9,封面!H9,封面!I9,封面!J9,封面!K9)
A4: =封面!D7&封面!F7 | I4: 金额单位：人民币元
A5: 序号 | B5: 户名（结算对象） | C5: 发生日期 | D5: 业务内容 | E5: 审计前账面值 | F5: 审计调整 | G5: 账面价值 | H5: 评估价值 | I5: 备注
A27: 合 计 | E27: =SUM(E6:E26) | G27: =SUM(G6:G26) | H27: =SUM(H6:H26)
A28: =封面!D11&封面!G11 | G28: ="评估人员："&封面!G38
A29: =CONCATENATE(封面!D13,封面!F13,封面!G13,封面!H13,封面!I13,封面!J13,封面!K13)

Sheet 应付票据
A1: 返回索引页 | B1: 返回
A2: 应付票据评估明细表
A3: =CONCATENATE(封面!D9,封面!F9,封面!G9,封面!H9,封面!I9,封面!J9,封面!K9)
A4: =封面!D7&封面!F7 | J4: 金额单位：人民币元
A5: 序号 | B5: 户名（结算对象） | C5: 发生日期 | D5: 到期日 | E5: 票面利率% | F5: 审计前账面值 | G5: 审计调整 | H5: 账面价值 | I5: 评估价值 | J5: 备注
A27: 合 计 | F27: =SUM(F6:F26) | H27: =SUM(H6:H26) | I27: =SUM(I6:I26)
A28: =封面!D11&封面!G11 | H28: ="评估人员："&封面!G38
A29: =CONCATENATE(封面!D13,封面!F13,封面!G13,封面!H13,封面!I13,封面!J13,封面!K13)

Sheet 应付账款
A1: 返回索引页 | B1: 返回
A2: 应付账款评估明细表
A3: =CONCATENATE(封面!D9,封面!F9,封面!G9,封面!H9,封面!I9,封面!J9,封面!K9)
A4: =封面!D7&封面!F7 | I4: 金额单位：人民币元
A5: 序号 | B5: 户名（结算对象） | C5: 发生日期 | D5: 业务内容 | E5: 审计前账面值 | F5: 审计调整 | G5: 账面价值 | H5: 评估价值 | I5: 备注
A6: 1 | H6: =G6
A7: 2 | H7: =G7
A8: 3 | H8: =G8
A9: 4 | H9: =G9
A10: 5 | H10: =G10
A11: 6 | H11: =G11
A12: 7 | H12: =G12
A13: 8 | H13: =G13
A14: 11 | H14: =G14
A15: 12 | H15: =G15
A16: 13 | H16: =G16
A17: 14 | H17: =G17
... A27: 28 | H27: =G27
A28: 合 计 | E28: =SUM(E6:E27) | G28: =SUM(G6:G27) | H28: =SUM(H6:H27)
A29: =封面!D11&封面!G11 | G29: ="评估人员："&封面!G38
A30: =CONCATENATE(封面!D13,封面!F13,封面!G13,封面!H13,封面!I13,封面!J13,封面!K13)

Sheet 预收账款
A1: 返回索引页 | B1: 返回
A2: 预收账款评估明细表
A3: =CONCATENATE(封面!D9,封面!F9,封面!G9,封面!H9,封面!I9,封面!J9,封面!K9)
A4: =封面!D7&封面!F7 | I4: 金额单位：人民币元
A5: 序号 | B5: 户名（结算对象） | C5: 发生日期 | D5: 业务内容 | E5: 审计前账面值 | F5: 审计调整 | G5: 账面价值 | H5: 评估价值 | I5: 备注
A27: 合 计 | E27: =SUM(E6:E26) | G27: =SUM(G6:G26) | H27: =SUM(H6:H26)
A28: =封面!D11&封面!G11 | G28: ="评估人员："&封面!G38
A29: =CONCATENATE(封面!D13,封面!F13,封面!G13,封面!H13,封面!I13,封面!J13,封面!K13)

Sheet 职工薪酬
A1: 返回索引页 | B1: 返回
A2: 应付职工薪酬评估明细表
A3: =CONCATENATE(封面!D9,封面!F9,封面!G9,封面!H9,封面!I9,封面!J9,封面!K9)
A4: =封面!D7&封面!F7 | H4: 金额单位：人民币元
A5: 序号 | B5: 结算内容 | C5: 发生日期 | D5: 审计前账面值 | E5: 审计调整 | F5: 账面价值 | G5: 评估价值 | H5: 备注
A6: 1 | G6: =F6
A7: 2 | G7: =F7
A8: 3 | G8: =F8
A27: 合 计 | D27: =SUM(D6:D26) | F27: =SUM(F6:F26) | G27: =SUM(G6:G26)
A28: =封面!D11&封面!G11 | F28: ="评估人员："&封面!G38
A29: =CONCATENATE(封面!D13,封面!F13,封面!G13,封面!H13,封面!I13,封面!J13,封面!K13)

Sheet 应交税费
A1: 返回索引页 | B1: 返回
A2: 应交税费评估明细表
A3: =CONCATENATE(封面!D9,封面!F9,封面!G9,封面!H9,封面!I9,封面!J9,封面!K9)
A4: =封面!D7&封面!F7 | I4: 金额单位：人民币元
A5: 序号 | B5: 征税机关 | C5: 发生日期 | D5: 税费种类 | E5: 审计前账面值 | F5: 审计调整 | G5: 账面价值 | H5: 评估价值 | I5: 备注
A6: 1 | H6: =G6
A7: 2 | H7: =G7
A8: 3 | H8: =G8
A9: 4 | H9: =G9
A10: 5 | H10: =G10
A11: 6 | H11: =G11
A12: 7 | H12: =G12
A27: 合 计 | E27: =SUM(E6:E26) | G27: =SUM(G6:G26) | H27: =SUM(H6:H26)
A28: =封面!D11&封面!G11 | G28: ="评估人员："&封面!G38
A29: =CONCATENATE(封面!D13,封面!F13,封面!G13,封面!H13,封面!I13,封面!J13,封面!K13)

Sheet 应付利息
A1: 返回索引页 | B1: 返回
A2: 应付利息评估明细表
A3: =CONCATENATE(封面!D9,封面!F9,封面!G9,封面!H9,封面!I9,封面!J9,封面!K9)
A4: =封面!D7&封面!F7 | L4: 金额单位：人民币元
A5: 序号 | B5: 户名（结算对象） | C5: 发生日期 | D5: 本金 | E5: 利息所属期间 | F5: 利息率% | G5: 审计前账面值 | H5: 审计调整 | I5: 账面价值 | J5: 评估价值 | K5: 增值率% | L5: 备注
K6: =IF(I6=0,"",(J6-I6)/I6*100)
K7: =IF(I7=0,"",(J7-I7)/I7*100)
K8: =IF(I8=0,"",(J8-I8)/I8*100)
K9: =IF(I9=0,"",(J9-I9)/I9*100)
K10: =IF(I10=0,"",(J10-I10)/I10*100)
K11: =IF(I11=0,"",(J11-I11)/I11*100)
K12: =IF(I12=0,"",(J12-I12)/I12*100)
K13: =IF(I13=0,"",(J13-I13)/I13*100)
K14: =IF(I14=0,"",(J14-I14)/I14*100)
K15: =IF(I15=0,"",(J15-I15)/I15*100)
K16: =IF(I16=0,"",(J16-I16)/I16*100)
K17: =IF(I17=0,"",(J17-I17)/I17*100)
... K25: =IF(I25=0,"",(J25-I25)/I25*100)
A27: 合 计 | D27: =SUM(D6:D26) | G27: =SUM(G6:G26) | I27: =SUM(I6:I26) | J27: =SUM(J6:J26) | K27: =IF(I27=0,"",(J27-I27)/I27*100)
A28: =封面!D11&封面!G11 | I28: ="评估人员："&封面!G20
A29: =CONCATENATE(封面!D13,封面!F13,封面!G13,封面!H13,封面!I13,封面!J13,封面!K13)

Sheet 应付股利（利润）
A1: 返回索引页 | B1: 返回
A2: 应付股利（应付利润）评估明细表
A3: =CONCATENATE(封面!D9,封面!F9,封面!G9,封面!H9,封面!I9,封面!J9,封面!K9)
A4: =封面!D7&封面!F7 | I4: 金额单位：人民币元
A5: 序号 | B5: 投资单位名称（股东） | C5: 发生日期 | D5: 利润所属期间 | E5: 审计前账面值 | F5: 审计调整 | G5: 账面价值 | H5: 评估价值 | I5: 备注
A27: 合 计 | E27: =SUM(E6:E26) | G27: =SUM(G6:G26) | H27: =SUM(H6:H26)
A28: =封面!D11&封面!G11 | G28: ="评估人员："&封面!G38
A29: =CONCATENATE(封面!D13,封面!F13,封面!G13,封面!H13,封面!I13,封面!J13,封面!K13)

Sheet 其他应付款
A1: 返回索引页 | B1: 返回
A2: 其他应付款评估明细表
A3: =CONCATENATE(封面!D9,封面!F9,封面!G9,封面!H9,封面!I9,封面!J9,封面!K9)
A4: =封面!D7&封面!F7 | I4: 金额单位：人民币元
A5: 序号 | B5: 户名（结算对象） | C5: 发生日期 | D5: 业务内容 | E5: 审计前账面值 | F5: 审计调整 | G5: 账面价值 | H5: 评估价值 | I5: 备注
A6: 1 | H6: =G6
A7: 2 | H7: =G7
A8: 3 | H8: =G8
A9: 4 | H9: =G9
A10: 5 | H10: =G10
A11: 6 | H11: =G11
A12: 7 | H12: =G12
A13: 8 | H13: =G13
A14: 9 | H14: =G14
A15: 10 | H15: =G15
A16: 11 | H16: =G16
A17: 12 | H17: =G17
... A50: 45 | H50: =G50
A51: 合 计 | E51: =SUM(E6:E50) | G51: =SUM(G6:G50) | H51: =SUM(H6:H50)
A52: =封面!D11&封面!G11 | G52: ="评估人员："&封面!G38
A53: =CONCATENATE(封面!D13,封面!F13,封面!G13,封面!H13,封面!I13,封面!J13,封面!K13)

Sheet 一年到期非流动负债
A1: 返回索引页 | B1: 返回
A2: 一年内到期的非流动负债评估明细表
A3: =CONCATENATE(封面!D9,封面!F9,封面!G9,封面!H9,封面!I9,封面!J9,封面!K9)
A4: =封面!D7&封面!F7 | J4: 金额单位：人民币元
A5: 序号 | B5: 结算项目 | C5: 发生日期 | D5: 到期日 | E5: 票面月利率% | F5: 审计前账面值 | G5: 审计调整 | H5: 账面价值 | I5: 评估价值 | J5: 备注
A27: 合 计 | F27: =SUM(F6:F26) | H27: =SUM(H6:H26) | I27: =SUM(I6:I26)
A28: =封面!D11&封面!G11 | H28: ="评估人员："&封面!G38
A29: =CONCATENATE(封面!D13,封面!F13,封面!G13,封面!H13,封面!I13,封面!J13,封面!K13)

Sheet 其他流动负债
A1: 返回索引页 | B1: 返回
A2: 其他流动负债评估明细表
A3: =CONCATENATE(封面!D9,封面!F9,封面!G9,封面!H9,封面!I9,封面!J9,封面!K9)
A4: =封面!D7&封面!F7 | I4: 金额单位：人民币元
A5: 序号 | B5: 户名（结算对象） | C5: 发生日期 | D5: 结算内容 | E5: 审计前账面值 | F5: 审计调整 | G5: 账面价值 | H5: 评估价值 | I5: 备注
A27: 合 计 | E27: =SUM(E6:E26) | G27: =SUM(G6:G26) | H27: =SUM(H6:H26)
A28: =封面!D11&封面!G11 | G28: ="评估人员："&封面!G38
A29: =CONCATENATE(封面!D13,封面!F13,封面!G13,封面!H13,封面!I13,封面!J13,封面!K13)

Sheet 非流动负债汇总 
A1: 返回索引页 | B1: 返回
A2: 非流动负债评估汇总表
A3: =CONCATENATE(封面!D9,封面!F9,封面!G9,封面!H9,封面!I9,封面!J9,封面!K9)
A4: =封面!D7&封面!F7 | G4: 金额单位：人民币元
A5: 编号 | B5: 科目名称 | C5: 审计前账面值 | D5: 账面价值 | E5: 评估价值 | F5: 增值额 | G5: 增值率%
A6: 6-1 | B6: 长期借款 | C6: =长期借款!H27 | D6: =长期借款!J27 | E6: =长期借款!L27 | F6: =E6-D6 | G6: =IF(D6=0,"",F6/D6*100)
A7: 6-2 | B7: 应付债券 | C7: =应付债券!G27 | D7: =应付债券!I27 | E7: =应付债券!J27 | F7: =E7-D7 | G7: =IF(D7=0,"",F7/D7*100)
A8: 6-3 | B8: 长期应付款 | C8: =长期应付款!G27 | D8: =长期应付款!K27 | E8: =长期应付款!L27 | F8: =E8-D8 | G8: =IF(D8=0,"",F8/D8*100)
A9: 6-4 | B9: 租赁负债 | D9: =租赁负债!G27 | E9: =租赁负债!H27 | F9: =E9-D9
A10: 6-5 | B10: 专项应付款 | C10: =专项应付款!D27 | D10: =专项应付款!F27 | E10: =专项应付款!G27 | F10: =E10-D10 | G10: =IF(D10=0,"",F10/D10*100)
A11: 6-6 | B11: 预计负债 | C11: =预计负债!E27 | D11: =预计负债!G27 | E11: =预计负债!H27 | F11: =E11-D11 | G11: =IF(D11=0,"",F11/D11*100)
A12: 6-7 | B12: 递延所得税负债 | C12: =递延所得税负债!D27 | D12: =递延所得税负债!F27 | E12: =递延所得税负债!G27 | F12: =E12-D12 | G12: =IF(D12=0,"",F12/D12*100)
A13: 6-8 | B13: 其他非流动负债 | C13: =其他非流动负债!E27 | D13: =其他非流动负债!G27 | E13: =其他非流动负债!H27 | F13: =E13-D13 | G13: =IF(D13=0,"",F13/D13*100)
A29: 10 | B29: 非流动负债合计 | C29: =SUM(C6:C28) | D29: =SUM(D6:D28) | E29: =SUM(E6:E28) | F29: =SUM(F6:F28) | G29: =IF(D29=0,"",F29/D29*100)
A30: =封面!D11&封面!G11 | E30: ="评估人员："&封面!G38
A31: =CONCATENATE(封面!D13,封面!F13,封面!G13,封面!H13,封面!I13,封面!J13,封面!K13)

Sheet 长期借款
A1: 返回索引页 | B1: 返回
A2: 长期借款评估明细表
A3: =CONCATENATE(封面!D9,封面!F9,封面!G9,封面!H9,封面!I9,封面!J9,封面!K9)
A4: =封面!D7&封面!F7 | M4: 金额单位：人民币元
A5: 序号 | B5: 放款银行或机构名称 | C5: 发生日期 | D5: 到期日 | E5: 月利率% | F5: 币种 | G5: 外币金额 | H5: 审计前账面值 | I5: 审计调整 | J5: 账面价值 | K5: 外币基准日汇率 | L5: 评估价值 | M5: 备注
A27: 合 计 | H27: =SUM(H6:H26) | J27: =SUM(J6:J26) | L27: =SUM(L6:L26)
A28: =封面!D11&封面!G11 | J28: ="评估人员："&封面!G38
A29: =CONCATENATE(封面!D13,封面!F13,封面!G13,封面!H13,封面!I13,封面!J13,封面!K13)

Sheet 应付债券
A1: 返回索引页 | B1: 返回
A2: 应付债券评估明细表
A3: =CONCATENATE(封面!D9,封面!F9,封面!G9,封面!H9,封面!I9,封面!J9,封面!K9)
A4: =封面!D7&封面!F7 | K4: 金额单位：人民币元
A5: 序号 | B5: 债券发行单位 | C5: 债券种类 | D5: 发生日期 | E5: 到期日 | F5: 票面利率% | G5: 审计前账面值 | H5: 审计调整 | I5: 账面价值 | J5: 评估价值 | K5: 备 注
A27: 合 计 | G27: =SUM(G6:G26) | I27: =SUM(I6:I26) | J27: =SUM(J6:J26)
A28: =封面!D11&封面!G11 | I28: ="评估人员："&封面!G38
A29: =CONCATENATE(封面!D13,封面!F13,封面!G13,封面!H13,封面!I13,封面!J13,封面!K13)

Sheet 长期应付款
A1: 返回索引页 | B1: 返回
A2: 长期应付款评估明细表
A3: =CONCATENATE(封面!D9,封面!F9,封面!G9,封面!H9,封面!I9,封面!J9,封面!K9)
A4: =封面!D7&封面!F7 | M4: 金额单位：人民币元
A5: 序号 | B5: 户名（结算对象） | C5: 发生日期 | D5: 业务内容 | E5: 审计前账面值 | H5: 审计调整 | I5: 账面价值 | L5: 评估价值 | M5: 备注
L7: =K7
A27: 合 计 | G27: =SUM(G7:G26) | K27: =SUM(K7:K26) | L27: =SUM(L7:L26)
A28: =封面!D11&封面!G11 | K28: ="评估人员："&封面!G38
A29: =CONCATENATE(封面!D13,封面!F13,封面!G13,封面!H13,封面!I13,封面!J13,封面!K13)

Sheet 专项应付款
A1: 返回索引页 | B1: 返回
A2: 专项应付款评估明细表
A3: =CONCATENATE(封面!D9,封面!F9,封面!G9,封面!H9,封面!I9,封面!J9,封面!K9)
A4: =封面!D7&封面!F7 | H4: 金额单位：人民币元
A5: 序号 | B5: 户名（或结算对象） | C5: 发生日期 | D5: 审计前账面值 | E5: 审计调整 | F5: 账面价值 | G5: 评估价值 | H5: 备 注
A27: 合 计 | D27: =SUM(D6:D26) | F27: =SUM(F6:F26) | G27: =SUM(G6:G26)
A28: =封面!D11&封面!G11 | F28: ="评估人员："&封面!G38
A29: =CONCATENATE(封面!D13,封面!F13,封面!G13,封面!H13,封面!I13,封面!J13,封面!K13)

Sheet 预计负债
A1: 返回索引页 | B1: 返回
A2: 预计负债评估明细表
A3: =CONCATENATE(封面!D9,封面!F9,封面!G9,封面!H9,封面!I9,封面!J9,封面!K9)
A4: =封面!D7&封面!F7 | I4: 金额单位：人民币元
A5: 序号 | B5: 户名（结算对象） | C5: 发生日期 | D5: 结算内容 | E5: 审计前账面值 | F5: 审计调整 | G5: 账面价值 | H5: 评估价值 | I5: 备注
A27: 合 计 | E27: =SUM(E6:E26) | G27: =SUM(G6:G26) | H27: =SUM(H6:H26)
A28: =封面!D11&封面!G11 | G28: ="评估人员："&封面!G38
A29: =CONCATENATE(封面!D13,封面!F13,封面!G13,封面!H13,封面!I13,封面!J13,封面!K13)

Sheet 租赁负债
A1: 返回索引页 | B1: 返回
A2: 租赁负债评估明细表
A3: =CONCATENATE(封面!D9,封面!F9,封面!G9,封面!H9,封面!I9,封面!J9,封面!K9)
A4: =封面!D7&封面!F7 | I4: 金额单位：人民币元
A5: 序号 | B5: 户名（结算对象） | C5: 发生日期 | D5: 结算内容 | E5: 审计前账面值 | F5: 审计调整 | G5: 账面价值 | H5: 评估价值 | I5: 备注
A27: 合 计 | E27: =SUM(E6:E26) | G27: =SUM(G6:G26) | H27: =SUM(H6:H26)
A28: =封面!D11&封面!G11 | G28: ="评估人员："&封面!G38
A29: =CONCATENATE(封面!D13,封面!F13,封面!G13,封面!H13,封面!I13,封面!J13,封面!K13)

Sheet 递延所得税负债
A1: 返回索引页 | B1: 返回
A2: 递延所得税负债评估明细表
A3: =CONCATENATE(封面!D9,封面!F9,封面!G9,封面!H9,封面!I9,封面!J9,封面!K9)
A4: =封面!D7&封面!F7 | H4: 金额单位：人民币元
A5: 序号 | B5: 内容 | C5: 发生日期 | D5: 审计前账面值 | E5: 审计调整 | F5: 账面价值 | G5: 评估价值 | H5: 备注
A27: 合 计 | D27: =SUM(D6:D26) | F27: =SUM(F6:F26) | G27: =SUM(G6:G26)
A28: =封面!D11&封面!G11 | F28: ="评估人员："&封面!G38
A29: =CONCATENATE(封面!D13,封面!F13,封面!G13,封面!H13,封面!I13,封面!J13,封面!K13)

Sheet 其他非流动负债
A1: 返回索引页 | B1: 返回
A2: 其他非流动负债评估明细表
A3: =CONCATENATE(封面!D9,封面!F9,封面!G9,封面!H9,封面!I9,封面!J9,封面!K9)
A4: =封面!D7&封面!F7 | I4: 金额单位：人民币元
A5: 序号 | B5: 户名（结算对象） | C5: 发生日期 | D5: 结算内容 | E5: 审计前账面值 | F5: 审计调整 | G5: 账面价值 | H5: 评估价值 | I5: 备注
A27: 合 计 | E27: =SUM(E6:E26) | G27: =SUM(G6:G26) | H27: =SUM(H6:H26)
A28: =封面!D11&封面!G11 | G28: ="评估人员："&封面!G38
A29: =CONCATENATE(封面!D13,封面!F13,封面!G13,封面!H13,封面!I13,封面!J13,封面!K13)

Sheet 00000000
